Workbook

Sheet Exposure
A1: Step 0:premium indexation
A3: Exposure measure
B6: Year | C6: Premium | E6: Number of risks | G6: Average premium | H6: Premium index | I6: indexed Premium
B7: 2016 | C7: 142145345 | E7: 124123 | G7: =$C7/$E7 -> 1145.1975 | H7: =$G7/$G$7*100 -> 100 | I7: =$C7*$H$18/$H7 -> 1.9165068e+08
B8: =B7+1 -> 2017 | C8: 143456190 | E8: 124487 | G8: =$C8/$E8 -> 1152.3789 | H8: =$G8/$G$7*100 -> 100.62709 | I8: =$C8*$H$18/$H8 -> 1.9221271e+08
B9: =B8+1 -> 2018 | C9: 1.4778857e+08 | E9: 125731.87 | G9: =$C9/$E9 -> 1175.4265 | H9: =$G9/$G$7*100 -> 102.63963 | I9: =$C9*$H$18/$H9 -> 1.9413484e+08
B10: =B9+1 -> 2019 | C10: 1.5526667e+08 | E10: 128246.51 | G10: =$C10/$E10 -> 1210.6893 | H10: =$G10/$G$7*100 -> 105.71882 | I10: =$C10*$H$18/$H10 -> 1.9801754e+08
B11: =B10+1 -> 2020 | C11: 1.6312316e+08 | E11: 132093.9 | G11: =$C11/$E11 -> 1234.903 | H11: =$G11/$G$7*100 -> 107.8332 | I11: =$C11*$H$18/$H11 -> 2.0395806e+08
B12: =B11+1 -> 2021 | C12: 1.6804948e+08 | E12: 134735.78 | G12: =$C12/$E12 -> 1247.2521 | H12: =$G12/$G$7*100 -> 108.91153 | I12: =$C12*$H$18/$H12 -> 2.0803722e+08
B13: =B12+1 -> 2022 | C13: 1.7655279e+08 | E13: 138777.85 | G13: =$C13/$E13 -> 1272.1971 | H13: =$G13/$G$7*100 -> 111.08976 | I13: =$C13*$H$18/$H13 -> 2.1427834e+08
B14: =B13+1 -> 2023 | C14: 1.801015e+08 | E14: 140165.63 | G14: =$C14/$E14 -> 1284.9191 | H14: =$G14/$G$7*100 -> 112.20066 | I14: =$C14*$H$18/$H14 -> 2.1642112e+08
B15: =B14+1 -> 2024 | C15: 1.8554056e+08 | E15: 141567.29 | G15: =$C15/$E15 -> 1310.6175 | H15: =$G15/$G$7*100 -> 114.44467 | I15: =$C15*$H$18/$H15 -> 2.1858534e+08
B16: =B15+1 -> 2025 | C16: 1.930364e+08 | E16: 144398.63 | G16: =$C16/$E16 -> 1336.8298 | H16: =$G16/$G$7*100 -> 116.73356 | I16: =$C16*$H$18/$H16 -> 2.2295704e+08
B17: =B16+1 -> 2026 | C17: 2.1446344e+08 | D17: Estimate | E17: 145842.62 | F17: Estimate | G17: =$C17/$E17 -> 1470.5128 | H17: =$G17/$G$7*100 -> 128.40692 | I17: =$C17*$H$18/$H17 -> 2.2518661e+08
B18: =B17+1 -> 2027 | C18: 2.2969034e+08 | D18: Estimate | E18: 148759.47 | F18: Estimate | G18: =$C18/$E18 -> 1544.0384 | H18: =$G18/$G$7*100 -> 134.82727 | I18: =$C18*$H$18/$H18 -> 2.2969034e+08
B23: Layer1 | C23: 6000000 | D23: XS | E23: 4000000
B24: Layer2 | C24: 20000000 | D24: XS | E24: 10000000
A26: Step 2:claims index
B28: Inflation + superimposed inflation
F29: SI
F30: 0.015
E31: Source : Statbel & Plan Bureau | H31: Stabel | I31: Historical CPI
B32: Accident year | C32: Claims Index | E32: CPI | F32: CPI+ SI | H32: Plan Bureau | I32: CPI forecast
B33: 2016 | C33: 100 | E33: 0.019736101 | F33: =$E33+$F$30 -> 0.034736101
B34: 2017 | C34: =$C33*(1+$F34) -> 103.62786 | E34: 0.02127859 | F34: =$E34+$F$30 -> 0.03627859
B35: 2018 | C35: =$C34*(1+$F35) -> 107.30875 | E35: 0.020520277 | F35: =$E35+$F$30 -> 0.035520277
B36: 2019 | C36: =$C35*(1+$F36) -> 110.46523 | E36: 0.014414897 | F36: =$E36+$F$30 -> 0.029414897
B37: 2020 | C37: =$C36*(1+$F37) -> 112.94114 | E37: 0.0074135669 | F37: =$E37+$F$30 -> 0.022413567
B38: =2021 -> 2021 | C38: =$C37*(1+$F38) -> 117.39198 | E38: 0.024408451 | F38: =$E38+$F$30 -> 0.039408451
B39: =B38+1 -> 2022 | C39: =$C38*(1+$F39) -> 130.39822 | E39: 0.09579327 | F39: =$E39+$F$30 -> 0.11079327
B40: =B39+1 -> 2023 | C40: =$C39*(1+$F40) -> 137.71902 | E40: 0.041141822 | F40: =$E40+$F$30 -> 0.056141822
B41: =B40+1 -> 2024 | C41: =$C40*(1+$F41) -> 144.11485 | E41: 0.031441217 | F41: =$E41+$F$30 -> 0.046441217
B42: =B41+1 -> 2025 | C42: =$C41*(1+$F42) -> 149.83756 | E42: 0.024709355 | F42: =$E42+$F$30 -> 0.039709355
B43: =B42+1 -> 2026 | C43: =$C42*(1+$F43) -> 155.15598 | E43: 0.020494583 | F43: =$E43+$F$30 -> 0.035494583
B44: =B43+1 -> 2027 | C44: =$C43*(1+$F44) -> 160.58644 | E44: 0.02 | F44: =E44+$F$30 -> 0.035
B45: =B44+1 -> 2028 | C45: =$C44*(1+$F45) -> 165.8858 | E45: 0.018 | F45: =E45+$F$30 -> 0.033
B46: =B45+1 -> 2029 | C46: =$C45*(1+$F46) -> 171.36003 | E46: 0.018 | F46: =E46+$F$30 -> 0.033
B47: =B46+1 -> 2030 | C47: =$C46*(1+$F47) -> 177.01491 | E47: 0.018 | F47: =E47+$F$30 -> 0.033
B48: =B47+1 -> 2031 | C48: =$C47*(1+$F48) -> 182.8564 | E48: 0.018 | F48: =E48+$F$30 -> 0.033
B49: =B48+1 -> 2032 | C49: =$C48*(1+$F49) -> 188.89066 | E49: 0.018 | F49: =E49+$F$30 -> 0.033
B50: 2033 | C50: =$C49*(1+$F50) -> 195.12405 | E50: 0.018 | F50: =E50+$F$30 -> 0.033
B51: 2034 | C51: =$C50*(1+$F51) -> 201.56315 | E51: 0.018 | F51: =E51+$F$30 -> 0.033
B52: 2035 | C52: =$C51*(1+$F52) -> 208.21473 | E52: 0.018 | F52: =E52+$F$30 -> 0.033
B53: 2036 | C53: =$C52*(1+$F53) -> 215.08582 | E53: 0.018 | F53: =E53+$F$30 -> 0.033

Sheet Cum. payments
A1: 42374 | B1: 1075.2577 | C1: 178338.24 | D1: 178725.72 | E1: 193644.1 | F1: 407131.62 | G1: 407204.68 | H1: 446327.88 | I1: 450203.64 | J1: 464546.44 | K1: 464581.88 | N1: Paiement incremental | P1: 1 | Q1: 2 | R1: 3 | S1: 4 | T1: 5 | U1: 6 | V1: 7 | W1: 8 | X1: 9 | Y1: 10 | AA1: Indexed Incremental | AC1: 1 | AD1: 2 | AE1: 3 | AF1: 4 | AG1: 5 | AH1: 6 | AI1: 7 | AJ1: 8 | AK1: 9 | AL1: 10 | AY1: Origine | AZ1: 1 | BA1: 2 | BB1: 3 | BC1: 4 | BD1: 5 | BE1: 6 | BF1: 7 | BG1: 8 | BH1: 9 | BI1: 10 | BN1: Destination | BO1: 1 | BP1: 2 | BQ1: 3 | BR1: 4 | BS1: 5 | BT1: 6 | BU1: 7 | BV1: 8 | BW1: 9 | BX1: 10
A2: 42415 | B2: 133391.11 | C2: 254564.44 | D2: 511692.04 | E2: 809383.33 | F2: 1017876.8 | G2: 1018292.4 | H2: 1059163.7 | I2: 1073359.4 | J2: 1073779.3 | K2: 1073830.1 | O2: =YEAR($A1) -> 2016 | P2: =$B1 -> 1075.2577 | Q2: =C1-B1 -> 177262.98 | R2: =D1-C1 -> 387.48247 | S2: =E1-D1 -> 14918.38 | T2: =F1-E1 -> 213487.52 | U2: =G1-F1 -> 73.059712 | V2: =H1-G1 -> 39123.201 | W2: =I1-H1 -> 3875.7651 | X2: =J1-I1 -> 14342.796 | Y2: =K1-J1 -> 35.44499 | AA2: =P2*(Exposure!C44/Exposure!C33) -> 1726.7181 | AB2: =$O2 -> 2016 | AC2: =AA2 -> 1726.7181 | AD2: =Q2*VLOOKUP(BP2,Exposure!$B$33:$C$53,2,FALSE)/VLOOKUP(BA2,Exposure!$B$33:$C$53,2,FALSE) -> 283759.71 | AE2: =R2*VLOOKUP(BQ2,Exposure!$B$33:$C$53,2,FALSE)/VLOOKUP(BB2,Exposure!$B$33:$C$53,2,FALSE) -> 618.76602 | AF2: =S2*VLOOKUP(BR2,Exposure!$B$33:$C$53,2,FALSE)/VLOOKUP(BC2,Exposure!$B$33:$C$53,2,FALSE) -> 23905.946 | AG2: =T2*VLOOKUP(BS2,Exposure!$B$33:$C$53,2,FALSE)/VLOOKUP(BD2,Exposure!$B$33:$C$53,2,FALSE) -> 345645.15 | AH2: =U2*VLOOKUP(BT2,Exposure!$B$33:$C$53,2,FALSE)/VLOOKUP(BE2,Exposure!$B$33:$C$53,2,FALSE) -> 117.55741 | AI2: =V2*VLOOKUP(BU2,Exposure!$B$33:$C$53,2,FALSE)/VLOOKUP(BF2,Exposure!$B$33:$C$53,2,FALSE) -> 58542.804 | AJ2: =W2*VLOOKUP(BV2,Exposure!$B$33:$C$53,2,FALSE)/VLOOKUP(BG2,Exposure!$B$33:$C$53,2,FALSE) -> 5672.5021 | AK2: =X2*VLOOKUP(BW2,Exposure!$B$33:$C$53,2,FALSE)/VLOOKUP(BH2,Exposure!$B$33:$C$53,2,FALSE) -> 20722.232 | AL2: =Y2*VLOOKUP(BX2,Exposure!$B$33:$C$53,2,FALSE)/VLOOKUP(BI2,Exposure!$B$33:$C$53,2,FALSE) -> 50.879863 | AZ2: =$O2 -> 2016 | BA2: =$AZ2+BA$1-1 -> 2017 | BB2: =$AZ2+BB$1-1 -> 2018 | BC2: =$AZ2+BC$1-1 -> 2019 | BD2: =$AZ2+BD$1-1 -> 2020 | BE2: =$AZ2+BE$1-1 -> 2021 | BF2: =$AZ2+BF$1-1 -> 2022 | BG2: =$AZ2+BG$1-1 -> 2023 | BH2: =$AZ2+BH$1-1 -> 2024 | BI2: =$AZ2+BI$1-1 -> 2025 | BO2: 2027 | BP2: =$BO2+BP$1-1 -> 2028 | BQ2: =$BO2+BQ$1-1 -> 2029 | BR2: =$BO2+BR$1-1 -> 2030 | BS2: =$BO2+BS$1-1 -> 2031 | BT2: =$BO2+BT$1-1 -> 2032 | BU2: =$BO2+BU$1-1 -> 2033 | BV2: =$BO2+BV$1-1 -> 2034 | BW2: =$BO2+BW$1-1 -> 2035 | BX2: =$BO2+BX$1-1 -> 2036
A3: 42427 | B3: 895.77971 | C3: 22122.991 | D3: 44450.822 | E3: 539532.64 | F3: 548998.53 | G3: 553903.94 | H3: 553908.13 | I3: 564465.28 | J3: 571130.48 | K3: 574135.6 | O3: =YEAR($A2) -> 2016 | P3: =$B2 -> 133391.11 | Q3: =C2-B2 -> 121173.34 | R3: =D2-C2 -> 257127.6 | S3: =E2-D2 -> 297691.28 | T3: =F2-E2 -> 208493.43 | U3: =G2-F2 -> 415.66153 | V3: =H2-G2 -> 40871.32 | W3: =I2-H2 -> 14195.682 | X3: =J2-I2 -> 419.83501 | Y3: =K2-J2 -> 50.812493 | AB3: =$O3 -> 2016 | AC3: =P3*VLOOKUP(BO3,Exposure!$B$33:$C$53,2,FALSE)/VLOOKUP(AZ3,Exposure!$B$33:$C$53,2,FALSE) -> 214208.04 | AD3: =Q3*VLOOKUP(BP3,Exposure!$B$33:$C$53,2,FALSE)/VLOOKUP(BA3,Exposure!$B$33:$C$53,2,FALSE) -> 193972.31 | AE3: =R3*VLOOKUP(BQ3,Exposure!$B$33:$C$53,2,FALSE)/VLOOKUP(BB3,Exposure!$B$33:$C$53,2,FALSE) -> 410603.92 | AF3: =S3*VLOOKUP(BR3,Exposure!$B$33:$C$53,2,FALSE)/VLOOKUP(BC3,Exposure!$B$33:$C$53,2,FALSE) -> 477035.15 | AG3: =T3*VLOOKUP(BS3,Exposure!$B$33:$C$53,2,FALSE)/VLOOKUP(BD3,Exposure!$B$33:$C$53,2,FALSE) -> 337559.52 | AH3: =U3*VLOOKUP(BT3,Exposure!$B$33:$C$53,2,FALSE)/VLOOKUP(BE3,Exposure!$B$33:$C$53,2,FALSE) -> 668.82407 | AI3: =V3*VLOOKUP(BU3,Exposure!$B$33:$C$53,2,FALSE)/VLOOKUP(BF3,Exposure!$B$33:$C$53,2,FALSE) -> 61158.637 | AJ3: =W3*VLOOKUP(BV3,Exposure!$B$33:$C$53,2,FALSE)/VLOOKUP(BG3,Exposure!$B$33:$C$53,2,FALSE) -> 20776.553 | ... AL3: =Y3*VLOOKUP(BX3,Exposure!$B$33:$C$53,2,FALSE)/VLOOKUP(BI3,Exposure!$B$33:$C$53,2,FALSE) -> 72.939298 | AZ3: =$O3 -> 2016 | BA3: =$AZ3+BA$1-1 -> 2017 | BB3: =$AZ3+BB$1-1 -> 2018 | BC3: =$AZ3+BC$1-1 -> 2019 | BD3: =$AZ3+BD$1-1 -> 2020 | BE3: =$AZ3+BE$1-1 -> 2021 | BF3: =$AZ3+BF$1-1 -> 2022 | BG3: =$AZ3+BG$1-1 -> 2023 | BH3: =$AZ3+BH$1-1 -> 2024 | BI3: =$AZ3+BI$1-1 -> 2025 | BO3: 2027 | BP3: =$BO3+BP$1-1 -> 2028 | BQ3: =$BO3+BQ$1-1 -> 2029 | BR3: =$BO3+BR$1-1 -> 2030 | BS3: =$BO3+BS$1-1 -> 2031 | BT3: =$BO3+BT$1-1 -> 2032 | BU3: =$BO3+BU$1-1 -> 2033 | BV3: =$BO3+BV$1-1 -> 2034 | BW3: =$BO3+BW$1-1 -> 2035 | BX3: =$BO3+BX$1-1 -> 2036
A4: 42443 | B4: 39582.689 | C4: 807040.04 | D4: 2147508.1 | E4: 2306274.5 | F4: 2366505.9 | G4: 2505548.1 | H4: 2537192.5 | I4: 2539172.9 | J4: 2658962.7 | K4: 2663885.8 | O4: =YEAR($A3) -> 2016 | P4: =$B3 -> 895.77971 | Q4: =C3-B3 -> 21227.211 | R4: =D3-C3 -> 22327.832 | S4: =E3-D3 -> 495081.81 | T4: =F3-E3 -> 9465.8963 | U4: =G3-F3 -> 4905.4035 | V4: =H3-G3 -> 4.1962054 | W4: =I3-H3 -> 10557.146 | X4: =J3-I3 -> 6665.2014 | Y4: =K3-J3 -> 3005.1193 | AB4: =$O4 -> 2016 | AC4: =P4*VLOOKUP(BO4,Exposure!$B$33:$C$53,2,FALSE)/VLOOKUP(AZ4,Exposure!$B$33:$C$53,2,FALSE) -> 1438.5008 | AD4: =Q4*VLOOKUP(BP4,Exposure!$B$33:$C$53,2,FALSE)/VLOOKUP(BA4,Exposure!$B$33:$C$53,2,FALSE) -> 33980.175 | AE4: =R4*VLOOKUP(BQ4,Exposure!$B$33:$C$53,2,FALSE)/VLOOKUP(BB4,Exposure!$B$33:$C$53,2,FALSE) -> 35655.041 | AF4: =S4*VLOOKUP(BR4,Exposure!$B$33:$C$53,2,FALSE)/VLOOKUP(BC4,Exposure!$B$33:$C$53,2,FALSE) -> 793343.44 | AG4: =T4*VLOOKUP(BS4,Exposure!$B$33:$C$53,2,FALSE)/VLOOKUP(BD4,Exposure!$B$33:$C$53,2,FALSE) -> 15325.679 | AH4: =U4*VLOOKUP(BT4,Exposure!$B$33:$C$53,2,FALSE)/VLOOKUP(BE4,Exposure!$B$33:$C$53,2,FALSE) -> 7893.0852 | AI4: =V4*VLOOKUP(BU4,Exposure!$B$33:$C$53,2,FALSE)/VLOOKUP(BF4,Exposure!$B$33:$C$53,2,FALSE) -> 6.2790781 | AJ4: =W4*VLOOKUP(BV4,Exposure!$B$33:$C$53,2,FALSE)/VLOOKUP(BG4,Exposure!$B$33:$C$53,2,FALSE) -> 15451.254 | ... AL4: =Y4*VLOOKUP(BX4,Exposure!$B$33:$C$53,2,FALSE)/VLOOKUP(BI4,Exposure!$B$33:$C$53,2,FALSE) -> 4313.7283 | AZ4: =$O4 -> 2016 | BA4: =$AZ4+BA$1-1 -> 2017 | BB4: =$AZ4+BB$1-1 -> 2018 | BC4: =$AZ4+BC$1-1 -> 2019 | BD4: =$AZ4+BD$1-1 -> 2020 | BE4: =$AZ4+BE$1-1 -> 2021 | BF4: =$AZ4+BF$1-1 -> 2022 | BG4: =$AZ4+BG$1-1 -> 2023 | BH4: =$AZ4+BH$1-1 -> 2024 | BI4: =$AZ4+BI$1-1 -> 2025 | BO4: 2027 | BP4: =$BO4+BP$1-1 -> 2028 | BQ4: =$BO4+BQ$1-1 -> 2029 | BR4: =$BO4+BR$1-1 -> 2030 | BS4: =$BO4+BS$1-1 -> 2031 | BT4: =$BO4+BT$1-1 -> 2032 | BU4: =$BO4+BU$1-1 -> 2033 | BV4: =$BO4+BV$1-1 -> 2034 | BW4: =$BO4+BW$1-1 -> 2035 | BX4: =$BO4+BX$1-1 -> 2036
A5: 42500 | B5: 31450.465 | C5: 44049.75 | D5: 408949.07 | E5: 414693.51 | F5: 428592.54 | G5: 942353.73 | H5: 949031.56 | I5: 949377.72 | J5: 950321.2 | K5: 952171.9 | O5: =YEAR($A4) -> 2016 | P5: =$B4 -> 39582.689 | Q5: =C4-B4 -> 767457.36 | R5: =D4-C4 -> 1340468 | S5: =E4-D4 -> 158766.46 | T5: =F4-E4 -> 60231.336 | U5: =G4-F4 -> 139042.21 | V5: =H4-G4 -> 31644.399 | W5: =I4-H4 -> 1980.4173 | X5: =J4-I4 -> 119789.84 | Y5: =K4-J4 -> 4923.0747 | AB5: =$O5 -> 2016 | AC5: =P5*VLOOKUP(BO5,Exposure!$B$33:$C$53,2,FALSE)/VLOOKUP(AZ5,Exposure!$B$33:$C$53,2,FALSE) -> 63564.432 | AD5: =Q5*VLOOKUP(BP5,Exposure!$B$33:$C$53,2,FALSE)/VLOOKUP(BA5,Exposure!$B$33:$C$53,2,FALSE) -> 1228533.3 | AE5: =R5*VLOOKUP(BQ5,Exposure!$B$33:$C$53,2,FALSE)/VLOOKUP(BB5,Exposure!$B$33:$C$53,2,FALSE) -> 2140577 | AF5: =S5*VLOOKUP(BR5,Exposure!$B$33:$C$53,2,FALSE)/VLOOKUP(BC5,Exposure!$B$33:$C$53,2,FALSE) -> 254415.18 | AG5: =T5*VLOOKUP(BS5,Exposure!$B$33:$C$53,2,FALSE)/VLOOKUP(BD5,Exposure!$B$33:$C$53,2,FALSE) -> 97517.033 | AH5: =U5*VLOOKUP(BT5,Exposure!$B$33:$C$53,2,FALSE)/VLOOKUP(BE5,Exposure!$B$33:$C$53,2,FALSE) -> 223727.16 | AI5: =V5*VLOOKUP(BU5,Exposure!$B$33:$C$53,2,FALSE)/VLOOKUP(BF5,Exposure!$B$33:$C$53,2,FALSE) -> 47351.745 | AJ5: =W5*VLOOKUP(BV5,Exposure!$B$33:$C$53,2,FALSE)/VLOOKUP(BG5,Exposure!$B$33:$C$53,2,FALSE) -> 2898.5042 | ... AL5: =Y5*VLOOKUP(BX5,Exposure!$B$33:$C$53,2,FALSE)/VLOOKUP(BI5,Exposure!$B$33:$C$53,2,FALSE) -> 7066.8765 | AZ5: =$O5 -> 2016 | BA5: =$AZ5+BA$1-1 -> 2017 | BB5: =$AZ5+BB$1-1 -> 2018 | BC5: =$AZ5+BC$1-1 -> 2019 | BD5: =$AZ5+BD$1-1 -> 2020 | BE5: =$AZ5+BE$1-1 -> 2021 | BF5: =$AZ5+BF$1-1 -> 2022 | BG5: =$AZ5+BG$1-1 -> 2023 | BH5: =$AZ5+BH$1-1 -> 2024 | BI5: =$AZ5+BI$1-1 -> 2025 | BO5: 2027 | BP5: =$BO5+BP$1-1 -> 2028 | BQ5: =$BO5+BQ$1-1 -> 2029 | BR5: =$BO5+BR$1-1 -> 2030 | BS5: =$BO5+BS$1-1 -> 2031 | BT5: =$BO5+BT$1-1 -> 2032 | BU5: =$BO5+BU$1-1 -> 2033 | BV5: =$BO5+BV$1-1 -> 2034 | BW5: =$BO5+BW$1-1 -> 2035 | BX5: =$BO5+BX$1-1 -> 2036
A6: 42513 | B6: 227513.45 | C6: 328297.69 | D6: 351684.06 | E6: 521237.26 | F6: 1849971.6 | G6: 1876628.4 | H6: 1877682.2 | I6: 1877698.8 | J6: 1877715.1 | K6: 1877715.1 | O6: =YEAR($A5) -> 2016 | P6: =$B5 -> 31450.465 | Q6: =C5-B5 -> 12599.285 | R6: =D5-C5 -> 364899.32 | S6: =E5-D5 -> 5744.4408 | T6: =F5-E5 -> 13899.022 | U6: =G5-F5 -> 513761.19 | V6: =H5-G5 -> 6677.8279 | W6: =I5-H5 -> 346.16058 | X6: =J5-I5 -> 943.48209 | Y6: =K5-J5 -> 1850.7003 | AB6: =$O6 -> 2016 | AC6: =P6*VLOOKUP(BO6,Exposure!$B$33:$C$53,2,FALSE)/VLOOKUP(AZ6,Exposure!$B$33:$C$53,2,FALSE) -> 50505.183 | AD6: =Q6*VLOOKUP(BP6,Exposure!$B$33:$C$53,2,FALSE)/VLOOKUP(BA6,Exposure!$B$33:$C$53,2,FALSE) -> 20168.731 | AE6: =R6*VLOOKUP(BQ6,Exposure!$B$33:$C$53,2,FALSE)/VLOOKUP(BB6,Exposure!$B$33:$C$53,2,FALSE) -> 582703.26 | AF6: =S6*VLOOKUP(BR6,Exposure!$B$33:$C$53,2,FALSE)/VLOOKUP(BC6,Exposure!$B$33:$C$53,2,FALSE) -> 9205.1743 | AG6: =T6*VLOOKUP(BS6,Exposure!$B$33:$C$53,2,FALSE)/VLOOKUP(BD6,Exposure!$B$33:$C$53,2,FALSE) -> 22503.094 | AH6: =U6*VLOOKUP(BT6,Exposure!$B$33:$C$53,2,FALSE)/VLOOKUP(BE6,Exposure!$B$33:$C$53,2,FALSE) -> 826672.24 | AI6: =V6*VLOOKUP(BU6,Exposure!$B$33:$C$53,2,FALSE)/VLOOKUP(BF6,Exposure!$B$33:$C$53,2,FALSE) -> 9992.5048 | AJ6: =W6*VLOOKUP(BV6,Exposure!$B$33:$C$53,2,FALSE)/VLOOKUP(BG6,Exposure!$B$33:$C$53,2,FALSE) -> 506.63458 | ... AL6: =Y6*VLOOKUP(BX6,Exposure!$B$33:$C$53,2,FALSE)/VLOOKUP(BI6,Exposure!$B$33:$C$53,2,FALSE) -> 2656.6061 | AZ6: =$O6 -> 2016 | BA6: =$AZ6+BA$1-1 -> 2017 | BB6: =$AZ6+BB$1-1 -> 2018 | BC6: =$AZ6+BC$1-1 -> 2019 | BD6: =$AZ6+BD$1-1 -> 2020 | BE6: =$AZ6+BE$1-1 -> 2021 | BF6: =$AZ6+BF$1-1 -> 2022 | BG6: =$AZ6+BG$1-1 -> 2023 | BH6: =$AZ6+BH$1-1 -> 2024 | BI6: =$AZ6+BI$1-1 -> 2025 | BO6: 2027 | BP6: =$BO6+BP$1-1 -> 2028 | BQ6: =$BO6+BQ$1-1 -> 2029 | BR6: =$BO6+BR$1-1 -> 2030 | BS6: =$BO6+BS$1-1 -> 2031 | BT6: =$BO6+BT$1-1 -> 2032 | BU6: =$BO6+BU$1-1 -> 2033 | BV6: =$BO6+BV$1-1 -> 2034 | BW6: =$BO6+BW$1-1 -> 2035 | BX6: =$BO6+BX$1-1 -> 2036
A7: 42516 | B7: 162919.32 | C7: 4294009.9 | D7: 4413502.1 | E7: 6709541.2 | F7: 6886454.5 | G7: 7344043.1 | H7: 8021732.7 | I7: 8035665.5 | J7: 8044842.8 | K7: 8049749.9 | O7: =YEAR($A6) -> 2016 | P7: =$B6 -> 227513.45 | Q7: =C6-B6 -> 100784.24 | R7: =D6-C6 -> 23386.368 | S7: =E6-D6 -> 169553.2 | T7: =F6-E6 -> 1328734.3 | U7: =G6-F6 -> 26656.775 | V7: =H6-G6 -> 1053.8106 | W7: =I6-H6 -> 16.613752 | X7: =J6-I6 -> 16.280591 | Y7: =K6-J6 -> 0.04388575 | AB7: =$O7 -> 2016 | AC7: =P7*VLOOKUP(BO7,Exposure!$B$33:$C$53,2,FALSE)/VLOOKUP(AZ7,Exposure!$B$33:$C$53,2,FALSE) -> 365355.76 | AD7: =Q7*VLOOKUP(BP7,Exposure!$B$33:$C$53,2,FALSE)/VLOOKUP(BA7,Exposure!$B$33:$C$53,2,FALSE) -> 161333.78 | AE7: =R7*VLOOKUP(BQ7,Exposure!$B$33:$C$53,2,FALSE)/VLOOKUP(BB7,Exposure!$B$33:$C$53,2,FALSE) -> 37345.405 | AF7: =S7*VLOOKUP(BR7,Exposure!$B$33:$C$53,2,FALSE)/VLOOKUP(BC7,Exposure!$B$33:$C$53,2,FALSE) -> 271700.38 | AG7: =T7*VLOOKUP(BS7,Exposure!$B$33:$C$53,2,FALSE)/VLOOKUP(BD7,Exposure!$B$33:$C$53,2,FALSE) -> 2151276 | AH7: =U7*VLOOKUP(BT7,Exposure!$B$33:$C$53,2,FALSE)/VLOOKUP(BE7,Exposure!$B$33:$C$53,2,FALSE) -> 42892.333 | AI7: =V7*VLOOKUP(BU7,Exposure!$B$33:$C$53,2,FALSE)/VLOOKUP(BF7,Exposure!$B$33:$C$53,2,FALSE) -> 1576.8912 | AJ7: =W7*VLOOKUP(BV7,Exposure!$B$33:$C$53,2,FALSE)/VLOOKUP(BG7,Exposure!$B$33:$C$53,2,FALSE) -> 24.315598 | ... AL7: =Y7*VLOOKUP(BX7,Exposure!$B$33:$C$53,2,FALSE)/VLOOKUP(BI7,Exposure!$B$33:$C$53,2,FALSE) -> 0.062996235 | AZ7: =$O7 -> 2016 | BA7: =$AZ7+BA$1-1 -> 2017 | BB7: =$AZ7+BB$1-1 -> 2018 | BC7: =$AZ7+BC$1-1 -> 2019 | BD7: =$AZ7+BD$1-1 -> 2020 | BE7: =$AZ7+BE$1-1 -> 2021 | BF7: =$AZ7+BF$1-1 -> 2022 | BG7: =$AZ7+BG$1-1 -> 2023 | BH7: =$AZ7+BH$1-1 -> 2024 | BI7: =$AZ7+BI$1-1 -> 2025 | BO7: 2027 | BP7: =$BO7+BP$1-1 -> 2028 | BQ7: =$BO7+BQ$1-1 -> 2029 | BR7: =$BO7+BR$1-1 -> 2030 | BS7: =$BO7+BS$1-1 -> 2031 | BT7: =$BO7+BT$1-1 -> 2032 | BU7: =$BO7+BU$1-1 -> 2033 | BV7: =$BO7+BV$1-1 -> 2034 | BW7: =$BO7+BW$1-1 -> 2035 | BX7: =$BO7+BX$1-1 -> 2036
A8: 42539 | B8: 190882.51 | C8: 606855.1 | D8: 634156.62 | E8: 638305.45 | F8: 689075.99 | G8: 731494.3 | H8: 732498.61 | I8: 735429.09 | J8: 735871.91 | K8: 795241.18 | O8: =YEAR($A7) -> 2016 | P8: =$B7 -> 162919.32 | Q8: =C7-B7 -> 4131090.6 | R8: =D7-C7 -> 119492.18 | S8: =E7-D7 -> 2296039.1 | T8: =F7-E7 -> 176913.34 | U8: =G7-F7 -> 457588.54 | V8: =H7-G7 -> 677689.66 | W8: =I7-H7 -> 13932.768 | X8: =J7-I7 -> 9177.3157 | Y8: =K7-J7 -> 4907.1342 | AB8: =$O8 -> 2016 | AC8: =P8*VLOOKUP(BO8,Exposure!$B$33:$C$53,2,FALSE)/VLOOKUP(AZ8,Exposure!$B$33:$C$53,2,FALSE) -> 261626.35 | AD8: =Q8*VLOOKUP(BP8,Exposure!$B$33:$C$53,2,FALSE)/VLOOKUP(BA8,Exposure!$B$33:$C$53,2,FALSE) -> 6612982.8 | AE8: =R8*VLOOKUP(BQ8,Exposure!$B$33:$C$53,2,FALSE)/VLOOKUP(BB8,Exposure!$B$33:$C$53,2,FALSE) -> 190815.61 | AF8: =S8*VLOOKUP(BR8,Exposure!$B$33:$C$53,2,FALSE)/VLOOKUP(BC8,Exposure!$B$33:$C$53,2,FALSE) -> 3679285.9 | AG8: =T8*VLOOKUP(BS8,Exposure!$B$33:$C$53,2,FALSE)/VLOOKUP(BD8,Exposure!$B$33:$C$53,2,FALSE) -> 286430.04 | AH8: =U8*VLOOKUP(BT8,Exposure!$B$33:$C$53,2,FALSE)/VLOOKUP(BE8,Exposure!$B$33:$C$53,2,FALSE) -> 736287.11 | AI8: =V8*VLOOKUP(BU8,Exposure!$B$33:$C$53,2,FALSE)/VLOOKUP(BF8,Exposure!$B$33:$C$53,2,FALSE) -> 1014074.8 | AJ8: =W8*VLOOKUP(BV8,Exposure!$B$33:$C$53,2,FALSE)/VLOOKUP(BG8,Exposure!$B$33:$C$53,2,FALSE) -> 20391.756 | ... AL8: =Y8*VLOOKUP(BX8,Exposure!$B$33:$C$53,2,FALSE)/VLOOKUP(BI8,Exposure!$B$33:$C$53,2,FALSE) -> 7043.9946 | AZ8: =$O8 -> 2016 | BA8: =$AZ8+BA$1-1 -> 2017 | BB8: =$AZ8+BB$1-1 -> 2018 | BC8: =$AZ8+BC$1-1 -> 2019 | BD8: =$AZ8+BD$1-1 -> 2020 | BE8: =$AZ8+BE$1-1 -> 2021 | BF8: =$AZ8+BF$1-1 -> 2022 | BG8: =$AZ8+BG$1-1 -> 2023 | BH8: =$AZ8+BH$1-1 -> 2024 | BI8: =$AZ8+BI$1-1 -> 2025 | BO8: 2027 | BP8: =$BO8+BP$1-1 -> 2028 | BQ8: =$BO8+BQ$1-1 -> 2029 | BR8: =$BO8+BR$1-1 -> 2030 | BS8: =$BO8+BS$1-1 -> 2031 | BT8: =$BO8+BT$1-1 -> 2032 | BU8: =$BO8+BU$1-1 -> 2033 | BV8: =$BO8+BV$1-1 -> 2034 | BW8: =$BO8+BW$1-1 -> 2035 | BX8: =$BO8+BX$1-1 -> 2036
A9: 42562 | B9: 704.26176 | C9: 216262.11 | D9: 247957.86 | E9: 413708.58 | F9: 598681.15 | G9: 598688.61 | H9: 601319.53 | I9: 601779.27 | J9: 601801.63 | K9: 601802.77 | O9: =YEAR($A8) -> 2016 | P9: =$B8 -> 190882.51 | Q9: =C8-B8 -> 415972.59 | R9: =D8-C8 -> 27301.522 | S9: =E8-D8 -> 4148.8235 | T9: =F8-E8 -> 50770.547 | U9: =G8-F8 -> 42418.302 | V9: =H8-G8 -> 1004.3159 | W9: =I8-H8 -> 2930.4739 | X9: =J8-I8 -> 442.82599 | Y9: =K8-J8 -> 59369.264 | AB9: =$O9 -> 2016 | AC9: =P9*VLOOKUP(BO9,Exposure!$B$33:$C$53,2,FALSE)/VLOOKUP(AZ9,Exposure!$B$33:$C$53,2,FALSE) -> 306531.43 | AD9: =Q9*VLOOKUP(BP9,Exposure!$B$33:$C$53,2,FALSE)/VLOOKUP(BA9,Exposure!$B$33:$C$53,2,FALSE) -> 665882.18 | AE9: =R9*VLOOKUP(BQ9,Exposure!$B$33:$C$53,2,FALSE)/VLOOKUP(BB9,Exposure!$B$33:$C$53,2,FALSE) -> 43597.467 | AF9: =S9*VLOOKUP(BR9,Exposure!$B$33:$C$53,2,FALSE)/VLOOKUP(BC9,Exposure!$B$33:$C$53,2,FALSE) -> 6648.2787 | AG9: =T9*VLOOKUP(BS9,Exposure!$B$33:$C$53,2,FALSE)/VLOOKUP(BD9,Exposure!$B$33:$C$53,2,FALSE) -> 82199.622 | AH9: =U9*VLOOKUP(BT9,Exposure!$B$33:$C$53,2,FALSE)/VLOOKUP(BE9,Exposure!$B$33:$C$53,2,FALSE) -> 68253.565 | AI9: =V9*VLOOKUP(BU9,Exposure!$B$33:$C$53,2,FALSE)/VLOOKUP(BF9,Exposure!$B$33:$C$53,2,FALSE) -> 1502.8287 | AJ9: =W9*VLOOKUP(BV9,Exposure!$B$33:$C$53,2,FALSE)/VLOOKUP(BG9,Exposure!$B$33:$C$53,2,FALSE) -> 4288.9905 | ... AL9: =Y9*VLOOKUP(BX9,Exposure!$B$33:$C$53,2,FALSE)/VLOOKUP(BI9,Exposure!$B$33:$C$53,2,FALSE) -> 85222.2 | AZ9: =$O9 -> 2016 | BA9: =$AZ9+BA$1-1 -> 2017 | BB9: =$AZ9+BB$1-1 -> 2018 | BC9: =$AZ9+BC$1-1 -> 2019 | BD9: =$AZ9+BD$1-1 -> 2020 | BE9: =$AZ9+BE$1-1 -> 2021 | BF9: =$AZ9+BF$1-1 -> 2022 | BG9: =$AZ9+BG$1-1 -> 2023 | BH9: =$AZ9+BH$1-1 -> 2024 | BI9: =$AZ9+BI$1-1 -> 2025 | BO9: 2027 | BP9: =$BO9+BP$1-1 -> 2028 | BQ9: =$BO9+BQ$1-1 -> 2029 | BR9: =$BO9+BR$1-1 -> 2030 | BS9: =$BO9+BS$1-1 -> 2031 | BT9: =$BO9+BT$1-1 -> 2032 | BU9: =$BO9+BU$1-1 -> 2033 | BV9: =$BO9+BV$1-1 -> 2034 | BW9: =$BO9+BW$1-1 -> 2035 | BX9: =$BO9+BX$1-1 -> 2036
A10: 42598 | B10: 746652.24 | C10: 750549.29 | D10: 1150922.8 | E10: 1162892.8 | F10: 2120678 | G10: 2263720.7 | H10: 2281562.4 | I10: 2294593.8 | J10: 2296186.9 | K10: 2296192.7 | O10: =YEAR($A9) -> 2016 | P10: =$B9 -> 704.26176 | Q10: =C9-B9 -> 215557.85 | R10: =D9-C9 -> 31695.748 | S10: =E9-D9 -> 165750.72 | T10: =F9-E9 -> 184972.58 | U10: =G9-F9 -> 7.4575811 | V10: =H9-G9 -> 2630.9208 | W10: =I9-H9 -> 459.73944 | X10: =J9-I9 -> 22.356881 | Y10: =K9-J9 -> 1.1395802 | AB10: =$O10 -> 2016 | AC10: =P10*VLOOKUP(BO10,Exposure!$B$33:$C$53,2,FALSE)/VLOOKUP(AZ10,Exposure!$B$33:$C$53,2,FALSE) -> 1130.9489 | AD10: =Q10*VLOOKUP(BP10,Exposure!$B$33:$C$53,2,FALSE)/VLOOKUP(BA10,Exposure!$B$33:$C$53,2,FALSE) -> 345061.51 | AE10: =R10*VLOOKUP(BQ10,Exposure!$B$33:$C$53,2,FALSE)/VLOOKUP(BB10,Exposure!$B$33:$C$53,2,FALSE) -> 50614.551 | AF10: =S10*VLOOKUP(BR10,Exposure!$B$33:$C$53,2,FALSE)/VLOOKUP(BC10,Exposure!$B$33:$C$53,2,FALSE) -> 265607.1 | AG10: =T10*VLOOKUP(BS10,Exposure!$B$33:$C$53,2,FALSE)/VLOOKUP(BD10,Exposure!$B$33:$C$53,2,FALSE) -> 299478.28 | AH10: =U10*VLOOKUP(BT10,Exposure!$B$33:$C$53,2,FALSE)/VLOOKUP(BE10,Exposure!$B$33:$C$53,2,FALSE) -> 11.99969 | AI10: =V10*VLOOKUP(BU10,Exposure!$B$33:$C$53,2,FALSE)/VLOOKUP(BF10,Exposure!$B$33:$C$53,2,FALSE) -> 3936.8322 | AJ10: =W10*VLOOKUP(BV10,Exposure!$B$33:$C$53,2,FALSE)/VLOOKUP(BG10,Exposure!$B$33:$C$53,2,FALSE) -> 672.86662 | ... AL10: =Y10*VLOOKUP(BX10,Exposure!$B$33:$C$53,2,FALSE)/VLOOKUP(BI10,Exposure!$B$33:$C$53,2,FALSE) -> 1.6358217 | AZ10: =$O10 -> 2016 | BA10: =$AZ10+BA$1-1 -> 2017 | BB10: =$AZ10+BB$1-1 -> 2018 | BC10: =$AZ10+BC$1-1 -> 2019 | BD10: =$AZ10+BD$1-1 -> 2020 | BE10: =$AZ10+BE$1-1 -> 2021 | BF10: =$AZ10+BF$1-1 -> 2022 | BG10: =$AZ10+BG$1-1 -> 2023 | BH10: =$AZ10+BH$1-1 -> 2024 | BI10: =$AZ10+BI$1-1 -> 2025 | BO10: 2027 | BP10: =$BO10+BP$1-1 -> 2028 | BQ10: =$BO10+BQ$1-1 -> 2029 | BR10: =$BO10+BR$1-1 -> 2030 | BS10: =$BO10+BS$1-1 -> 2031 | BT10: =$BO10+BT$1-1 -> 2032 | BU10: =$BO10+BU$1-1 -> 2033 | BV10: =$BO10+BV$1-1 -> 2034 | BW10: =$BO10+BW$1-1 -> 2035 | BX10: =$BO10+BX$1-1 -> 2036
A11: 42618 | B11: 22115.283 | C11: 223882.25 | D11: 1902460.6 | E11: 1933629.7 | F11: 2145163.9 | G11: 2152022 | H11: 2161925.9 | I11: 2161925.9 | J11: 2162166.1 | K11: 2162166.9 | O11: =YEAR($A10) -> 2016 | P11: =$B10 -> 746652.24 | Q11: =C10-B10 -> 3897.0431 | R11: =D10-C10 -> 400373.52 | S11: =E10-D10 -> 11970.019 | T11: =F10-E10 -> 957785.16 | U11: =G10-F10 -> 143042.69 | V11: =H10-G10 -> 17841.754 | W11: =I10-H10 -> 13031.397 | X11: =J10-I10 -> 1593.089 | Y11: =K10-J10 -> 5.7913746 | AB11: =$O11 -> 2016 | AC11: =P11*VLOOKUP(BO11,Exposure!$B$33:$C$53,2,FALSE)/VLOOKUP(AZ11,Exposure!$B$33:$C$53,2,FALSE) -> 1199022.3 | AD11: =Q11*VLOOKUP(BP11,Exposure!$B$33:$C$53,2,FALSE)/VLOOKUP(BA11,Exposure!$B$33:$C$53,2,FALSE) -> 6238.3234 | AE11: =R11*VLOOKUP(BQ11,Exposure!$B$33:$C$53,2,FALSE)/VLOOKUP(BB11,Exposure!$B$33:$C$53,2,FALSE) -> 639351.58 | AF11: =S11*VLOOKUP(BR11,Exposure!$B$33:$C$53,2,FALSE)/VLOOKUP(BC11,Exposure!$B$33:$C$53,2,FALSE) -> 19181.347 | AG11: =T11*VLOOKUP(BS11,Exposure!$B$33:$C$53,2,FALSE)/VLOOKUP(BD11,Exposure!$B$33:$C$53,2,FALSE) -> 1550693.9 | AH11: =U11*VLOOKUP(BT11,Exposure!$B$33:$C$53,2,FALSE)/VLOOKUP(BE11,Exposure!$B$33:$C$53,2,FALSE) -> 230164.17 | AI11: =V11*VLOOKUP(BU11,Exposure!$B$33:$C$53,2,FALSE)/VLOOKUP(BF11,Exposure!$B$33:$C$53,2,FALSE) -> 26697.874 | AJ11: =W11*VLOOKUP(BV11,Exposure!$B$33:$C$53,2,FALSE)/VLOOKUP(BG11,Exposure!$B$33:$C$53,2,FALSE) -> 19072.526 | ... AL11: =Y11*VLOOKUP(BX11,Exposure!$B$33:$C$53,2,FALSE)/VLOOKUP(BI11,Exposure!$B$33:$C$53,2,FALSE) -> 8.3132863 | AZ11: =$O11 -> 2016 | BA11: =$AZ11+BA$1-1 -> 2017 | BB11: =$AZ11+BB$1-1 -> 2018 | BC11: =$AZ11+BC$1-1 -> 2019 | BD11: =$AZ11+BD$1-1 -> 2020 | BE11: =$AZ11+BE$1-1 -> 2021 | BF11: =$AZ11+BF$1-1 -> 2022 | BG11: =$AZ11+BG$1-1 -> 2023 | BH11: =$AZ11+BH$1-1 -> 2024 | BI11: =$AZ11+BI$1-1 -> 2025 | BO11: 2027 | BP11: =$BO11+BP$1-1 -> 2028 | BQ11: =$BO11+BQ$1-1 -> 2029 | BR11: =$BO11+BR$1-1 -> 2030 | BS11: =$BO11+BS$1-1 -> 2031 | BT11: =$BO11+BT$1-1 -> 2032 | BU11: =$BO11+BU$1-1 -> 2033 | BV11: =$BO11+BV$1-1 -> 2034 | BW11: =$BO11+BW$1-1 -> 2035 | BX11: =$BO11+BX$1-1 -> 2036
A12: 42630 | B12: 5220.8083 | C12: 359287.75 | D12: 369384.15 | E12: 1107719.6 | F12: 1168827.6 | G12: 1177317.7 | H12: 1177319.4 | I12: 1177320 | J12: 1177321.5 | K12: 1177322.1 | O12: =YEAR($A11) -> 2016 | P12: =$B11 -> 22115.283 | Q12: =C11-B11 -> 201766.97 | R12: =D11-C11 -> 1678578.4 | S12: =E11-D11 -> 31169.075 | T12: =F11-E11 -> 211534.19 | U12: =G11-F11 -> 6858.1199 | V12: =H11-G11 -> 9903.8586 | W12: =I11-H11 -> 0.063418521 | X12: =J11-I11 -> 240.17136 | Y12: =K11-J11 -> 0.80848745 | AB12: =$O12 -> 2016 | AC12: =P12*VLOOKUP(BO12,Exposure!$B$33:$C$53,2,FALSE)/VLOOKUP(AZ12,Exposure!$B$33:$C$53,2,FALSE) -> 35514.146 | AD12: =Q12*VLOOKUP(BP12,Exposure!$B$33:$C$53,2,FALSE)/VLOOKUP(BA12,Exposure!$B$33:$C$53,2,FALSE) -> 322985.29 | AE12: =R12*VLOOKUP(BQ12,Exposure!$B$33:$C$53,2,FALSE)/VLOOKUP(BB12,Exposure!$B$33:$C$53,2,FALSE) -> 2680501.3 | AF12: =S12*VLOOKUP(BR12,Exposure!$B$33:$C$53,2,FALSE)/VLOOKUP(BC12,Exposure!$B$33:$C$53,2,FALSE) -> 49946.858 | AG12: =T12*VLOOKUP(BS12,Exposure!$B$33:$C$53,2,FALSE)/VLOOKUP(BD12,Exposure!$B$33:$C$53,2,FALSE) -> 342482.63 | AH12: =U12*VLOOKUP(BT12,Exposure!$B$33:$C$53,2,FALSE)/VLOOKUP(BE12,Exposure!$B$33:$C$53,2,FALSE) -> 11035.122 | AI12: =V12*VLOOKUP(BU12,Exposure!$B$33:$C$53,2,FALSE)/VLOOKUP(BF12,Exposure!$B$33:$C$53,2,FALSE) -> 14819.842 | AJ12: =W12*VLOOKUP(BV12,Exposure!$B$33:$C$53,2,FALSE)/VLOOKUP(BG12,Exposure!$B$33:$C$53,2,FALSE) -> 0.09281824 | ... AL12: =Y12*VLOOKUP(BX12,Exposure!$B$33:$C$53,2,FALSE)/VLOOKUP(BI12,Exposure!$B$33:$C$53,2,FALSE) -> 1.1605513 | AZ12: =$O12 -> 2016 | BA12: =$AZ12+BA$1-1 -> 2017 | BB12: =$AZ12+BB$1-1 -> 2018 | BC12: =$AZ12+BC$1-1 -> 2019 | BD12: =$AZ12+BD$1-1 -> 2020 | BE12: =$AZ12+BE$1-1 -> 2021 | BF12: =$AZ12+BF$1-1 -> 2022 | BG12: =$AZ12+BG$1-1 -> 2023 | BH12: =$AZ12+BH$1-1 -> 2024 | BI12: =$AZ12+BI$1-1 -> 2025 | BO12: 2027 | BP12: =$BO12+BP$1-1 -> 2028 | BQ12: =$BO12+BQ$1-1 -> 2029 | BR12: =$BO12+BR$1-1 -> 2030 | BS12: =$BO12+BS$1-1 -> 2031 | BT12: =$BO12+BT$1-1 -> 2032 | BU12: =$BO12+BU$1-1 -> 2033 | BV12: =$BO12+BV$1-1 -> 2034 | BW12: =$BO12+BW$1-1 -> 2035 | BX12: =$BO12+BX$1-1 -> 2036
A13: 42673 | B13: 48508.148 | C13: 58558.077 | D13: 778959.71 | E13: 828568.29 | F13: 828631.11 | G13: 830826.09 | H13: 831209.69 | I13: 831230.88 | J13: 831251.15 | K13: 831284.8 | O13: =YEAR($A12) -> 2016 | P13: =$B12 -> 5220.8083 | Q13: =C12-B12 -> 354066.95 | R13: =D12-C12 -> 10096.399 | S13: =E12-D12 -> 738335.41 | T13: =F12-E12 -> 61108.085 | U13: =G12-F12 -> 8490.0964 | V13: =H12-G12 -> 1.6240313 | W13: =I12-H12 -> 0.58914969 | X13: =J12-I12 -> 1.5477351 | Y13: =K12-J12 -> 0.6051519 | AB13: =$O13 -> 2016 | AC13: =P13*VLOOKUP(BO13,Exposure!$B$33:$C$53,2,FALSE)/VLOOKUP(AZ13,Exposure!$B$33:$C$53,2,FALSE) -> 8383.9104 | AD13: =Q13*VLOOKUP(BP13,Exposure!$B$33:$C$53,2,FALSE)/VLOOKUP(BA13,Exposure!$B$33:$C$53,2,FALSE) -> 566784.62 | AE13: =R13*VLOOKUP(BQ13,Exposure!$B$33:$C$53,2,FALSE)/VLOOKUP(BB13,Exposure!$B$33:$C$53,2,FALSE) -> 16122.816 | AF13: =S13*VLOOKUP(BR13,Exposure!$B$33:$C$53,2,FALSE)/VLOOKUP(BC13,Exposure!$B$33:$C$53,2,FALSE) -> 1183145 | AG13: =T13*VLOOKUP(BS13,Exposure!$B$33:$C$53,2,FALSE)/VLOOKUP(BD13,Exposure!$B$33:$C$53,2,FALSE) -> 98936.525 | AH13: =U13*VLOOKUP(BT13,Exposure!$B$33:$C$53,2,FALSE)/VLOOKUP(BE13,Exposure!$B$33:$C$53,2,FALSE) -> 13661.069 | AI13: =V13*VLOOKUP(BU13,Exposure!$B$33:$C$53,2,FALSE)/VLOOKUP(BF13,Exposure!$B$33:$C$53,2,FALSE) -> 2.4301526 | AJ13: =W13*VLOOKUP(BV13,Exposure!$B$33:$C$53,2,FALSE)/VLOOKUP(BG13,Exposure!$B$33:$C$53,2,FALSE) -> 0.86226921 | ... AL13: =Y13*VLOOKUP(BX13,Exposure!$B$33:$C$53,2,FALSE)/VLOOKUP(BI13,Exposure!$B$33:$C$53,2,FALSE) -> 0.8686713 | AZ13: =$O13 -> 2016 | BA13: =$AZ13+BA$1-1 -> 2017 | BB13: =$AZ13+BB$1-1 -> 2018 | BC13: =$AZ13+BC$1-1 -> 2019 | BD13: =$AZ13+BD$1-1 -> 2020 | BE13: =$AZ13+BE$1-1 -> 2021 | BF13: =$AZ13+BF$1-1 -> 2022 | BG13: =$AZ13+BG$1-1 -> 2023 | BH13: =$AZ13+BH$1-1 -> 2024 | BI13: =$AZ13+BI$1-1 -> 2025 | BO13: 2027 | BP13: =$BO13+BP$1-1 -> 2028 | BQ13: =$BO13+BQ$1-1 -> 2029 | BR13: =$BO13+BR$1-1 -> 2030 | BS13: =$BO13+BS$1-1 -> 2031 | BT13: =$BO13+BT$1-1 -> 2032 | BU13: =$BO13+BU$1-1 -> 2033 | BV13: =$BO13+BV$1-1 -> 2034 | BW13: =$BO13+BW$1-1 -> 2035 | BX13: =$BO13+BX$1-1 -> 2036
A14: 42683 | B14: 1281489.4 | C14: 1290805.5 | D14: 1293569 | E14: 1387890 | F14: 1772318.7 | G14: 2235654.1 | H14: 2285067.1 | I14: 2344718.9 | J14: 2346425.9 | K14: 2346444.2 | O14: =YEAR($A13) -> 2016 | P14: =$B13 -> 48508.148 | Q14: =C13-B13 -> 10049.929 | R14: =D13-C13 -> 720401.64 | S14: =E13-D13 -> 49608.581 | T14: =F13-E13 -> 62.812292 | U14: =G13-F13 -> 2194.9828 | V14: =H13-G13 -> 383.59633 | W14: =I13-H13 -> 21.195405 | X14: =J13-I13 -> 20.271308 | Y14: =K13-J13 -> 33.647274 | AB14: =$O14 -> 2016 | AC14: =P14*VLOOKUP(BO14,Exposure!$B$33:$C$53,2,FALSE)/VLOOKUP(AZ14,Exposure!$B$33:$C$53,2,FALSE) -> 77897.51 | AD14: =Q14*VLOOKUP(BP14,Exposure!$B$33:$C$53,2,FALSE)/VLOOKUP(BA14,Exposure!$B$33:$C$53,2,FALSE) -> 16087.764 | AE14: =R14*VLOOKUP(BQ14,Exposure!$B$33:$C$53,2,FALSE)/VLOOKUP(BB14,Exposure!$B$33:$C$53,2,FALSE) -> 1150400.5 | AF14: =S14*VLOOKUP(BR14,Exposure!$B$33:$C$53,2,FALSE)/VLOOKUP(BC14,Exposure!$B$33:$C$53,2,FALSE) -> 79495.23 | AG14: =T14*VLOOKUP(BS14,Exposure!$B$33:$C$53,2,FALSE)/VLOOKUP(BD14,Exposure!$B$33:$C$53,2,FALSE) -> 101.69571 | AH14: =U14*VLOOKUP(BT14,Exposure!$B$33:$C$53,2,FALSE)/VLOOKUP(BE14,Exposure!$B$33:$C$53,2,FALSE) -> 3531.8575 | AI14: =V14*VLOOKUP(BU14,Exposure!$B$33:$C$53,2,FALSE)/VLOOKUP(BF14,Exposure!$B$33:$C$53,2,FALSE) -> 574.00223 | AJ14: =W14*VLOOKUP(BV14,Exposure!$B$33:$C$53,2,FALSE)/VLOOKUP(BG14,Exposure!$B$33:$C$53,2,FALSE) -> 31.021225 | ... AL14: =Y14*VLOOKUP(BX14,Exposure!$B$33:$C$53,2,FALSE)/VLOOKUP(BI14,Exposure!$B$33:$C$53,2,FALSE) -> 48.299313 | AZ14: =$O14 -> 2016 | BA14: =$AZ14+BA$1-1 -> 2017 | BB14: =$AZ14+BB$1-1 -> 2018 | BC14: =$AZ14+BC$1-1 -> 2019 | BD14: =$AZ14+BD$1-1 -> 2020 | BE14: =$AZ14+BE$1-1 -> 2021 | BF14: =$AZ14+BF$1-1 -> 2022 | BG14: =$AZ14+BG$1-1 -> 2023 | BH14: =$AZ14+BH$1-1 -> 2024 | BI14: =$AZ14+BI$1-1 -> 2025 | BO14: 2027 | BP14: =$BO14+BP$1-1 -> 2028 | BQ14: =$BO14+BQ$1-1 -> 2029 | BR14: =$BO14+BR$1-1 -> 2030 | BS14: =$BO14+BS$1-1 -> 2031 | BT14: =$BO14+BT$1-1 -> 2032 | BU14: =$BO14+BU$1-1 -> 2033 | BV14: =$BO14+BV$1-1 -> 2034 | BW14: =$BO14+BW$1-1 -> 2035 | BX14: =$BO14+BX$1-1 -> 2036
A15: 42721 | B15: 408506.28 | C15: 841725.92 | D15: 847014.85 | E15: 882491.85 | F15: 1036788.2 | G15: 1162665.9 | H15: 1324549.6 | I15: 1469476.4 | J15: 2387942.9 | K15: 2397781.8 | O15: =YEAR($A14) -> 2016 | P15: =$B14 -> 1281489.4 | Q15: =C14-B14 -> 9316.0929 | R15: =D14-C14 -> 2763.5707 | S15: =E14-D14 -> 94320.971 | T15: =F14-E14 -> 384428.67 | U15: =G14-F14 -> 463335.46 | V15: =H14-G14 -> 49412.965 | W15: =I14-H14 -> 59651.859 | X15: =J14-I14 -> 1706.9217 | Y15: =K14-J14 -> 18.319925 | AB15: =$O15 -> 2016 | AC15: =P15*VLOOKUP(BO15,Exposure!$B$33:$C$53,2,FALSE)/VLOOKUP(AZ15,Exposure!$B$33:$C$53,2,FALSE) -> 2057898.2 | AD15: =Q15*VLOOKUP(BP15,Exposure!$B$33:$C$53,2,FALSE)/VLOOKUP(BA15,Exposure!$B$33:$C$53,2,FALSE) -> 14913.05 | AE15: =R15*VLOOKUP(BQ15,Exposure!$B$33:$C$53,2,FALSE)/VLOOKUP(BB15,Exposure!$B$33:$C$53,2,FALSE) -> 4413.1122 | AF15: =S15*VLOOKUP(BR15,Exposure!$B$33:$C$53,2,FALSE)/VLOOKUP(BC15,Exposure!$B$33:$C$53,2,FALSE) -> 151144.56 | AG15: =T15*VLOOKUP(BS15,Exposure!$B$33:$C$53,2,FALSE)/VLOOKUP(BD15,Exposure!$B$33:$C$53,2,FALSE) -> 622405.96 | AH15: =U15*VLOOKUP(BT15,Exposure!$B$33:$C$53,2,FALSE)/VLOOKUP(BE15,Exposure!$B$33:$C$53,2,FALSE) -> 745534.24 | AI15: =V15*VLOOKUP(BU15,Exposure!$B$33:$C$53,2,FALSE)/VLOOKUP(BF15,Exposure!$B$33:$C$53,2,FALSE) -> 73940.103 | AJ15: =W15*VLOOKUP(BV15,Exposure!$B$33:$C$53,2,FALSE)/VLOOKUP(BG15,Exposure!$B$33:$C$53,2,FALSE) -> 87305.42 | ... AL15: =Y15*VLOOKUP(BX15,Exposure!$B$33:$C$53,2,FALSE)/VLOOKUP(BI15,Exposure!$B$33:$C$53,2,FALSE) -> 26.297518 | AZ15: =$O15 -> 2016 | BA15: =$AZ15+BA$1-1 -> 2017 | BB15: =$AZ15+BB$1-1 -> 2018 | BC15: =$AZ15+BC$1-1 -> 2019 | BD15: =$AZ15+BD$1-1 -> 2020 | BE15: =$AZ15+BE$1-1 -> 2021 | BF15: =$AZ15+BF$1-1 -> 2022 | BG15: =$AZ15+BG$1-1 -> 2023 | BH15: =$AZ15+BH$1-1 -> 2024 | BI15: =$AZ15+BI$1-1 -> 2025 | BO15: 2027 | BP15: =$BO15+BP$1-1 -> 2028 | BQ15: =$BO15+BQ$1-1 -> 2029 | BR15: =$BO15+BR$1-1 -> 2030 | BS15: =$BO15+BS$1-1 -> 2031 | BT15: =$BO15+BT$1-1 -> 2032 | BU15: =$BO15+BU$1-1 -> 2033 | BV15: =$BO15+BV$1-1 -> 2034 | BW15: =$BO15+BW$1-1 -> 2035 | BX15: =$BO15+BX$1-1 -> 2036
A16: 42761 | B16: 590333.35 | C16: 604906.01 | D16: 1968378.3 | E16: 2262789 | F16: 2505929.8 | G16: 2958402.6 | H16: 2959750 | I16: 2960125.9 | J16: 2960133.4 | O16: =YEAR($A15) -> 2016 | P16: =$B15 -> 408506.28 | Q16: =C15-B15 -> 433219.64 | R16: =D15-C15 -> 5288.9258 | S16: =E15-D15 -> 35477.007 | T16: =F15-E15 -> 154296.37 | U16: =G15-F15 -> 125877.66 | V16: =H15-G15 -> 161883.73 | W16: =I15-H15 -> 144926.75 | X16: =J15-I15 -> 918466.52 | Y16: =K15-J15 -> 9838.8824 | AB16: =$O16 -> 2016 | AC16: =P16*VLOOKUP(BO16,Exposure!$B$33:$C$53,2,FALSE)/VLOOKUP(AZ16,Exposure!$B$33:$C$53,2,FALSE) -> 656005.71 | AD16: =Q16*VLOOKUP(BP16,Exposure!$B$33:$C$53,2,FALSE)/VLOOKUP(BA16,Exposure!$B$33:$C$53,2,FALSE) -> 693490.97 | AE16: =R16*VLOOKUP(BQ16,Exposure!$B$33:$C$53,2,FALSE)/VLOOKUP(BB16,Exposure!$B$33:$C$53,2,FALSE) -> 8445.8208 | AF16: =S16*VLOOKUP(BR16,Exposure!$B$33:$C$53,2,FALSE)/VLOOKUP(BC16,Exposure!$B$33:$C$53,2,FALSE) -> 56850.1 | AG16: =T16*VLOOKUP(BS16,Exposure!$B$33:$C$53,2,FALSE)/VLOOKUP(BD16,Exposure!$B$33:$C$53,2,FALSE) -> 249812.23 | AH16: =U16*VLOOKUP(BT16,Exposure!$B$33:$C$53,2,FALSE)/VLOOKUP(BE16,Exposure!$B$33:$C$53,2,FALSE) -> 202544.62 | AI16: =V16*VLOOKUP(BU16,Exposure!$B$33:$C$53,2,FALSE)/VLOOKUP(BF16,Exposure!$B$33:$C$53,2,FALSE) -> 242238.03 | AJ16: =W16*VLOOKUP(BV16,Exposure!$B$33:$C$53,2,FALSE)/VLOOKUP(BG16,Exposure!$B$33:$C$53,2,FALSE) -> 212112.26 | ... AL16: =Y16*VLOOKUP(BX16,Exposure!$B$33:$C$53,2,FALSE)/VLOOKUP(BI16,Exposure!$B$33:$C$53,2,FALSE) -> 14123.322 | AZ16: =$O16 -> 2016 | BA16: =$AZ16+BA$1-1 -> 2017 | BB16: =$AZ16+BB$1-1 -> 2018 | BC16: =$AZ16+BC$1-1 -> 2019 | BD16: =$AZ16+BD$1-1 -> 2020 | BE16: =$AZ16+BE$1-1 -> 2021 | BF16: =$AZ16+BF$1-1 -> 2022 | BG16: =$AZ16+BG$1-1 -> 2023 | BH16: =$AZ16+BH$1-1 -> 2024 | BI16: =$AZ16+BI$1-1 -> 2025 | BO16: 2027 | BP16: =$BO16+BP$1-1 -> 2028 | BQ16: =$BO16+BQ$1-1 -> 2029 | BR16: =$BO16+BR$1-1 -> 2030 | BS16: =$BO16+BS$1-1 -> 2031 | BT16: =$BO16+BT$1-1 -> 2032 | BU16: =$BO16+BU$1-1 -> 2033 | BV16: =$BO16+BV$1-1 -> 2034 | BW16: =$BO16+BW$1-1 -> 2035 | BX16: =$BO16+BX$1-1 -> 2036
A17: 42775 | B17: 297429.69 | C17: 324197.87 | D17: 330954.1 | E17: 1212831 | F17: 1215271.7 | G17: 1231003.8 | H17: 1233298.6 | I17: 1250468.7 | J17: 1277885.7 | O17: =YEAR($A16) -> 2017 | P17: =$B16 -> 590333.35 | Q17: =C16-B16 -> 14572.665 | R17: =D16-C16 -> 1363472.3 | S17: =E16-D16 -> 294410.67 | T17: =F16-E16 -> 243140.79 | U17: =G16-F16 -> 452472.82 | V17: =H16-G16 -> 1347.4442 | W17: =I16-H16 -> 375.90144 | X17: =J16-I16 -> 7.5121361 | AB17: =$O17 -> 2017 | AC17: =P17*VLOOKUP(BO17,Exposure!$B$33:$C$53,2,FALSE)/VLOOKUP(AZ17,Exposure!$B$33:$C$53,2,FALSE) -> 914807.4 | AD17: =Q17*VLOOKUP(BP17,Exposure!$B$33:$C$53,2,FALSE)/VLOOKUP(BA17,Exposure!$B$33:$C$53,2,FALSE) -> 22527.503 | AE17: =R17*VLOOKUP(BQ17,Exposure!$B$33:$C$53,2,FALSE)/VLOOKUP(BB17,Exposure!$B$33:$C$53,2,FALSE) -> 2115096.8 | AF17: =S17*VLOOKUP(BR17,Exposure!$B$33:$C$53,2,FALSE)/VLOOKUP(BC17,Exposure!$B$33:$C$53,2,FALSE) -> 461435.71 | AG17: =T17*VLOOKUP(BS17,Exposure!$B$33:$C$53,2,FALSE)/VLOOKUP(BD17,Exposure!$B$33:$C$53,2,FALSE) -> 378729.87 | AH17: =U17*VLOOKUP(BT17,Exposure!$B$33:$C$53,2,FALSE)/VLOOKUP(BE17,Exposure!$B$33:$C$53,2,FALSE) -> 655437.55 | AI17: =V17*VLOOKUP(BU17,Exposure!$B$33:$C$53,2,FALSE)/VLOOKUP(BF17,Exposure!$B$33:$C$53,2,FALSE) -> 1909.0956 | AJ17: =W17*VLOOKUP(BV17,Exposure!$B$33:$C$53,2,FALSE)/VLOOKUP(BG17,Exposure!$B$33:$C$53,2,FALSE) -> 525.74648 | AK17: =X17*VLOOKUP(BW17,Exposure!$B$33:$C$53,2,FALSE)/VLOOKUP(BH17,Exposure!$B$33:$C$53,2,FALSE) -> 10.438887 | AZ17: =$O17 -> 2017 | BA17: =$AZ17+BA$1-1 -> 2018 | BB17: =$AZ17+BB$1-1 -> 2019 | BC17: =$AZ17+BC$1-1 -> 2020 | BD17: =$AZ17+BD$1-1 -> 2021 | BE17: =$AZ17+BE$1-1 -> 2022 | BF17: =$AZ17+BF$1-1 -> 2023 | BG17: =$AZ17+BG$1-1 -> 2024 | BH17: =$AZ17+BH$1-1 -> 2025 | BO17: 2027 | BP17: =$BO17+BP$1-1 -> 2028 | BQ17: =$BO17+BQ$1-1 -> 2029 | BR17: =$BO17+BR$1-1 -> 2030 | BS17: =$BO17+BS$1-1 -> 2031 | BT17: =$BO17+BT$1-1 -> 2032 | BU17: =$BO17+BU$1-1 -> 2033 | BV17: =$BO17+BV$1-1 -> 2034 | BW17: =$BO17+BW$1-1 -> 2035
A18: 42832 | B18: 92188.352 | C18: 850262.73 | D18: 1281096.1 | E18: 1357000.1 | F18: 1357180.4 | G18: 1727536.7 | H18: 1730782.1 | I18: 1854340.6 | J18: 1858893.6 | O18: =YEAR($A17) -> 2017 | P18: =$B17 -> 297429.69 | Q18: =C17-B17 -> 26768.184 | R18: =D17-C17 -> 6756.2243 | S18: =E17-D17 -> 881876.87 | T18: =F17-E17 -> 2440.7151 | U18: =G17-F17 -> 15732.116 | V18: =H17-G17 -> 2294.8191 | W18: =I17-H17 -> 17170.086 | X18: =J17-I17 -> 27416.958 | AB18: =$O18 -> 2017 | AC18: =P18*VLOOKUP(BO18,Exposure!$B$33:$C$53,2,FALSE)/VLOOKUP(AZ18,Exposure!$B$33:$C$53,2,FALSE) -> 460910.57 | AD18: =Q18*VLOOKUP(BP18,Exposure!$B$33:$C$53,2,FALSE)/VLOOKUP(BA18,Exposure!$B$33:$C$53,2,FALSE) -> 41380.237 | AE18: =R18*VLOOKUP(BQ18,Exposure!$B$33:$C$53,2,FALSE)/VLOOKUP(BB18,Exposure!$B$33:$C$53,2,FALSE) -> 10480.645 | AF18: =S18*VLOOKUP(BR18,Exposure!$B$33:$C$53,2,FALSE)/VLOOKUP(BC18,Exposure!$B$33:$C$53,2,FALSE) -> 1382183.2 | AG18: =T18*VLOOKUP(BS18,Exposure!$B$33:$C$53,2,FALSE)/VLOOKUP(BD18,Exposure!$B$33:$C$53,2,FALSE) -> 3801.7962 | AH18: =U18*VLOOKUP(BT18,Exposure!$B$33:$C$53,2,FALSE)/VLOOKUP(BE18,Exposure!$B$33:$C$53,2,FALSE) -> 22789.036 | AI18: =V18*VLOOKUP(BU18,Exposure!$B$33:$C$53,2,FALSE)/VLOOKUP(BF18,Exposure!$B$33:$C$53,2,FALSE) -> 3251.3622 | AJ18: =W18*VLOOKUP(BV18,Exposure!$B$33:$C$53,2,FALSE)/VLOOKUP(BG18,Exposure!$B$33:$C$53,2,FALSE) -> 24014.573 | AK18: =X18*VLOOKUP(BW18,Exposure!$B$33:$C$53,2,FALSE)/VLOOKUP(BH18,Exposure!$B$33:$C$53,2,FALSE) -> 38098.688 | AZ18: =$O18 -> 2017 | BA18: =$AZ18+BA$1-1 -> 2018 | BB18: =$AZ18+BB$1-1 -> 2019 | BC18: =$AZ18+BC$1-1 -> 2020 | BD18: =$AZ18+BD$1-1 -> 2021 | BE18: =$AZ18+BE$1-1 -> 2022 | BF18: =$AZ18+BF$1-1 -> 2023 | BG18: =$AZ18+BG$1-1 -> 2024 | BH18: =$AZ18+BH$1-1 -> 2025 | BO18: 2027 | BP18: =$BO18+BP$1-1 -> 2028 | BQ18: =$BO18+BQ$1-1 -> 2029 | BR18: =$BO18+BR$1-1 -> 2030 | BS18: =$BO18+BS$1-1 -> 2031 | BT18: =$BO18+BT$1-1 -> 2032 | BU18: =$BO18+BU$1-1 -> 2033 | BV18: =$BO18+BV$1-1 -> 2034 | BW18: =$BO18+BW$1-1 -> 2035
A19: 42844 | B19: 36320.305 | C19: 212686.51 | D19: 497060.3 | E19: 744519.85 | F19: 1259933.8 | G19: 1259933.9 | H19: 1259934 | I19: 1259934 | J19: 1259934 | O19: =YEAR($A18) -> 2017 | P19: =$B18 -> 92188.352 | Q19: =C18-B18 -> 758074.38 | R19: =D18-C18 -> 430833.32 | S19: =E18-D18 -> 75903.999 | T19: =F18-E18 -> 180.34719 | U19: =G18-F18 -> 370356.26 | V19: =H18-G18 -> 3245.423 | W19: =I18-H18 -> 123558.56 | X19: =J18-I18 -> 4552.9831 | AB19: =$O19 -> 2017 | AC19: =P19*VLOOKUP(BO19,Exposure!$B$33:$C$53,2,FALSE)/VLOOKUP(AZ19,Exposure!$B$33:$C$53,2,FALSE) -> 142859.26 | AD19: =Q19*VLOOKUP(BP19,Exposure!$B$33:$C$53,2,FALSE)/VLOOKUP(BA19,Exposure!$B$33:$C$53,2,FALSE) -> 1171887.4 | AE19: =R19*VLOOKUP(BQ19,Exposure!$B$33:$C$53,2,FALSE)/VLOOKUP(BB19,Exposure!$B$33:$C$53,2,FALSE) -> 668333.49 | AF19: =S19*VLOOKUP(BR19,Exposure!$B$33:$C$53,2,FALSE)/VLOOKUP(BC19,Exposure!$B$33:$C$53,2,FALSE) -> 118965.85 | AG19: =T19*VLOOKUP(BS19,Exposure!$B$33:$C$53,2,FALSE)/VLOOKUP(BD19,Exposure!$B$33:$C$53,2,FALSE) -> 280.919 | AH19: =U19*VLOOKUP(BT19,Exposure!$B$33:$C$53,2,FALSE)/VLOOKUP(BE19,Exposure!$B$33:$C$53,2,FALSE) -> 536486.14 | AI19: =V19*VLOOKUP(BU19,Exposure!$B$33:$C$53,2,FALSE)/VLOOKUP(BF19,Exposure!$B$33:$C$53,2,FALSE) -> 4598.2037 | AJ19: =W19*VLOOKUP(BV19,Exposure!$B$33:$C$53,2,FALSE)/VLOOKUP(BG19,Exposure!$B$33:$C$53,2,FALSE) -> 172812.53 | AK19: =X19*VLOOKUP(BW19,Exposure!$B$33:$C$53,2,FALSE)/VLOOKUP(BH19,Exposure!$B$33:$C$53,2,FALSE) -> 6326.8392 | AZ19: =$O19 -> 2017 | BA19: =$AZ19+BA$1-1 -> 2018 | BB19: =$AZ19+BB$1-1 -> 2019 | BC19: =$AZ19+BC$1-1 -> 2020 | BD19: =$AZ19+BD$1-1 -> 2021 | BE19: =$AZ19+BE$1-1 -> 2022 | BF19: =$AZ19+BF$1-1 -> 2023 | BG19: =$AZ19+BG$1-1 -> 2024 | BH19: =$AZ19+BH$1-1 -> 2025 | BO19: 2027 | BP19: =$BO19+BP$1-1 -> 2028 | BQ19: =$BO19+BQ$1-1 -> 2029 | BR19: =$BO19+BR$1-1 -> 2030 | BS19: =$BO19+BS$1-1 -> 2031 | BT19: =$BO19+BT$1-1 -> 2032 | BU19: =$BO19+BU$1-1 -> 2033 | BV19: =$BO19+BV$1-1 -> 2034 | BW19: =$BO19+BW$1-1 -> 2035
A20: 42844 | B20: 100859.96 | C20: 1565441.6 | D20: 1662022 | E20: 2532525.6 | F20: 2592835.1 | G20: 2592972.2 | H20: 2615002.3 | I20: 2618178.7 | J20: 2618827.1 | O20: =YEAR($A19) -> 2017 | P20: =$B19 -> 36320.305 | Q20: =C19-B19 -> 176366.21 | R20: =D19-C19 -> 284373.78 | S20: =E19-D19 -> 247459.56 | T20: =F19-E19 -> 515413.95 | U20: =G19-F19 -> 0.11950152 | V20: =H19-G19 -> 0.0793357 | W20: =I19-H19 -> 0.00038990541 | X20: =J19-I19 -> 5.4949662e-05 | AB20: =$O20 -> 2017 | AC20: =P20*VLOOKUP(BO20,Exposure!$B$33:$C$53,2,FALSE)/VLOOKUP(AZ20,Exposure!$B$33:$C$53,2,FALSE) -> 56283.596 | AD20: =Q20*VLOOKUP(BP20,Exposure!$B$33:$C$53,2,FALSE)/VLOOKUP(BA20,Exposure!$B$33:$C$53,2,FALSE) -> 272639.92 | AE20: =R20*VLOOKUP(BQ20,Exposure!$B$33:$C$53,2,FALSE)/VLOOKUP(BB20,Exposure!$B$33:$C$53,2,FALSE) -> 441137.01 | AF20: =S20*VLOOKUP(BR20,Exposure!$B$33:$C$53,2,FALSE)/VLOOKUP(BC20,Exposure!$B$33:$C$53,2,FALSE) -> 387848.3 | AG20: =T20*VLOOKUP(BS20,Exposure!$B$33:$C$53,2,FALSE)/VLOOKUP(BD20,Exposure!$B$33:$C$53,2,FALSE) -> 802837.97 | AH20: =U20*VLOOKUP(BT20,Exposure!$B$33:$C$53,2,FALSE)/VLOOKUP(BE20,Exposure!$B$33:$C$53,2,FALSE) -> 0.17310605 | AI20: =V20*VLOOKUP(BU20,Exposure!$B$33:$C$53,2,FALSE)/VLOOKUP(BF20,Exposure!$B$33:$C$53,2,FALSE) -> 0.11240498 | AJ20: =W20*VLOOKUP(BV20,Exposure!$B$33:$C$53,2,FALSE)/VLOOKUP(BG20,Exposure!$B$33:$C$53,2,FALSE) -> 0.00054533284 | AK20: =X20*VLOOKUP(BW20,Exposure!$B$33:$C$53,2,FALSE)/VLOOKUP(BH20,Exposure!$B$33:$C$53,2,FALSE) -> 7.6358217e-05 | AZ20: =$O20 -> 2017 | BA20: =$AZ20+BA$1-1 -> 2018 | BB20: =$AZ20+BB$1-1 -> 2019 | BC20: =$AZ20+BC$1-1 -> 2020 | BD20: =$AZ20+BD$1-1 -> 2021 | BE20: =$AZ20+BE$1-1 -> 2022 | BF20: =$AZ20+BF$1-1 -> 2023 | BG20: =$AZ20+BG$1-1 -> 2024 | BH20: =$AZ20+BH$1-1 -> 2025 | BO20: 2027 | BP20: =$BO20+BP$1-1 -> 2028 | BQ20: =$BO20+BQ$1-1 -> 2029 | BR20: =$BO20+BR$1-1 -> 2030 | BS20: =$BO20+BS$1-1 -> 2031 | BT20: =$BO20+BT$1-1 -> 2032 | BU20: =$BO20+BU$1-1 -> 2033 | BV20: =$BO20+BV$1-1 -> 2034 | BW20: =$BO20+BW$1-1 -> 2035
A21: 42884 | B21: 192663.34 | C21: 249091.69 | D21: 500853.76 | E21: 590380.75 | F21: 1060433.2 | G21: 1060629 | H21: 1064819.5 | I21: 1065471.6 | J21: 1067758.8 | O21: =YEAR($A20) -> 2017 | P21: =$B20 -> 100859.96 | Q21: =C20-B20 -> 1464581.7 | R21: =D20-C20 -> 96580.406 | S21: =E20-D20 -> 870503.53 | T21: =F20-E20 -> 60309.578 | U21: =G20-F20 -> 137.01918 | V21: =H20-G20 -> 22030.195 | W21: =I20-H20 -> 3176.3218 | X21: =J20-I20 -> 648.40088 | AB21: =$O21 -> 2017 | AC21: =P21*VLOOKUP(BO21,Exposure!$B$33:$C$53,2,FALSE)/VLOOKUP(AZ21,Exposure!$B$33:$C$53,2,FALSE) -> 156297.18 | AD21: =Q21*VLOOKUP(BP21,Exposure!$B$33:$C$53,2,FALSE)/VLOOKUP(BA21,Exposure!$B$33:$C$53,2,FALSE) -> 2264058.6 | AE21: =R21*VLOOKUP(BQ21,Exposure!$B$33:$C$53,2,FALSE)/VLOOKUP(BB21,Exposure!$B$33:$C$53,2,FALSE) -> 149821.1 | AF21: =S21*VLOOKUP(BR21,Exposure!$B$33:$C$53,2,FALSE)/VLOOKUP(BC21,Exposure!$B$33:$C$53,2,FALSE) -> 1364357.5 | AG21: =T21*VLOOKUP(BS21,Exposure!$B$33:$C$53,2,FALSE)/VLOOKUP(BD21,Exposure!$B$33:$C$53,2,FALSE) -> 93941.616 | AH21: =U21*VLOOKUP(BT21,Exposure!$B$33:$C$53,2,FALSE)/VLOOKUP(BE21,Exposure!$B$33:$C$53,2,FALSE) -> 198.48156 | AI21: =V21*VLOOKUP(BU21,Exposure!$B$33:$C$53,2,FALSE)/VLOOKUP(BF21,Exposure!$B$33:$C$53,2,FALSE) -> 31212.98 | AJ21: =W21*VLOOKUP(BV21,Exposure!$B$33:$C$53,2,FALSE)/VLOOKUP(BG21,Exposure!$B$33:$C$53,2,FALSE) -> 4442.4943 | AK21: =X21*VLOOKUP(BW21,Exposure!$B$33:$C$53,2,FALSE)/VLOOKUP(BH21,Exposure!$B$33:$C$53,2,FALSE) -> 901.01982 | AZ21: =$O21 -> 2017 | BA21: =$AZ21+BA$1-1 -> 2018 | BB21: =$AZ21+BB$1-1 -> 2019 | BC21: =$AZ21+BC$1-1 -> 2020 | BD21: =$AZ21+BD$1-1 -> 2021 | BE21: =$AZ21+BE$1-1 -> 2022 | BF21: =$AZ21+BF$1-1 -> 2023 | BG21: =$AZ21+BG$1-1 -> 2024 | BH21: =$AZ21+BH$1-1 -> 2025 | BO21: 2027 | BP21: =$BO21+BP$1-1 -> 2028 | BQ21: =$BO21+BQ$1-1 -> 2029 | BR21: =$BO21+BR$1-1 -> 2030 | BS21: =$BO21+BS$1-1 -> 2031 | BT21: =$BO21+BT$1-1 -> 2032 | BU21: =$BO21+BU$1-1 -> 2033 | BV21: =$BO21+BV$1-1 -> 2034 | BW21: =$BO21+BW$1-1 -> 2035
A22: 42920 | B22: 1056983.6 | C22: 1167275.9 | D22: 2062388.1 | E22: 2166650.1 | F22: 3798380.1 | G22: 3883242.9 | H22: 3883968.5 | I22: 3883978 | J22: 3884107.8 | O22: =YEAR($A21) -> 2017 | P22: =$B21 -> 192663.34 | Q22: =C21-B21 -> 56428.344 | R22: =D21-C21 -> 251762.07 | S22: =E21-D21 -> 89526.998 | T22: =F21-E21 -> 470052.45 | U22: =G21-F21 -> 195.80013 | V22: =H21-G21 -> 4190.4946 | W22: =I21-H21 -> 652.06391 | X22: =J21-I21 -> 2287.235 | AB22: =$O22 -> 2017 | AC22: =P22*VLOOKUP(BO22,Exposure!$B$33:$C$53,2,FALSE)/VLOOKUP(AZ22,Exposure!$B$33:$C$53,2,FALSE) -> 298559.88 | AD22: =Q22*VLOOKUP(BP22,Exposure!$B$33:$C$53,2,FALSE)/VLOOKUP(BA22,Exposure!$B$33:$C$53,2,FALSE) -> 87231.105 | AE22: =R22*VLOOKUP(BQ22,Exposure!$B$33:$C$53,2,FALSE)/VLOOKUP(BB22,Exposure!$B$33:$C$53,2,FALSE) -> 390547.84 | AF22: =S22*VLOOKUP(BR22,Exposure!$B$33:$C$53,2,FALSE)/VLOOKUP(BC22,Exposure!$B$33:$C$53,2,FALSE) -> 140317.45 | AG22: =T22*VLOOKUP(BS22,Exposure!$B$33:$C$53,2,FALSE)/VLOOKUP(BD22,Exposure!$B$33:$C$53,2,FALSE) -> 732180.33 | AH22: =U22*VLOOKUP(BT22,Exposure!$B$33:$C$53,2,FALSE)/VLOOKUP(BE22,Exposure!$B$33:$C$53,2,FALSE) -> 283.62976 | AI22: =V22*VLOOKUP(BU22,Exposure!$B$33:$C$53,2,FALSE)/VLOOKUP(BF22,Exposure!$B$33:$C$53,2,FALSE) -> 5937.2069 | AJ22: =W22*VLOOKUP(BV22,Exposure!$B$33:$C$53,2,FALSE)/VLOOKUP(BG22,Exposure!$B$33:$C$53,2,FALSE) -> 911.99518 | AK22: =X22*VLOOKUP(BW22,Exposure!$B$33:$C$53,2,FALSE)/VLOOKUP(BH22,Exposure!$B$33:$C$53,2,FALSE) -> 3178.3486 | AZ22: =$O22 -> 2017 | BA22: =$AZ22+BA$1-1 -> 2018 | BB22: =$AZ22+BB$1-1 -> 2019 | BC22: =$AZ22+BC$1-1 -> 2020 | BD22: =$AZ22+BD$1-1 -> 2021 | BE22: =$AZ22+BE$1-1 -> 2022 | BF22: =$AZ22+BF$1-1 -> 2023 | BG22: =$AZ22+BG$1-1 -> 2024 | BH22: =$AZ22+BH$1-1 -> 2025 | BO22: 2027 | BP22: =$BO22+BP$1-1 -> 2028 | BQ22: =$BO22+BQ$1-1 -> 2029 | BR22: =$BO22+BR$1-1 -> 2030 | BS22: =$BO22+BS$1-1 -> 2031 | BT22: =$BO22+BT$1-1 -> 2032 | BU22: =$BO22+BU$1-1 -> 2033 | BV22: =$BO22+BV$1-1 -> 2034 | BW22: =$BO22+BW$1-1 -> 2035
A23: 42943 | B23: 321245.03 | C23: 356845.44 | D23: 397791.85 | E23: 796518.9 | F23: 1314135.2 | G23: 1389442 | H23: 1477040.5 | I23: 1479239.8 | J23: 1523440.9 | O23: =YEAR($A22) -> 2017 | P23: =$B22 -> 1056983.6 | Q23: =C22-B22 -> 110292.31 | R23: =D22-C22 -> 895112.16 | S23: =E22-D22 -> 104261.96 | T23: =F22-E22 -> 1631730 | U23: =G22-F22 -> 84862.845 | V23: =H22-G22 -> 725.57485 | W23: =I22-H22 -> 9.4653319 | X23: =J22-I22 -> 129.80258 | AB23: =$O23 -> 2017 | AC23: =P23*VLOOKUP(BO23,Exposure!$B$33:$C$53,2,FALSE)/VLOOKUP(AZ23,Exposure!$B$33:$C$53,2,FALSE) -> 1637949.9 | AD23: =Q23*VLOOKUP(BP23,Exposure!$B$33:$C$53,2,FALSE)/VLOOKUP(BA23,Exposure!$B$33:$C$53,2,FALSE) -> 170498 | AE23: =R23*VLOOKUP(BQ23,Exposure!$B$33:$C$53,2,FALSE)/VLOOKUP(BB23,Exposure!$B$33:$C$53,2,FALSE) -> 1388549.6 | AF23: =S23*VLOOKUP(BR23,Exposure!$B$33:$C$53,2,FALSE)/VLOOKUP(BC23,Exposure!$B$33:$C$53,2,FALSE) -> 163411.86 | AG23: =T23*VLOOKUP(BS23,Exposure!$B$33:$C$53,2,FALSE)/VLOOKUP(BD23,Exposure!$B$33:$C$53,2,FALSE) -> 2541675.1 | AH23: =U23*VLOOKUP(BT23,Exposure!$B$33:$C$53,2,FALSE)/VLOOKUP(BE23,Exposure!$B$33:$C$53,2,FALSE) -> 122929.58 | AI23: =V23*VLOOKUP(BU23,Exposure!$B$33:$C$53,2,FALSE)/VLOOKUP(BF23,Exposure!$B$33:$C$53,2,FALSE) -> 1028.0142 | AJ23: =W23*VLOOKUP(BV23,Exposure!$B$33:$C$53,2,FALSE)/VLOOKUP(BG23,Exposure!$B$33:$C$53,2,FALSE) -> 13.238483 | AK23: =X23*VLOOKUP(BW23,Exposure!$B$33:$C$53,2,FALSE)/VLOOKUP(BH23,Exposure!$B$33:$C$53,2,FALSE) -> 180.37406 | AZ23: =$O23 -> 2017 | BA23: =$AZ23+BA$1-1 -> 2018 | BB23: =$AZ23+BB$1-1 -> 2019 | BC23: =$AZ23+BC$1-1 -> 2020 | BD23: =$AZ23+BD$1-1 -> 2021 | BE23: =$AZ23+BE$1-1 -> 2022 | BF23: =$AZ23+BF$1-1 -> 2023 | BG23: =$AZ23+BG$1-1 -> 2024 | BH23: =$AZ23+BH$1-1 -> 2025 | BO23: 2027 | BP23: =$BO23+BP$1-1 -> 2028 | BQ23: =$BO23+BQ$1-1 -> 2029 | BR23: =$BO23+BR$1-1 -> 2030 | BS23: =$BO23+BS$1-1 -> 2031 | BT23: =$BO23+BT$1-1 -> 2032 | BU23: =$BO23+BU$1-1 -> 2033 | BV23: =$BO23+BV$1-1 -> 2034 | BW23: =$BO23+BW$1-1 -> 2035
A24: 43008 | B24: 2694.7167 | C24: 16477.935 | D24: 80432.26 | E24: 209615.05 | F24: 643984.99 | G24: 971640.13 | H24: 1011270.4 | I24: 1049042.2 | J24: 1061951.1 | O24: =YEAR($A23) -> 2017 | P24: =$B23 -> 321245.03 | Q24: =C23-B23 -> 35600.405 | R24: =D23-C23 -> 40946.412 | S24: =E23-D23 -> 398727.05 | T24: =F23-E23 -> 517616.35 | U24: =G23-F23 -> 75306.72 | V24: =H23-G23 -> 87598.486 | W24: =I23-H23 -> 2199.3282 | X24: =J23-I23 -> 44201.162 | AB24: =$O24 -> 2017 | AC24: =P24*VLOOKUP(BO24,Exposure!$B$33:$C$53,2,FALSE)/VLOOKUP(AZ24,Exposure!$B$33:$C$53,2,FALSE) -> 497815.91 | AD24: =Q24*VLOOKUP(BP24,Exposure!$B$33:$C$53,2,FALSE)/VLOOKUP(BA24,Exposure!$B$33:$C$53,2,FALSE) -> 55033.738 | AE24: =R24*VLOOKUP(BQ24,Exposure!$B$33:$C$53,2,FALSE)/VLOOKUP(BB24,Exposure!$B$33:$C$53,2,FALSE) -> 63518.435 | AF24: =S24*VLOOKUP(BR24,Exposure!$B$33:$C$53,2,FALSE)/VLOOKUP(BC24,Exposure!$B$33:$C$53,2,FALSE) -> 624932.85 | AG24: =T24*VLOOKUP(BS24,Exposure!$B$33:$C$53,2,FALSE)/VLOOKUP(BD24,Exposure!$B$33:$C$53,2,FALSE) -> 806268.56 | AH24: =U24*VLOOKUP(BT24,Exposure!$B$33:$C$53,2,FALSE)/VLOOKUP(BE24,Exposure!$B$33:$C$53,2,FALSE) -> 109086.89 | AI24: =V24*VLOOKUP(BU24,Exposure!$B$33:$C$53,2,FALSE)/VLOOKUP(BF24,Exposure!$B$33:$C$53,2,FALSE) -> 124111.92 | AJ24: =W24*VLOOKUP(BV24,Exposure!$B$33:$C$53,2,FALSE)/VLOOKUP(BG24,Exposure!$B$33:$C$53,2,FALSE) -> 3076.0432 | AK24: =X24*VLOOKUP(BW24,Exposure!$B$33:$C$53,2,FALSE)/VLOOKUP(BH24,Exposure!$B$33:$C$53,2,FALSE) -> 61422.068 | AZ24: =$O24 -> 2017 | BA24: =$AZ24+BA$1-1 -> 2018 | BB24: =$AZ24+BB$1-1 -> 2019 | BC24: =$AZ24+BC$1-1 -> 2020 | BD24: =$AZ24+BD$1-1 -> 2021 | BE24: =$AZ24+BE$1-1 -> 2022 | BF24: =$AZ24+BF$1-1 -> 2023 | BG24: =$AZ24+BG$1-1 -> 2024 | BH24: =$AZ24+BH$1-1 -> 2025 | BO24: 2027 | BP24: =$BO24+BP$1-1 -> 2028 | BQ24: =$BO24+BQ$1-1 -> 2029 | BR24: =$BO24+BR$1-1 -> 2030 | BS24: =$BO24+BS$1-1 -> 2031 | BT24: =$BO24+BT$1-1 -> 2032 | BU24: =$BO24+BU$1-1 -> 2033 | BV24: =$BO24+BV$1-1 -> 2034 | BW24: =$BO24+BW$1-1 -> 2035
A25: 43020 | B25: 41370.154 | C25: 110660.4 | D25: 516755.22 | E25: 521602.5 | F25: 551811.19 | G25: 601041.55 | H25: 729995.7 | I25: 733889.12 | J25: 735004.03 | O25: =YEAR($A24) -> 2017 | P25: =$B24 -> 2694.7167 | Q25: =C24-B24 -> 13783.219 | R25: =D24-C24 -> 63954.325 | S25: =E24-D24 -> 129182.79 | T25: =F24-E24 -> 434369.94 | U25: =G24-F24 -> 327655.14 | V25: =H24-G24 -> 39630.244 | W25: =I24-H24 -> 37771.846 | X25: =J24-I24 -> 12908.836 | AB25: =$O25 -> 2017 | AC25: =P25*VLOOKUP(BO25,Exposure!$B$33:$C$53,2,FALSE)/VLOOKUP(AZ25,Exposure!$B$33:$C$53,2,FALSE) -> 4175.8556 | AD25: =Q25*VLOOKUP(BP25,Exposure!$B$33:$C$53,2,FALSE)/VLOOKUP(BA25,Exposure!$B$33:$C$53,2,FALSE) -> 21307.118 | AE25: =R25*VLOOKUP(BQ25,Exposure!$B$33:$C$53,2,FALSE)/VLOOKUP(BB25,Exposure!$B$33:$C$53,2,FALSE) -> 99209.636 | AF25: =S25*VLOOKUP(BR25,Exposure!$B$33:$C$53,2,FALSE)/VLOOKUP(BC25,Exposure!$B$33:$C$53,2,FALSE) -> 202470.77 | AG25: =T25*VLOOKUP(BS25,Exposure!$B$33:$C$53,2,FALSE)/VLOOKUP(BD25,Exposure!$B$33:$C$53,2,FALSE) -> 676599.23 | AH25: =U25*VLOOKUP(BT25,Exposure!$B$33:$C$53,2,FALSE)/VLOOKUP(BE25,Exposure!$B$33:$C$53,2,FALSE) -> 474630.67 | AI25: =V25*VLOOKUP(BU25,Exposure!$B$33:$C$53,2,FALSE)/VLOOKUP(BF25,Exposure!$B$33:$C$53,2,FALSE) -> 56149.21 | AJ25: =W25*VLOOKUP(BV25,Exposure!$B$33:$C$53,2,FALSE)/VLOOKUP(BG25,Exposure!$B$33:$C$53,2,FALSE) -> 52828.782 | AK25: =X25*VLOOKUP(BW25,Exposure!$B$33:$C$53,2,FALSE)/VLOOKUP(BH25,Exposure!$B$33:$C$53,2,FALSE) -> 17938.158 | AZ25: =$O25 -> 2017 | BA25: =$AZ25+BA$1-1 -> 2018 | BB25: =$AZ25+BB$1-1 -> 2019 | BC25: =$AZ25+BC$1-1 -> 2020 | BD25: =$AZ25+BD$1-1 -> 2021 | BE25: =$AZ25+BE$1-1 -> 2022 | BF25: =$AZ25+BF$1-1 -> 2023 | BG25: =$AZ25+BG$1-1 -> 2024 | BH25: =$AZ25+BH$1-1 -> 2025 | BO25: 2027 | BP25: =$BO25+BP$1-1 -> 2028 | BQ25: =$BO25+BQ$1-1 -> 2029 | BR25: =$BO25+BR$1-1 -> 2030 | BS25: =$BO25+BS$1-1 -> 2031 | BT25: =$BO25+BT$1-1 -> 2032 | BU25: =$BO25+BU$1-1 -> 2033 | BV25: =$BO25+BV$1-1 -> 2034 | BW25: =$BO25+BW$1-1 -> 2035
A26: 43038 | B26: 123255.33 | C26: 134583.52 | D26: 154964.71 | E26: 2135490.8 | F26: 2151079.2 | G26: 2283965.2 | H26: 2284453.5 | I26: 2290084.6 | J26: 2290103.4 | O26: =YEAR($A25) -> 2017 | P26: =$B25 -> 41370.154 | Q26: =C25-B25 -> 69290.245 | R26: =D25-C25 -> 406094.82 | S26: =E25-D25 -> 4847.2831 | T26: =F25-E25 -> 30208.689 | U26: =G25-F25 -> 49230.363 | V26: =H25-G25 -> 128954.15 | W26: =I25-H25 -> 3893.4238 | X26: =J25-I25 -> 1114.91 | AB26: =$O26 -> 2017 | AC26: =P26*VLOOKUP(BO26,Exposure!$B$33:$C$53,2,FALSE)/VLOOKUP(AZ26,Exposure!$B$33:$C$53,2,FALSE) -> 64109.072 | AD26: =Q26*VLOOKUP(BP26,Exposure!$B$33:$C$53,2,FALSE)/VLOOKUP(BA26,Exposure!$B$33:$C$53,2,FALSE) -> 107113.98 | AE26: =R26*VLOOKUP(BQ26,Exposure!$B$33:$C$53,2,FALSE)/VLOOKUP(BB26,Exposure!$B$33:$C$53,2,FALSE) -> 629957.7 | AF26: =S26*VLOOKUP(BR26,Exposure!$B$33:$C$53,2,FALSE)/VLOOKUP(BC26,Exposure!$B$33:$C$53,2,FALSE) -> 7597.2434 | AG26: =T26*VLOOKUP(BS26,Exposure!$B$33:$C$53,2,FALSE)/VLOOKUP(BD26,Exposure!$B$33:$C$53,2,FALSE) -> 47054.765 | AH26: =U26*VLOOKUP(BT26,Exposure!$B$33:$C$53,2,FALSE)/VLOOKUP(BE26,Exposure!$B$33:$C$53,2,FALSE) -> 71313.516 | AI26: =V26*VLOOKUP(BU26,Exposure!$B$33:$C$53,2,FALSE)/VLOOKUP(BF26,Exposure!$B$33:$C$53,2,FALSE) -> 182705.75 | AJ26: =W26*VLOOKUP(BV26,Exposure!$B$33:$C$53,2,FALSE)/VLOOKUP(BG26,Exposure!$B$33:$C$53,2,FALSE) -> 5445.4536 | AK26: =X26*VLOOKUP(BW26,Exposure!$B$33:$C$53,2,FALSE)/VLOOKUP(BH26,Exposure!$B$33:$C$53,2,FALSE) -> 1549.2824 | AZ26: =$O26 -> 2017 | BA26: =$AZ26+BA$1-1 -> 2018 | BB26: =$AZ26+BB$1-1 -> 2019 | BC26: =$AZ26+BC$1-1 -> 2020 | BD26: =$AZ26+BD$1-1 -> 2021 | BE26: =$AZ26+BE$1-1 -> 2022 | BF26: =$AZ26+BF$1-1 -> 2023 | BG26: =$AZ26+BG$1-1 -> 2024 | BH26: =$AZ26+BH$1-1 -> 2025 | BO26: 2027 | BP26: =$BO26+BP$1-1 -> 2028 | BQ26: =$BO26+BQ$1-1 -> 2029 | BR26: =$BO26+BR$1-1 -> 2030 | BS26: =$BO26+BS$1-1 -> 2031 | BT26: =$BO26+BT$1-1 -> 2032 | BU26: =$BO26+BU$1-1 -> 2033 | BV26: =$BO26+BV$1-1 -> 2034 | BW26: =$BO26+BW$1-1 -> 2035
A27: 43053 | B27: 58611.766 | C27: 182911.28 | D27: 382492.92 | E27: 2067816.2 | F27: 2153530 | G27: 2876978.3 | H27: 3445373.1 | I27: 3446491.5 | J27: 3446675 | O27: =YEAR($A26) -> 2017 | P27: =$B26 -> 123255.33 | Q27: =C26-B26 -> 11328.186 | R27: =D26-C26 -> 20381.188 | S27: =E26-D26 -> 1980526.1 | T27: =F26-E26 -> 15588.406 | U27: =G26-F26 -> 132885.96 | V27: =H26-G26 -> 488.33437 | W27: =I26-H26 -> 5631.0549 | X27: =J26-I26 -> 18.825127 | AB27: =$O27 -> 2017 | AC27: =P27*VLOOKUP(BO27,Exposure!$B$33:$C$53,2,FALSE)/VLOOKUP(AZ27,Exposure!$B$33:$C$53,2,FALSE) -> 191002.07 | AD27: =Q27*VLOOKUP(BP27,Exposure!$B$33:$C$53,2,FALSE)/VLOOKUP(BA27,Exposure!$B$33:$C$53,2,FALSE) -> 17511.947 | AE27: =R27*VLOOKUP(BQ27,Exposure!$B$33:$C$53,2,FALSE)/VLOOKUP(BB27,Exposure!$B$33:$C$53,2,FALSE) -> 31616.474 | AF27: =S27*VLOOKUP(BR27,Exposure!$B$33:$C$53,2,FALSE)/VLOOKUP(BC27,Exposure!$B$33:$C$53,2,FALSE) -> 3104118.1 | AG27: =T27*VLOOKUP(BS27,Exposure!$B$33:$C$53,2,FALSE)/VLOOKUP(BD27,Exposure!$B$33:$C$53,2,FALSE) -> 24281.384 | AH27: =U27*VLOOKUP(BT27,Exposure!$B$33:$C$53,2,FALSE)/VLOOKUP(BE27,Exposure!$B$33:$C$53,2,FALSE) -> 192494.31 | AI27: =V27*VLOOKUP(BU27,Exposure!$B$33:$C$53,2,FALSE)/VLOOKUP(BF27,Exposure!$B$33:$C$53,2,FALSE) -> 691.88545 | AJ27: =W27*VLOOKUP(BV27,Exposure!$B$33:$C$53,2,FALSE)/VLOOKUP(BG27,Exposure!$B$33:$C$53,2,FALSE) -> 7875.7541 | AK27: =X27*VLOOKUP(BW27,Exposure!$B$33:$C$53,2,FALSE)/VLOOKUP(BH27,Exposure!$B$33:$C$53,2,FALSE) -> 26.159454 | AZ27: =$O27 -> 2017 | BA27: =$AZ27+BA$1-1 -> 2018 | BB27: =$AZ27+BB$1-1 -> 2019 | BC27: =$AZ27+BC$1-1 -> 2020 | BD27: =$AZ27+BD$1-1 -> 2021 | BE27: =$AZ27+BE$1-1 -> 2022 | BF27: =$AZ27+BF$1-1 -> 2023 | BG27: =$AZ27+BG$1-1 -> 2024 | BH27: =$AZ27+BH$1-1 -> 2025 | BO27: 2027 | BP27: =$BO27+BP$1-1 -> 2028 | BQ27: =$BO27+BQ$1-1 -> 2029 | BR27: =$BO27+BR$1-1 -> 2030 | BS27: =$BO27+BS$1-1 -> 2031 | BT27: =$BO27+BT$1-1 -> 2032 | BU27: =$BO27+BU$1-1 -> 2033 | BV27: =$BO27+BV$1-1 -> 2034 | BW27: =$BO27+BW$1-1 -> 2035
A28: 43055 | B28: 843676.92 | C28: 1758471.8 | D28: 1773841.3 | E28: 1837037 | F28: 3121214.3 | G28: 3127097.1 | H28: 3127119 | I28: 3127220.1 | J28: 3128570.4 | O28: =YEAR($A27) -> 2017 | P28: =$B27 -> 58611.766 | Q28: =C27-B27 -> 124299.51 | R28: =D27-C27 -> 199581.64 | S28: =E27-D27 -> 1685323.3 | T28: =F27-E27 -> 85713.765 | U28: =G27-F27 -> 723448.38 | V28: =H27-G27 -> 568394.77 | W28: =I27-H27 -> 1118.3888 | X28: =J27-I27 -> 183.46771 | AB28: =$O28 -> 2017 | AC28: =P28*VLOOKUP(BO28,Exposure!$B$33:$C$53,2,FALSE)/VLOOKUP(AZ28,Exposure!$B$33:$C$53,2,FALSE) -> 90827.459 | AD28: =Q28*VLOOKUP(BP28,Exposure!$B$33:$C$53,2,FALSE)/VLOOKUP(BA28,Exposure!$B$33:$C$53,2,FALSE) -> 192151.37 | AE28: =R28*VLOOKUP(BQ28,Exposure!$B$33:$C$53,2,FALSE)/VLOOKUP(BB28,Exposure!$B$33:$C$53,2,FALSE) -> 309602.55 | AF28: =S28*VLOOKUP(BR28,Exposure!$B$33:$C$53,2,FALSE)/VLOOKUP(BC28,Exposure!$B$33:$C$53,2,FALSE) -> 2641440.8 | AG28: =T28*VLOOKUP(BS28,Exposure!$B$33:$C$53,2,FALSE)/VLOOKUP(BD28,Exposure!$B$33:$C$53,2,FALSE) -> 133512.62 | AH28: =U28*VLOOKUP(BT28,Exposure!$B$33:$C$53,2,FALSE)/VLOOKUP(BE28,Exposure!$B$33:$C$53,2,FALSE) -> 1047964 | AI28: =V28*VLOOKUP(BU28,Exposure!$B$33:$C$53,2,FALSE)/VLOOKUP(BF28,Exposure!$B$33:$C$53,2,FALSE) -> 805317.2 | AJ28: =W28*VLOOKUP(BV28,Exposure!$B$33:$C$53,2,FALSE)/VLOOKUP(BG28,Exposure!$B$33:$C$53,2,FALSE) -> 1564.2105 | AK28: =X28*VLOOKUP(BW28,Exposure!$B$33:$C$53,2,FALSE)/VLOOKUP(BH28,Exposure!$B$33:$C$53,2,FALSE) -> 254.94729 | AZ28: =$O28 -> 2017 | BA28: =$AZ28+BA$1-1 -> 2018 | BB28: =$AZ28+BB$1-1 -> 2019 | BC28: =$AZ28+BC$1-1 -> 2020 | BD28: =$AZ28+BD$1-1 -> 2021 | BE28: =$AZ28+BE$1-1 -> 2022 | BF28: =$AZ28+BF$1-1 -> 2023 | BG28: =$AZ28+BG$1-1 -> 2024 | BH28: =$AZ28+BH$1-1 -> 2025 | BO28: 2027 | BP28: =$BO28+BP$1-1 -> 2028 | BQ28: =$BO28+BQ$1-1 -> 2029 | BR28: =$BO28+BR$1-1 -> 2030 | BS28: =$BO28+BS$1-1 -> 2031 | BT28: =$BO28+BT$1-1 -> 2032 | BU28: =$BO28+BU$1-1 -> 2033 | BV28: =$BO28+BV$1-1 -> 2034 | BW28: =$BO28+BW$1-1 -> 2035
A29: 43151 | B29: 182785 | C29: 194143.63 | D29: 217475.91 | E29: 282562.61 | F29: 1548554.2 | G29: 1595609.8 | H29: 1597194.2 | I29: 1602377.2 | O29: =YEAR($A28) -> 2017 | P29: =$B28 -> 843676.92 | Q29: =C28-B28 -> 914794.9 | R29: =D28-C28 -> 15369.449 | S29: =E28-D28 -> 63195.681 | T29: =F28-E28 -> 1284177.3 | U29: =G28-F28 -> 5882.8611 | V29: =H28-G28 -> 21.888143 | W29: =I28-H28 -> 101.11313 | X29: =J28-I28 -> 1350.2072 | AB29: =$O29 -> 2017 | AC29: =P29*VLOOKUP(BO29,Exposure!$B$33:$C$53,2,FALSE)/VLOOKUP(AZ29,Exposure!$B$33:$C$53,2,FALSE) -> 1307400.1 | AD29: =Q29*VLOOKUP(BP29,Exposure!$B$33:$C$53,2,FALSE)/VLOOKUP(BA29,Exposure!$B$33:$C$53,2,FALSE) -> 1414157.6 | AE29: =R29*VLOOKUP(BQ29,Exposure!$B$33:$C$53,2,FALSE)/VLOOKUP(BB29,Exposure!$B$33:$C$53,2,FALSE) -> 23841.976 | AF29: =S29*VLOOKUP(BR29,Exposure!$B$33:$C$53,2,FALSE)/VLOOKUP(BC29,Exposure!$B$33:$C$53,2,FALSE) -> 99047.851 | AG29: =T29*VLOOKUP(BS29,Exposure!$B$33:$C$53,2,FALSE)/VLOOKUP(BD29,Exposure!$B$33:$C$53,2,FALSE) -> 2000307.4 | AH29: =U29*VLOOKUP(BT29,Exposure!$B$33:$C$53,2,FALSE)/VLOOKUP(BE29,Exposure!$B$33:$C$53,2,FALSE) -> 8521.7229 | AI29: =V29*VLOOKUP(BU29,Exposure!$B$33:$C$53,2,FALSE)/VLOOKUP(BF29,Exposure!$B$33:$C$53,2,FALSE) -> 31.011717 | AJ29: =W29*VLOOKUP(BV29,Exposure!$B$33:$C$53,2,FALSE)/VLOOKUP(BG29,Exposure!$B$33:$C$53,2,FALSE) -> 141.41971 | AK29: =X29*VLOOKUP(BW29,Exposure!$B$33:$C$53,2,FALSE)/VLOOKUP(BH29,Exposure!$B$33:$C$53,2,FALSE) -> 1876.252 | AZ29: =$O29 -> 2017 | BA29: =$AZ29+BA$1-1 -> 2018 | BB29: =$AZ29+BB$1-1 -> 2019 | BC29: =$AZ29+BC$1-1 -> 2020 | BD29: =$AZ29+BD$1-1 -> 2021 | BE29: =$AZ29+BE$1-1 -> 2022 | BF29: =$AZ29+BF$1-1 -> 2023 | BG29: =$AZ29+BG$1-1 -> 2024 | BH29: =$AZ29+BH$1-1 -> 2025 | BO29: 2027 | BP29: =$BO29+BP$1-1 -> 2028 | BQ29: =$BO29+BQ$1-1 -> 2029 | BR29: =$BO29+BR$1-1 -> 2030 | BS29: =$BO29+BS$1-1 -> 2031 | BT29: =$BO29+BT$1-1 -> 2032 | BU29: =$BO29+BU$1-1 -> 2033 | BV29: =$BO29+BV$1-1 -> 2034 | BW29: =$BO29+BW$1-1 -> 2035
A30: 43161 | B30: 174941.3 | C30: 432036.37 | D30: 1522629.8 | E30: 1678520.6 | F30: 1701476.9 | G30: 1832924.5 | H30: 1836719 | I30: 1836719 | O30: =YEAR($A29) -> 2018 | P30: =$B29 -> 182785 | Q30: =C29-B29 -> 11358.629 | R30: =D29-C29 -> 23332.276 | S30: =E29-D29 -> 65086.706 | T30: =F29-E29 -> 1265991.6 | U30: =G29-F29 -> 47055.536 | V30: =H29-G29 -> 1584.4616 | W30: =I29-H29 -> 5183.0006 | AB30: =$O30 -> 2018 | AC30: =P30*VLOOKUP(BO30,Exposure!$B$33:$C$53,2,FALSE)/VLOOKUP(AZ30,Exposure!$B$33:$C$53,2,FALSE) -> 273535.88 | AD30: =Q30*VLOOKUP(BP30,Exposure!$B$33:$C$53,2,FALSE)/VLOOKUP(BA30,Exposure!$B$33:$C$53,2,FALSE) -> 17057.271 | AE30: =R30*VLOOKUP(BQ30,Exposure!$B$33:$C$53,2,FALSE)/VLOOKUP(BB30,Exposure!$B$33:$C$53,2,FALSE) -> 35400.911 | AF30: =S30*VLOOKUP(BR30,Exposure!$B$33:$C$53,2,FALSE)/VLOOKUP(BC30,Exposure!$B$33:$C$53,2,FALSE) -> 98143.99 | AG30: =T30*VLOOKUP(BS30,Exposure!$B$33:$C$53,2,FALSE)/VLOOKUP(BD30,Exposure!$B$33:$C$53,2,FALSE) -> 1775290.1 | AH30: =U30*VLOOKUP(BT30,Exposure!$B$33:$C$53,2,FALSE)/VLOOKUP(BE30,Exposure!$B$33:$C$53,2,FALSE) -> 64539.753 | AI30: =V30*VLOOKUP(BU30,Exposure!$B$33:$C$53,2,FALSE)/VLOOKUP(BF30,Exposure!$B$33:$C$53,2,FALSE) -> 2145.279 | AJ30: =W30*VLOOKUP(BV30,Exposure!$B$33:$C$53,2,FALSE)/VLOOKUP(BG30,Exposure!$B$33:$C$53,2,FALSE) -> 6972.2298 | AZ30: =$O30 -> 2018 | BA30: =$AZ30+BA$1-1 -> 2019 | BB30: =$AZ30+BB$1-1 -> 2020 | BC30: =$AZ30+BC$1-1 -> 2021 | BD30: =$AZ30+BD$1-1 -> 2022 | BE30: =$AZ30+BE$1-1 -> 2023 | BF30: =$AZ30+BF$1-1 -> 2024 | BG30: =$AZ30+BG$1-1 -> 2025 | BO30: 2027 | BP30: =$BO30+BP$1-1 -> 2028 | BQ30: =$BO30+BQ$1-1 -> 2029 | BR30: =$BO30+BR$1-1 -> 2030 | BS30: =$BO30+BS$1-1 -> 2031 | BT30: =$BO30+BT$1-1 -> 2032 | BU30: =$BO30+BU$1-1 -> 2033 | BV30: =$BO30+BV$1-1 -> 2034
A31: 43206 | B31: 24967.154 | C31: 50759.542 | D31: 1451556.4 | E31: 1451579.6 | F31: 1583507.7 | G31: 1599438.7 | H31: 1608003.8 | I31: 1612352.6 | O31: =YEAR($A30) -> 2018 | P31: =$B30 -> 174941.3 | Q31: =C30-B30 -> 257095.07 | R31: =D30-C30 -> 1090593.4 | S31: =E30-D30 -> 155890.83 | T31: =F30-E30 -> 22956.271 | U31: =G30-F30 -> 131447.65 | V31: =H30-G30 -> 3794.4796 | W31: =I30-H30 -> 0.0021189123 | AB31: =$O31 -> 2018 | AC31: =P31*VLOOKUP(BO31,Exposure!$B$33:$C$53,2,FALSE)/VLOOKUP(AZ31,Exposure!$B$33:$C$53,2,FALSE) -> 261797.87 | AD31: =Q31*VLOOKUP(BP31,Exposure!$B$33:$C$53,2,FALSE)/VLOOKUP(BA31,Exposure!$B$33:$C$53,2,FALSE) -> 386080.05 | AE31: =R31*VLOOKUP(BQ31,Exposure!$B$33:$C$53,2,FALSE)/VLOOKUP(BB31,Exposure!$B$33:$C$53,2,FALSE) -> 1654703.6 | AF31: =S31*VLOOKUP(BR31,Exposure!$B$33:$C$53,2,FALSE)/VLOOKUP(BC31,Exposure!$B$33:$C$53,2,FALSE) -> 235067.17 | AG31: =T31*VLOOKUP(BS31,Exposure!$B$33:$C$53,2,FALSE)/VLOOKUP(BD31,Exposure!$B$33:$C$53,2,FALSE) -> 32191.398 | AH31: =U31*VLOOKUP(BT31,Exposure!$B$33:$C$53,2,FALSE)/VLOOKUP(BE31,Exposure!$B$33:$C$53,2,FALSE) -> 180289.07 | AI31: =V31*VLOOKUP(BU31,Exposure!$B$33:$C$53,2,FALSE)/VLOOKUP(BF31,Exposure!$B$33:$C$53,2,FALSE) -> 5137.529 | AJ31: =W31*VLOOKUP(BV31,Exposure!$B$33:$C$53,2,FALSE)/VLOOKUP(BG31,Exposure!$B$33:$C$53,2,FALSE) -> 0.0028503843 | AZ31: =$O31 -> 2018 | BA31: =$AZ31+BA$1-1 -> 2019 | BB31: =$AZ31+BB$1-1 -> 2020 | BC31: =$AZ31+BC$1-1 -> 2021 | BD31: =$AZ31+BD$1-1 -> 2022 | BE31: =$AZ31+BE$1-1 -> 2023 | BF31: =$AZ31+BF$1-1 -> 2024 | BG31: =$AZ31+BG$1-1 -> 2025 | BO31: 2027 | BP31: =$BO31+BP$1-1 -> 2028 | BQ31: =$BO31+BQ$1-1 -> 2029 | BR31: =$BO31+BR$1-1 -> 2030 | BS31: =$BO31+BS$1-1 -> 2031 | BT31: =$BO31+BT$1-1 -> 2032 | BU31: =$BO31+BU$1-1 -> 2033 | BV31: =$BO31+BV$1-1 -> 2034
A32: 43249 | B32: 535852.54 | C32: 578018.02 | D32: 1274990.3 | E32: 1387201.2 | F32: 1387784.2 | G32: 1395168.3 | H32: 1404536.5 | I32: 1423744 | O32: =YEAR($A31) -> 2018 | P32: =$B31 -> 24967.154 | Q32: =C31-B31 -> 25792.388 | R32: =D31-C31 -> 1400796.9 | S32: =E31-D31 -> 23.150222 | T32: =F31-E31 -> 131928.11 | U32: =G31-F31 -> 15930.992 | V32: =H31-G31 -> 8565.0901 | W32: =I31-H31 -> 4348.8467 | AB32: =$O32 -> 2018 | AC32: =P32*VLOOKUP(BO32,Exposure!$B$33:$C$53,2,FALSE)/VLOOKUP(AZ32,Exposure!$B$33:$C$53,2,FALSE) -> 37363.09 | AD32: =Q32*VLOOKUP(BP32,Exposure!$B$33:$C$53,2,FALSE)/VLOOKUP(BA32,Exposure!$B$33:$C$53,2,FALSE) -> 38732.468 | AE32: =R32*VLOOKUP(BQ32,Exposure!$B$33:$C$53,2,FALSE)/VLOOKUP(BB32,Exposure!$B$33:$C$53,2,FALSE) -> 2125360 | AF32: =S32*VLOOKUP(BR32,Exposure!$B$33:$C$53,2,FALSE)/VLOOKUP(BC32,Exposure!$B$33:$C$53,2,FALSE) -> 34.908129 | AG32: =T32*VLOOKUP(BS32,Exposure!$B$33:$C$53,2,FALSE)/VLOOKUP(BD32,Exposure!$B$33:$C$53,2,FALSE) -> 185001.75 | AH32: =U32*VLOOKUP(BT32,Exposure!$B$33:$C$53,2,FALSE)/VLOOKUP(BE32,Exposure!$B$33:$C$53,2,FALSE) -> 21850.4 | AI32: =V32*VLOOKUP(BU32,Exposure!$B$33:$C$53,2,FALSE)/VLOOKUP(BF32,Exposure!$B$33:$C$53,2,FALSE) -> 11596.689 | AJ32: =W32*VLOOKUP(BV32,Exposure!$B$33:$C$53,2,FALSE)/VLOOKUP(BG32,Exposure!$B$33:$C$53,2,FALSE) -> 5850.1167 | AZ32: =$O32 -> 2018 | BA32: =$AZ32+BA$1-1 -> 2019 | BB32: =$AZ32+BB$1-1 -> 2020 | BC32: =$AZ32+BC$1-1 -> 2021 | BD32: =$AZ32+BD$1-1 -> 2022 | BE32: =$AZ32+BE$1-1 -> 2023 | BF32: =$AZ32+BF$1-1 -> 2024 | BG32: =$AZ32+BG$1-1 -> 2025 | BO32: 2027 | BP32: =$BO32+BP$1-1 -> 2028 | BQ32: =$BO32+BQ$1-1 -> 2029 | BR32: =$BO32+BR$1-1 -> 2030 | BS32: =$BO32+BS$1-1 -> 2031 | BT32: =$BO32+BT$1-1 -> 2032 | BU32: =$BO32+BU$1-1 -> 2033 | BV32: =$BO32+BV$1-1 -> 2034
A33: 43266 | B33: 618850.1 | C33: 695426.55 | D33: 833998.22 | E33: 1334111.7 | F33: 1334682.9 | G33: 1334895.6 | H33: 1342633.8 | I33: 1357785.4 | O33: =YEAR($A32) -> 2018 | P33: =$B32 -> 535852.54 | Q33: =C32-B32 -> 42165.482 | R33: =D32-C32 -> 696972.3 | S33: =E32-D32 -> 112210.86 | T33: =F32-E32 -> 583.04272 | U33: =G32-F32 -> 7384.0925 | V33: =H32-G32 -> 9368.1692 | W33: =I32-H32 -> 19207.538 | AB33: =$O33 -> 2018 | AC33: =P33*VLOOKUP(BO33,Exposure!$B$33:$C$53,2,FALSE)/VLOOKUP(AZ33,Exposure!$B$33:$C$53,2,FALSE) -> 801897.83 | AD33: =Q33*VLOOKUP(BP33,Exposure!$B$33:$C$53,2,FALSE)/VLOOKUP(BA33,Exposure!$B$33:$C$53,2,FALSE) -> 63319.968 | AE33: =R33*VLOOKUP(BQ33,Exposure!$B$33:$C$53,2,FALSE)/VLOOKUP(BB33,Exposure!$B$33:$C$53,2,FALSE) -> 1057481.7 | AF33: =S33*VLOOKUP(BR33,Exposure!$B$33:$C$53,2,FALSE)/VLOOKUP(BC33,Exposure!$B$33:$C$53,2,FALSE) -> 169202.31 | AG33: =T33*VLOOKUP(BS33,Exposure!$B$33:$C$53,2,FALSE)/VLOOKUP(BD33,Exposure!$B$33:$C$53,2,FALSE) -> 817.59621 | AH33: =U33*VLOOKUP(BT33,Exposure!$B$33:$C$53,2,FALSE)/VLOOKUP(BE33,Exposure!$B$33:$C$53,2,FALSE) -> 10127.767 | AI33: =V33*VLOOKUP(BU33,Exposure!$B$33:$C$53,2,FALSE)/VLOOKUP(BF33,Exposure!$B$33:$C$53,2,FALSE) -> 12684.016 | AJ33: =W33*VLOOKUP(BV33,Exposure!$B$33:$C$53,2,FALSE)/VLOOKUP(BG33,Exposure!$B$33:$C$53,2,FALSE) -> 25838.193 | AZ33: =$O33 -> 2018 | BA33: =$AZ33+BA$1-1 -> 2019 | BB33: =$AZ33+BB$1-1 -> 2020 | BC33: =$AZ33+BC$1-1 -> 2021 | BD33: =$AZ33+BD$1-1 -> 2022 | BE33: =$AZ33+BE$1-1 -> 2023 | BF33: =$AZ33+BF$1-1 -> 2024 | BG33: =$AZ33+BG$1-1 -> 2025 | BO33: 2027 | BP33: =$BO33+BP$1-1 -> 2028 | BQ33: =$BO33+BQ$1-1 -> 2029 | BR33: =$BO33+BR$1-1 -> 2030 | BS33: =$BO33+BS$1-1 -> 2031 | BT33: =$BO33+BT$1-1 -> 2032 | BU33: =$BO33+BU$1-1 -> 2033 | BV33: =$BO33+BV$1-1 -> 2034
A34: 43306 | B34: 62045.273 | C34: 296581.96 | D34: 324168.51 | E34: 526181.96 | F34: 609789.6 | G34: 677387.07 | H34: 722477.03 | I34: 882877.98 | O34: =YEAR($A33) -> 2018 | P34: =$B33 -> 618850.1 | Q34: =C33-B33 -> 76576.447 | R34: =D33-C33 -> 138571.67 | S34: =E33-D33 -> 500113.52 | T34: =F33-E33 -> 571.14107 | U34: =G33-F33 -> 212.74863 | V34: =H33-G33 -> 7738.1446 | W34: =I33-H33 -> 15151.604 | AB34: =$O34 -> 2018 | AC34: =P34*VLOOKUP(BO34,Exposure!$B$33:$C$53,2,FALSE)/VLOOKUP(AZ34,Exposure!$B$33:$C$53,2,FALSE) -> 926102.83 | AD34: =Q34*VLOOKUP(BP34,Exposure!$B$33:$C$53,2,FALSE)/VLOOKUP(BA34,Exposure!$B$33:$C$53,2,FALSE) -> 114994.97 | AE34: =R34*VLOOKUP(BQ34,Exposure!$B$33:$C$53,2,FALSE)/VLOOKUP(BB34,Exposure!$B$33:$C$53,2,FALSE) -> 210247.96 | AF34: =S34*VLOOKUP(BR34,Exposure!$B$33:$C$53,2,FALSE)/VLOOKUP(BC34,Exposure!$B$33:$C$53,2,FALSE) -> 754119.22 | AG34: =T34*VLOOKUP(BS34,Exposure!$B$33:$C$53,2,FALSE)/VLOOKUP(BD34,Exposure!$B$33:$C$53,2,FALSE) -> 800.90662 | AH34: =U34*VLOOKUP(BT34,Exposure!$B$33:$C$53,2,FALSE)/VLOOKUP(BE34,Exposure!$B$33:$C$53,2,FALSE) -> 291.7987 | AI34: =V34*VLOOKUP(BU34,Exposure!$B$33:$C$53,2,FALSE)/VLOOKUP(BF34,Exposure!$B$33:$C$53,2,FALSE) -> 10477.047 | AJ34: =W34*VLOOKUP(BV34,Exposure!$B$33:$C$53,2,FALSE)/VLOOKUP(BG34,Exposure!$B$33:$C$53,2,FALSE) -> 20382.106 | AZ34: =$O34 -> 2018 | BA34: =$AZ34+BA$1-1 -> 2019 | BB34: =$AZ34+BB$1-1 -> 2020 | BC34: =$AZ34+BC$1-1 -> 2021 | BD34: =$AZ34+BD$1-1 -> 2022 | BE34: =$AZ34+BE$1-1 -> 2023 | BF34: =$AZ34+BF$1-1 -> 2024 | BG34: =$AZ34+BG$1-1 -> 2025 | BO34: 2027 | BP34: =$BO34+BP$1-1 -> 2028 | BQ34: =$BO34+BQ$1-1 -> 2029 | BR34: =$BO34+BR$1-1 -> 2030 | BS34: =$BO34+BS$1-1 -> 2031 | BT34: =$BO34+BT$1-1 -> 2032 | BU34: =$BO34+BU$1-1 -> 2033 | BV34: =$BO34+BV$1-1 -> 2034
A35: 43316 | B35: 33866.786 | C35: 43530.066 | D35: 965061.53 | E35: 1051041.2 | F35: 1344540.5 | G35: 1349116 | H35: 1351881.1 | I35: 1356292.9 | O35: =YEAR($A34) -> 2018 | P35: =$B34 -> 62045.273 | Q35: =C34-B34 -> 234536.69 | R35: =D34-C34 -> 27586.548 | S35: =E34-D34 -> 202013.44 | T35: =F34-E34 -> 83607.646 | U35: =G34-F34 -> 67597.465 | V35: =H34-G34 -> 45089.963 | W35: =I34-H34 -> 160400.95 | AB35: =$O35 -> 2018 | AC35: =P35*VLOOKUP(BO35,Exposure!$B$33:$C$53,2,FALSE)/VLOOKUP(AZ35,Exposure!$B$33:$C$53,2,FALSE) -> 92850.115 | AD35: =Q35*VLOOKUP(BP35,Exposure!$B$33:$C$53,2,FALSE)/VLOOKUP(BA35,Exposure!$B$33:$C$53,2,FALSE) -> 352204.1 | AE35: =R35*VLOOKUP(BQ35,Exposure!$B$33:$C$53,2,FALSE)/VLOOKUP(BB35,Exposure!$B$33:$C$53,2,FALSE) -> 41855.708 | AF35: =S35*VLOOKUP(BR35,Exposure!$B$33:$C$53,2,FALSE)/VLOOKUP(BC35,Exposure!$B$33:$C$53,2,FALSE) -> 304615.28 | AG35: =T35*VLOOKUP(BS35,Exposure!$B$33:$C$53,2,FALSE)/VLOOKUP(BD35,Exposure!$B$33:$C$53,2,FALSE) -> 117242.34 | AH35: =U35*VLOOKUP(BT35,Exposure!$B$33:$C$53,2,FALSE)/VLOOKUP(BE35,Exposure!$B$33:$C$53,2,FALSE) -> 92714.357 | AI35: =V35*VLOOKUP(BU35,Exposure!$B$33:$C$53,2,FALSE)/VLOOKUP(BF35,Exposure!$B$33:$C$53,2,FALSE) -> 61049.477 | AJ35: =W35*VLOOKUP(BV35,Exposure!$B$33:$C$53,2,FALSE)/VLOOKUP(BG35,Exposure!$B$33:$C$53,2,FALSE) -> 215773.14 | AZ35: =$O35 -> 2018 | BA35: =$AZ35+BA$1-1 -> 2019 | BB35: =$AZ35+BB$1-1 -> 2020 | BC35: =$AZ35+BC$1-1 -> 2021 | BD35: =$AZ35+BD$1-1 -> 2022 | BE35: =$AZ35+BE$1-1 -> 2023 | BF35: =$AZ35+BF$1-1 -> 2024 | BG35: =$AZ35+BG$1-1 -> 2025 | BO35: 2027 | BP35: =$BO35+BP$1-1 -> 2028 | BQ35: =$BO35+BQ$1-1 -> 2029 | BR35: =$BO35+BR$1-1 -> 2030 | BS35: =$BO35+BS$1-1 -> 2031 | BT35: =$BO35+BT$1-1 -> 2032 | BU35: =$BO35+BU$1-1 -> 2033 | BV35: =$BO35+BV$1-1 -> 2034
A36: 43333 | B36: 149557.32 | C36: 521064.69 | D36: 636739.53 | E36: 636758.05 | F36: 1957072.3 | G36: 2150939.7 | H36: 2181462.8 | I36: 2188133 | O36: =YEAR($A35) -> 2018 | P36: =$B35 -> 33866.786 | Q36: =C35-B35 -> 9663.2796 | R36: =D35-C35 -> 921531.47 | S36: =E35-D35 -> 85979.649 | T36: =F35-E35 -> 293499.33 | U36: =G35-F35 -> 4575.5251 | V36: =H35-G35 -> 2765.0226 | W36: =I35-H35 -> 4411.8557 | AB36: =$O36 -> 2018 | AC36: =P36*VLOOKUP(BO36,Exposure!$B$33:$C$53,2,FALSE)/VLOOKUP(AZ36,Exposure!$B$33:$C$53,2,FALSE) -> 50681.298 | AD36: =Q36*VLOOKUP(BP36,Exposure!$B$33:$C$53,2,FALSE)/VLOOKUP(BA36,Exposure!$B$33:$C$53,2,FALSE) -> 14511.362 | AE36: =R36*VLOOKUP(BQ36,Exposure!$B$33:$C$53,2,FALSE)/VLOOKUP(BB36,Exposure!$B$33:$C$53,2,FALSE) -> 1398194.2 | AF36: =S36*VLOOKUP(BR36,Exposure!$B$33:$C$53,2,FALSE)/VLOOKUP(BC36,Exposure!$B$33:$C$53,2,FALSE) -> 129648.38 | AG36: =T36*VLOOKUP(BS36,Exposure!$B$33:$C$53,2,FALSE)/VLOOKUP(BD36,Exposure!$B$33:$C$53,2,FALSE) -> 411571.8 | AH36: =U36*VLOOKUP(BT36,Exposure!$B$33:$C$53,2,FALSE)/VLOOKUP(BE36,Exposure!$B$33:$C$53,2,FALSE) -> 6275.6328 | AI36: =V36*VLOOKUP(BU36,Exposure!$B$33:$C$53,2,FALSE)/VLOOKUP(BF36,Exposure!$B$33:$C$53,2,FALSE) -> 3743.6975 | AJ36: =W36*VLOOKUP(BV36,Exposure!$B$33:$C$53,2,FALSE)/VLOOKUP(BG36,Exposure!$B$33:$C$53,2,FALSE) -> 5934.8771 | AZ36: =$O36 -> 2018 | BA36: =$AZ36+BA$1-1 -> 2019 | BB36: =$AZ36+BB$1-1 -> 2020 | BC36: =$AZ36+BC$1-1 -> 2021 | BD36: =$AZ36+BD$1-1 -> 2022 | BE36: =$AZ36+BE$1-1 -> 2023 | BF36: =$AZ36+BF$1-1 -> 2024 | BG36: =$AZ36+BG$1-1 -> 2025 | BO36: 2027 | BP36: =$BO36+BP$1-1 -> 2028 | BQ36: =$BO36+BQ$1-1 -> 2029 | BR36: =$BO36+BR$1-1 -> 2030 | BS36: =$BO36+BS$1-1 -> 2031 | BT36: =$BO36+BT$1-1 -> 2032 | BU36: =$BO36+BU$1-1 -> 2033 | BV36: =$BO36+BV$1-1 -> 2034
A37: 43356 | B37: 4343.4275 | C37: 680606.66 | D37: 1648768.8 | E37: 1731765.2 | F37: 2230805.6 | G37: 2231446.1 | H37: 2272053.5 | I37: 2273325.8 | O37: =YEAR($A36) -> 2018 | P37: =$B36 -> 149557.32 | Q37: =C36-B36 -> 371507.37 | R37: =D36-C36 -> 115674.84 | S37: =E36-D36 -> 18.520788 | T37: =F36-E36 -> 1320314.3 | U37: =G36-F36 -> 193867.37 | V37: =H36-G36 -> 30523.136 | W37: =I36-H36 -> 6670.1558 | AB37: =$O37 -> 2018 | AC37: =P37*VLOOKUP(BO37,Exposure!$B$33:$C$53,2,FALSE)/VLOOKUP(AZ37,Exposure!$B$33:$C$53,2,FALSE) -> 223811 | AD37: =Q37*VLOOKUP(BP37,Exposure!$B$33:$C$53,2,FALSE)/VLOOKUP(BA37,Exposure!$B$33:$C$53,2,FALSE) -> 557893.18 | AE37: =R37*VLOOKUP(BQ37,Exposure!$B$33:$C$53,2,FALSE)/VLOOKUP(BB37,Exposure!$B$33:$C$53,2,FALSE) -> 175507.72 | AF37: =S37*VLOOKUP(BR37,Exposure!$B$33:$C$53,2,FALSE)/VLOOKUP(BC37,Exposure!$B$33:$C$53,2,FALSE) -> 27.927423 | AG37: =T37*VLOOKUP(BS37,Exposure!$B$33:$C$53,2,FALSE)/VLOOKUP(BD37,Exposure!$B$33:$C$53,2,FALSE) -> 1851466.3 | AH37: =U37*VLOOKUP(BT37,Exposure!$B$33:$C$53,2,FALSE)/VLOOKUP(BE37,Exposure!$B$33:$C$53,2,FALSE) -> 265901.82 | AI37: =V37*VLOOKUP(BU37,Exposure!$B$33:$C$53,2,FALSE)/VLOOKUP(BF37,Exposure!$B$33:$C$53,2,FALSE) -> 41326.746 | AJ37: =W37*VLOOKUP(BV37,Exposure!$B$33:$C$53,2,FALSE)/VLOOKUP(BG37,Exposure!$B$33:$C$53,2,FALSE) -> 8972.7674 | AZ37: =$O37 -> 2018 | BA37: =$AZ37+BA$1-1 -> 2019 | BB37: =$AZ37+BB$1-1 -> 2020 | BC37: =$AZ37+BC$1-1 -> 2021 | BD37: =$AZ37+BD$1-1 -> 2022 | BE37: =$AZ37+BE$1-1 -> 2023 | BF37: =$AZ37+BF$1-1 -> 2024 | BG37: =$AZ37+BG$1-1 -> 2025 | BO37: 2027 | BP37: =$BO37+BP$1-1 -> 2028 | BQ37: =$BO37+BQ$1-1 -> 2029 | BR37: =$BO37+BR$1-1 -> 2030 | BS37: =$BO37+BS$1-1 -> 2031 | BT37: =$BO37+BT$1-1 -> 2032 | BU37: =$BO37+BU$1-1 -> 2033 | BV37: =$BO37+BV$1-1 -> 2034
A38: 43365 | B38: 42418.563 | C38: 51439.393 | D38: 218140.64 | E38: 562318.82 | F38: 1067132.2 | G38: 1179309.6 | H38: 1179480.7 | I38: 1179699.4 | O38: =YEAR($A37) -> 2018 | P38: =$B37 -> 4343.4275 | Q38: =C37-B37 -> 676263.24 | R38: =D37-C37 -> 968162.17 | S38: =E37-D37 -> 82996.361 | T38: =F37-E37 -> 499040.36 | U38: =G37-F37 -> 640.57926 | V38: =H37-G37 -> 40607.354 | W38: =I37-H37 -> 1272.3513 | AB38: =$O38 -> 2018 | AC38: =P38*VLOOKUP(BO38,Exposure!$B$33:$C$53,2,FALSE)/VLOOKUP(AZ38,Exposure!$B$33:$C$53,2,FALSE) -> 6499.8948 | AD38: =Q38*VLOOKUP(BP38,Exposure!$B$33:$C$53,2,FALSE)/VLOOKUP(BA38,Exposure!$B$33:$C$53,2,FALSE) -> 1015545.5 | AE38: =R38*VLOOKUP(BQ38,Exposure!$B$33:$C$53,2,FALSE)/VLOOKUP(BB38,Exposure!$B$33:$C$53,2,FALSE) -> 1468944.7 | AF38: =S38*VLOOKUP(BR38,Exposure!$B$33:$C$53,2,FALSE)/VLOOKUP(BC38,Exposure!$B$33:$C$53,2,FALSE) -> 125149.89 | AG38: =T38*VLOOKUP(BS38,Exposure!$B$33:$C$53,2,FALSE)/VLOOKUP(BD38,Exposure!$B$33:$C$53,2,FALSE) -> 699800.37 | AH38: =U38*VLOOKUP(BT38,Exposure!$B$33:$C$53,2,FALSE)/VLOOKUP(BE38,Exposure!$B$33:$C$53,2,FALSE) -> 878.59647 | AI38: =V38*VLOOKUP(BU38,Exposure!$B$33:$C$53,2,FALSE)/VLOOKUP(BF38,Exposure!$B$33:$C$53,2,FALSE) -> 54980.255 | AJ38: =W38*VLOOKUP(BV38,Exposure!$B$33:$C$53,2,FALSE)/VLOOKUP(BG38,Exposure!$B$33:$C$53,2,FALSE) -> 1711.5811 | AZ38: =$O38 -> 2018 | BA38: =$AZ38+BA$1-1 -> 2019 | BB38: =$AZ38+BB$1-1 -> 2020 | BC38: =$AZ38+BC$1-1 -> 2021 | BD38: =$AZ38+BD$1-1 -> 2022 | BE38: =$AZ38+BE$1-1 -> 2023 | BF38: =$AZ38+BF$1-1 -> 2024 | BG38: =$AZ38+BG$1-1 -> 2025 | BO38: 2027 | BP38: =$BO38+BP$1-1 -> 2028 | BQ38: =$BO38+BQ$1-1 -> 2029 | BR38: =$BO38+BR$1-1 -> 2030 | BS38: =$BO38+BS$1-1 -> 2031 | BT38: =$BO38+BT$1-1 -> 2032 | BU38: =$BO38+BU$1-1 -> 2033 | BV38: =$BO38+BV$1-1 -> 2034
A39: 43388 | B39: 610960.45 | C39: 1347633 | D39: 1662026.5 | E39: 2365568.3 | F39: 2528170.8 | G39: 2548028.3 | H39: 2548066.6 | I39: 2548229.2 | O39: =YEAR($A38) -> 2018 | P39: =$B38 -> 42418.563 | Q39: =C38-B38 -> 9020.8303 | R39: =D38-C38 -> 166701.25 | S39: =E38-D38 -> 344178.17 | T39: =F38-E38 -> 504813.38 | U39: =G38-F38 -> 112177.37 | V39: =H38-G38 -> 171.16052 | W39: =I38-H38 -> 218.62593 | AB39: =$O39 -> 2018 | AC39: =P39*VLOOKUP(BO39,Exposure!$B$33:$C$53,2,FALSE)/VLOOKUP(AZ39,Exposure!$B$33:$C$53,2,FALSE) -> 63478.944 | AD39: =Q39*VLOOKUP(BP39,Exposure!$B$33:$C$53,2,FALSE)/VLOOKUP(BA39,Exposure!$B$33:$C$53,2,FALSE) -> 13546.595 | AE39: =R39*VLOOKUP(BQ39,Exposure!$B$33:$C$53,2,FALSE)/VLOOKUP(BB39,Exposure!$B$33:$C$53,2,FALSE) -> 252927.58 | AF39: =S39*VLOOKUP(BR39,Exposure!$B$33:$C$53,2,FALSE)/VLOOKUP(BC39,Exposure!$B$33:$C$53,2,FALSE) -> 518984.92 | AG39: =T39*VLOOKUP(BS39,Exposure!$B$33:$C$53,2,FALSE)/VLOOKUP(BD39,Exposure!$B$33:$C$53,2,FALSE) -> 707895.83 | AH39: =U39*VLOOKUP(BT39,Exposure!$B$33:$C$53,2,FALSE)/VLOOKUP(BE39,Exposure!$B$33:$C$53,2,FALSE) -> 153858.62 | AI39: =V39*VLOOKUP(BU39,Exposure!$B$33:$C$53,2,FALSE)/VLOOKUP(BF39,Exposure!$B$33:$C$53,2,FALSE) -> 231.74248 | AJ39: =W39*VLOOKUP(BV39,Exposure!$B$33:$C$53,2,FALSE)/VLOOKUP(BG39,Exposure!$B$33:$C$53,2,FALSE) -> 294.09802 | AZ39: =$O39 -> 2018 | BA39: =$AZ39+BA$1-1 -> 2019 | BB39: =$AZ39+BB$1-1 -> 2020 | BC39: =$AZ39+BC$1-1 -> 2021 | BD39: =$AZ39+BD$1-1 -> 2022 | BE39: =$AZ39+BE$1-1 -> 2023 | BF39: =$AZ39+BF$1-1 -> 2024 | BG39: =$AZ39+BG$1-1 -> 2025 | BO39: 2027 | BP39: =$BO39+BP$1-1 -> 2028 | BQ39: =$BO39+BQ$1-1 -> 2029 | BR39: =$BO39+BR$1-1 -> 2030 | BS39: =$BO39+BS$1-1 -> 2031 | BT39: =$BO39+BT$1-1 -> 2032 | BU39: =$BO39+BU$1-1 -> 2033 | BV39: =$BO39+BV$1-1 -> 2034
A40: 43466 | B40: 116234.76 | C40: 638960.98 | D40: 639821.19 | E40: 1329853.6 | F40: 1467604.4 | G40: 1516535.9 | H40: 1539238.1 | O40: =YEAR($A39) -> 2018 | P40: =$B39 -> 610960.45 | Q40: =C39-B39 -> 736672.55 | R40: =D39-C39 -> 314393.46 | S40: =E39-D39 -> 703541.87 | T40: =F39-E39 -> 162602.5 | U40: =G39-F39 -> 19857.47 | V40: =H39-G39 -> 38.31648 | W40: =I39-H39 -> 162.54792 | AB40: =$O40 -> 2018 | AC40: =P40*VLOOKUP(BO40,Exposure!$B$33:$C$53,2,FALSE)/VLOOKUP(AZ40,Exposure!$B$33:$C$53,2,FALSE) -> 914296.05 | AD40: =Q40*VLOOKUP(BP40,Exposure!$B$33:$C$53,2,FALSE)/VLOOKUP(BA40,Exposure!$B$33:$C$53,2,FALSE) -> 1106262.3 | AE40: =R40*VLOOKUP(BQ40,Exposure!$B$33:$C$53,2,FALSE)/VLOOKUP(BB40,Exposure!$B$33:$C$53,2,FALSE) -> 477013.69 | AF40: =S40*VLOOKUP(BR40,Exposure!$B$33:$C$53,2,FALSE)/VLOOKUP(BC40,Exposure!$B$33:$C$53,2,FALSE) -> 1060868 | AG40: =T40*VLOOKUP(BS40,Exposure!$B$33:$C$53,2,FALSE)/VLOOKUP(BD40,Exposure!$B$33:$C$53,2,FALSE) -> 228016.2 | AH40: =U40*VLOOKUP(BT40,Exposure!$B$33:$C$53,2,FALSE)/VLOOKUP(BE40,Exposure!$B$33:$C$53,2,FALSE) -> 27235.822 | AI40: =V40*VLOOKUP(BU40,Exposure!$B$33:$C$53,2,FALSE)/VLOOKUP(BF40,Exposure!$B$33:$C$53,2,FALSE) -> 51.87853 | AJ40: =W40*VLOOKUP(BV40,Exposure!$B$33:$C$53,2,FALSE)/VLOOKUP(BG40,Exposure!$B$33:$C$53,2,FALSE) -> 218.66126 | AZ40: =$O40 -> 2018 | BA40: =$AZ40+BA$1-1 -> 2019 | BB40: =$AZ40+BB$1-1 -> 2020 | BC40: =$AZ40+BC$1-1 -> 2021 | BD40: =$AZ40+BD$1-1 -> 2022 | BE40: =$AZ40+BE$1-1 -> 2023 | BF40: =$AZ40+BF$1-1 -> 2024 | BG40: =$AZ40+BG$1-1 -> 2025 | BO40: 2027 | BP40: =$BO40+BP$1-1 -> 2028 | BQ40: =$BO40+BQ$1-1 -> 2029 | BR40: =$BO40+BR$1-1 -> 2030 | BS40: =$BO40+BS$1-1 -> 2031 | BT40: =$BO40+BT$1-1 -> 2032 | BU40: =$BO40+BU$1-1 -> 2033 | BV40: =$BO40+BV$1-1 -> 2034
A41: 43485 | B41: 43067.006 | C41: 44079.95 | D41: 654335.98 | E41: 654763.06 | F41: 974979.76 | G41: 1019857.7 | H41: 1088256.9 | O41: =YEAR($A40) -> 2019 | P41: =$B40 -> 116234.76 | Q41: =C40-B40 -> 522726.22 | R41: =D40-C40 -> 860.20593 | S41: =E40-D40 -> 690032.37 | T41: =F40-E40 -> 137750.88 | U41: =G40-F40 -> 48931.464 | V41: =H40-G40 -> 22702.208 | AB41: =$O41 -> 2019 | AC41: =P41*VLOOKUP(BO41,Exposure!$B$33:$C$53,2,FALSE)/VLOOKUP(AZ41,Exposure!$B$33:$C$53,2,FALSE) -> 168973.78 | AD41: =Q41*VLOOKUP(BP41,Exposure!$B$33:$C$53,2,FALSE)/VLOOKUP(BA41,Exposure!$B$33:$C$53,2,FALSE) -> 767770.29 | AE41: =R41*VLOOKUP(BQ41,Exposure!$B$33:$C$53,2,FALSE)/VLOOKUP(BB41,Exposure!$B$33:$C$53,2,FALSE) -> 1255.6642 | AF41: =S41*VLOOKUP(BR41,Exposure!$B$33:$C$53,2,FALSE)/VLOOKUP(BC41,Exposure!$B$33:$C$53,2,FALSE) -> 936715.36 | AG41: =T41*VLOOKUP(BS41,Exposure!$B$33:$C$53,2,FALSE)/VLOOKUP(BD41,Exposure!$B$33:$C$53,2,FALSE) -> 182898.71 | AH41: =U41*VLOOKUP(BT41,Exposure!$B$33:$C$53,2,FALSE)/VLOOKUP(BE41,Exposure!$B$33:$C$53,2,FALSE) -> 64134.24 | AI41: =V41*VLOOKUP(BU41,Exposure!$B$33:$C$53,2,FALSE)/VLOOKUP(BF41,Exposure!$B$33:$C$53,2,FALSE) -> 29563.661 | AZ41: =$O41 -> 2019 | BA41: =$AZ41+BA$1-1 -> 2020 | BB41: =$AZ41+BB$1-1 -> 2021 | BC41: =$AZ41+BC$1-1 -> 2022 | BD41: =$AZ41+BD$1-1 -> 2023 | BE41: =$AZ41+BE$1-1 -> 2024 | BF41: =$AZ41+BF$1-1 -> 2025 | BO41: 2027 | BP41: =$BO41+BP$1-1 -> 2028 | BQ41: =$BO41+BQ$1-1 -> 2029 | BR41: =$BO41+BR$1-1 -> 2030 | BS41: =$BO41+BS$1-1 -> 2031 | BT41: =$BO41+BT$1-1 -> 2032 | BU41: =$BO41+BU$1-1 -> 2033
A42: 43528 | B42: 515258.79 | C42: 527450.79 | D42: 556739.12 | E42: 557431.76 | F42: 940767.61 | G42: 1226351.2 | H42: 1423268.6 | O42: =YEAR($A41) -> 2019 | P42: =$B41 -> 43067.006 | Q42: =C41-B41 -> 1012.9442 | R42: =D41-C41 -> 610256.03 | S42: =E41-D41 -> 427.08022 | T42: =F41-E41 -> 320216.69 | U42: =G41-F41 -> 44877.957 | V42: =H41-G41 -> 68399.169 | AB42: =$O42 -> 2019 | AC42: =P42*VLOOKUP(BO42,Exposure!$B$33:$C$53,2,FALSE)/VLOOKUP(AZ42,Exposure!$B$33:$C$53,2,FALSE) -> 62607.733 | AD42: =Q42*VLOOKUP(BP42,Exposure!$B$33:$C$53,2,FALSE)/VLOOKUP(BA42,Exposure!$B$33:$C$53,2,FALSE) -> 1487.793 | AE42: =R42*VLOOKUP(BQ42,Exposure!$B$33:$C$53,2,FALSE)/VLOOKUP(BB42,Exposure!$B$33:$C$53,2,FALSE) -> 890806.08 | AF42: =S42*VLOOKUP(BR42,Exposure!$B$33:$C$53,2,FALSE)/VLOOKUP(BC42,Exposure!$B$33:$C$53,2,FALSE) -> 579.75917 | AG42: =T42*VLOOKUP(BS42,Exposure!$B$33:$C$53,2,FALSE)/VLOOKUP(BD42,Exposure!$B$33:$C$53,2,FALSE) -> 425167.66 | AH42: =U42*VLOOKUP(BT42,Exposure!$B$33:$C$53,2,FALSE)/VLOOKUP(BE42,Exposure!$B$33:$C$53,2,FALSE) -> 58821.327 | AI42: =V42*VLOOKUP(BU42,Exposure!$B$33:$C$53,2,FALSE)/VLOOKUP(BF42,Exposure!$B$33:$C$53,2,FALSE) -> 89071.945 | AZ42: =$O42 -> 2019 | BA42: =$AZ42+BA$1-1 -> 2020 | BB42: =$AZ42+BB$1-1 -> 2021 | BC42: =$AZ42+BC$1-1 -> 2022 | BD42: =$AZ42+BD$1-1 -> 2023 | BE42: =$AZ42+BE$1-1 -> 2024 | BF42: =$AZ42+BF$1-1 -> 2025 | BO42: 2027 | BP42: =$BO42+BP$1-1 -> 2028 | BQ42: =$BO42+BQ$1-1 -> 2029 | BR42: =$BO42+BR$1-1 -> 2030 | BS42: =$BO42+BS$1-1 -> 2031 | BT42: =$BO42+BT$1-1 -> 2032 | BU42: =$BO42+BU$1-1 -> 2033
A43: 43587 | B43: 165353.22 | C43: 194542.92 | D43: 522075.77 | E43: 740486.81 | F43: 790706.79 | G43: 805035.08 | H43: 813342.77 | O43: =YEAR($A42) -> 2019 | P43: =$B42 -> 515258.79 | Q43: =C42-B42 -> 12191.997 | R43: =D42-C42 -> 29288.326 | S43: =E42-D42 -> 692.64089 | T43: =F42-E42 -> 383335.85 | U43: =G42-F42 -> 285583.63 | V43: =H42-G42 -> 196917.4 | AB43: =$O43 -> 2019 | AC43: =P43*VLOOKUP(BO43,Exposure!$B$33:$C$53,2,FALSE)/VLOOKUP(AZ43,Exposure!$B$33:$C$53,2,FALSE) -> 749046.38 | AD43: =Q43*VLOOKUP(BP43,Exposure!$B$33:$C$53,2,FALSE)/VLOOKUP(BA43,Exposure!$B$33:$C$53,2,FALSE) -> 17907.372 | AE43: =R43*VLOOKUP(BQ43,Exposure!$B$33:$C$53,2,FALSE)/VLOOKUP(BB43,Exposure!$B$33:$C$53,2,FALSE) -> 42752.906 | AF43: =S43*VLOOKUP(BR43,Exposure!$B$33:$C$53,2,FALSE)/VLOOKUP(BC43,Exposure!$B$33:$C$53,2,FALSE) -> 940.25641 | AG43: =T43*VLOOKUP(BS43,Exposure!$B$33:$C$53,2,FALSE)/VLOOKUP(BD43,Exposure!$B$33:$C$53,2,FALSE) -> 508974.11 | AH43: =U43*VLOOKUP(BT43,Exposure!$B$33:$C$53,2,FALSE)/VLOOKUP(BE43,Exposure!$B$33:$C$53,2,FALSE) -> 374313.12 | AI43: =V43*VLOOKUP(BU43,Exposure!$B$33:$C$53,2,FALSE)/VLOOKUP(BF43,Exposure!$B$33:$C$53,2,FALSE) -> 256433.17 | AZ43: =$O43 -> 2019 | BA43: =$AZ43+BA$1-1 -> 2020 | BB43: =$AZ43+BB$1-1 -> 2021 | BC43: =$AZ43+BC$1-1 -> 2022 | BD43: =$AZ43+BD$1-1 -> 2023 | BE43: =$AZ43+BE$1-1 -> 2024 | BF43: =$AZ43+BF$1-1 -> 2025 | BO43: 2027 | BP43: =$BO43+BP$1-1 -> 2028 | BQ43: =$BO43+BQ$1-1 -> 2029 | BR43: =$BO43+BR$1-1 -> 2030 | BS43: =$BO43+BS$1-1 -> 2031 | BT43: =$BO43+BT$1-1 -> 2032 | BU43: =$BO43+BU$1-1 -> 2033
A44: 43593 | B44: 48575.054 | C44: 112143.85 | D44: 183715.1 | E44: 215914.65 | F44: 642972.01 | G44: 1216974.2 | H44: 1316060.6 | O44: =YEAR($A43) -> 2019 | P44: =$B43 -> 165353.22 | Q44: =C43-B43 -> 29189.698 | R44: =D43-C43 -> 327532.85 | S44: =E43-D43 -> 218411.05 | T44: =F43-E43 -> 50219.975 | U44: =G43-F43 -> 14328.289 | V44: =H43-G43 -> 8307.6953 | AB44: =$O44 -> 2019 | AC44: =P44*VLOOKUP(BO44,Exposure!$B$33:$C$53,2,FALSE)/VLOOKUP(AZ44,Exposure!$B$33:$C$53,2,FALSE) -> 240378.68 | AD44: =Q44*VLOOKUP(BP44,Exposure!$B$33:$C$53,2,FALSE)/VLOOKUP(BA44,Exposure!$B$33:$C$53,2,FALSE) -> 42873.27 | AE44: =R44*VLOOKUP(BQ44,Exposure!$B$33:$C$53,2,FALSE)/VLOOKUP(BB44,Exposure!$B$33:$C$53,2,FALSE) -> 478107.94 | AF44: =S44*VLOOKUP(BR44,Exposure!$B$33:$C$53,2,FALSE)/VLOOKUP(BC44,Exposure!$B$33:$C$53,2,FALSE) -> 296491.86 | AG44: =T44*VLOOKUP(BS44,Exposure!$B$33:$C$53,2,FALSE)/VLOOKUP(BD44,Exposure!$B$33:$C$53,2,FALSE) -> 66679.563 | AH44: =U44*VLOOKUP(BT44,Exposure!$B$33:$C$53,2,FALSE)/VLOOKUP(BE44,Exposure!$B$33:$C$53,2,FALSE) -> 18780.021 | AI44: =V44*VLOOKUP(BU44,Exposure!$B$33:$C$53,2,FALSE)/VLOOKUP(BF44,Exposure!$B$33:$C$53,2,FALSE) -> 10818.59 | AZ44: =$O44 -> 2019 | BA44: =$AZ44+BA$1-1 -> 2020 | BB44: =$AZ44+BB$1-1 -> 2021 | BC44: =$AZ44+BC$1-1 -> 2022 | BD44: =$AZ44+BD$1-1 -> 2023 | BE44: =$AZ44+BE$1-1 -> 2024 | BF44: =$AZ44+BF$1-1 -> 2025 | BO44: 2027 | BP44: =$BO44+BP$1-1 -> 2028 | BQ44: =$BO44+BQ$1-1 -> 2029 | BR44: =$BO44+BR$1-1 -> 2030 | BS44: =$BO44+BS$1-1 -> 2031 | BT44: =$BO44+BT$1-1 -> 2032 | BU44: =$BO44+BU$1-1 -> 2033
A45: 43603 | B45: 21899.379 | C45: 105555.14 | D45: 267578.49 | E45: 318724.31 | F45: 453397.12 | G45: 939406.86 | H45: 939770.67 | O45: =YEAR($A44) -> 2019 | P45: =$B44 -> 48575.054 | Q45: =C44-B44 -> 63568.796 | R45: =D44-C44 -> 71571.254 | S45: =E44-D44 -> 32199.55 | T45: =F44-E44 -> 427057.35 | U45: =G44-F44 -> 574002.16 | V45: =H44-G44 -> 99086.419 | AB45: =$O45 -> 2019 | AC45: =P45*VLOOKUP(BO45,Exposure!$B$33:$C$53,2,FALSE)/VLOOKUP(AZ45,Exposure!$B$33:$C$53,2,FALSE) -> 70614.939 | AD45: =Q45*VLOOKUP(BP45,Exposure!$B$33:$C$53,2,FALSE)/VLOOKUP(BA45,Exposure!$B$33:$C$53,2,FALSE) -> 93368.633 | AE45: =R45*VLOOKUP(BQ45,Exposure!$B$33:$C$53,2,FALSE)/VLOOKUP(BB45,Exposure!$B$33:$C$53,2,FALSE) -> 104474.36 | AF45: =S45*VLOOKUP(BR45,Exposure!$B$33:$C$53,2,FALSE)/VLOOKUP(BC45,Exposure!$B$33:$C$53,2,FALSE) -> 43710.722 | AG45: =T45*VLOOKUP(BS45,Exposure!$B$33:$C$53,2,FALSE)/VLOOKUP(BD45,Exposure!$B$33:$C$53,2,FALSE) -> 567025.33 | AH45: =U45*VLOOKUP(BT45,Exposure!$B$33:$C$53,2,FALSE)/VLOOKUP(BE45,Exposure!$B$33:$C$53,2,FALSE) -> 752341.93 | AI45: =V45*VLOOKUP(BU45,Exposure!$B$33:$C$53,2,FALSE)/VLOOKUP(BF45,Exposure!$B$33:$C$53,2,FALSE) -> 129034.02 | AZ45: =$O45 -> 2019 | BA45: =$AZ45+BA$1-1 -> 2020 | BB45: =$AZ45+BB$1-1 -> 2021 | BC45: =$AZ45+BC$1-1 -> 2022 | BD45: =$AZ45+BD$1-1 -> 2023 | BE45: =$AZ45+BE$1-1 -> 2024 | BF45: =$AZ45+BF$1-1 -> 2025 | BO45: 2027 | BP45: =$BO45+BP$1-1 -> 2028 | BQ45: =$BO45+BQ$1-1 -> 2029 | BR45: =$BO45+BR$1-1 -> 2030 | BS45: =$BO45+BS$1-1 -> 2031 | BT45: =$BO45+BT$1-1 -> 2032 | BU45: =$BO45+BU$1-1 -> 2033
A46: 43609 | B46: 458728.97 | C46: 2058938.9 | D46: 2136071 | E46: 2653192.9 | F46: 2755962.9 | G46: 2795744.8 | H46: 2800740 | O46: =YEAR($A45) -> 2019 | P46: =$B45 -> 21899.379 | Q46: =C45-B45 -> 83655.762 | R46: =D45-C45 -> 162023.34 | S46: =E45-D45 -> 51145.823 | T46: =F45-E45 -> 134672.81 | U46: =G45-F45 -> 486009.74 | V46: =H45-G45 -> 363.81209 | AB46: =$O46 -> 2019 | AC46: =P46*VLOOKUP(BO46,Exposure!$B$33:$C$53,2,FALSE)/VLOOKUP(AZ46,Exposure!$B$33:$C$53,2,FALSE) -> 31835.751 | AD46: =Q46*VLOOKUP(BP46,Exposure!$B$33:$C$53,2,FALSE)/VLOOKUP(BA46,Exposure!$B$33:$C$53,2,FALSE) -> 122871.98 | AE46: =R46*VLOOKUP(BQ46,Exposure!$B$33:$C$53,2,FALSE)/VLOOKUP(BB46,Exposure!$B$33:$C$53,2,FALSE) -> 236509.55 | AF46: =S46*VLOOKUP(BR46,Exposure!$B$33:$C$53,2,FALSE)/VLOOKUP(BC46,Exposure!$B$33:$C$53,2,FALSE) -> 69430.189 | AG46: =T46*VLOOKUP(BS46,Exposure!$B$33:$C$53,2,FALSE)/VLOOKUP(BD46,Exposure!$B$33:$C$53,2,FALSE) -> 178811.8 | AH46: =U46*VLOOKUP(BT46,Exposure!$B$33:$C$53,2,FALSE)/VLOOKUP(BE46,Exposure!$B$33:$C$53,2,FALSE) -> 637010.68 | AI46: =V46*VLOOKUP(BU46,Exposure!$B$33:$C$53,2,FALSE)/VLOOKUP(BF46,Exposure!$B$33:$C$53,2,FALSE) -> 473.76965 | AZ46: =$O46 -> 2019 | BA46: =$AZ46+BA$1-1 -> 2020 | BB46: =$AZ46+BB$1-1 -> 2021 | BC46: =$AZ46+BC$1-1 -> 2022 | BD46: =$AZ46+BD$1-1 -> 2023 | BE46: =$AZ46+BE$1-1 -> 2024 | BF46: =$AZ46+BF$1-1 -> 2025 | BO46: 2027 | BP46: =$BO46+BP$1-1 -> 2028 | BQ46: =$BO46+BQ$1-1 -> 2029 | BR46: =$BO46+BR$1-1 -> 2030 | BS46: =$BO46+BS$1-1 -> 2031 | BT46: =$BO46+BT$1-1 -> 2032 | BU46: =$BO46+BU$1-1 -> 2033
A47: 43650 | B47: 356443.81 | C47: 446399.55 | D47: 581614.99 | E47: 590534.52 | F47: 703199.13 | G47: 732558.74 | H47: 757135.45 | O47: =YEAR($A46) -> 2019 | P47: =$B46 -> 458728.97 | Q47: =C46-B46 -> 1600210 | R47: =D46-C46 -> 77132.04 | S47: =E46-D46 -> 517121.99 | T47: =F46-E46 -> 102769.99 | U47: =G46-F46 -> 39781.861 | V47: =H46-G46 -> 4995.1707 | AB47: =$O47 -> 2019 | AC47: =P47*VLOOKUP(BO47,Exposure!$B$33:$C$53,2,FALSE)/VLOOKUP(AZ47,Exposure!$B$33:$C$53,2,FALSE) -> 666867.36 | AD47: =Q47*VLOOKUP(BP47,Exposure!$B$33:$C$53,2,FALSE)/VLOOKUP(BA47,Exposure!$B$33:$C$53,2,FALSE) -> 2350357.8 | AE47: =R47*VLOOKUP(BQ47,Exposure!$B$33:$C$53,2,FALSE)/VLOOKUP(BB47,Exposure!$B$33:$C$53,2,FALSE) -> 112591.58 | AF47: =S47*VLOOKUP(BR47,Exposure!$B$33:$C$53,2,FALSE)/VLOOKUP(BC47,Exposure!$B$33:$C$53,2,FALSE) -> 701990.41 | AG47: =T47*VLOOKUP(BS47,Exposure!$B$33:$C$53,2,FALSE)/VLOOKUP(BD47,Exposure!$B$33:$C$53,2,FALSE) -> 136452.84 | AH47: =U47*VLOOKUP(BT47,Exposure!$B$33:$C$53,2,FALSE)/VLOOKUP(BE47,Exposure!$B$33:$C$53,2,FALSE) -> 52141.898 | AI47: =V47*VLOOKUP(BU47,Exposure!$B$33:$C$53,2,FALSE)/VLOOKUP(BF47,Exposure!$B$33:$C$53,2,FALSE) -> 6504.8973 | AZ47: =$O47 -> 2019 | BA47: =$AZ47+BA$1-1 -> 2020 | BB47: =$AZ47+BB$1-1 -> 2021 | BC47: =$AZ47+BC$1-1 -> 2022 | BD47: =$AZ47+BD$1-1 -> 2023 | BE47: =$AZ47+BE$1-1 -> 2024 | BF47: =$AZ47+BF$1-1 -> 2025 | BO47: 2027 | BP47: =$BO47+BP$1-1 -> 2028 | BQ47: =$BO47+BQ$1-1 -> 2029 | BR47: =$BO47+BR$1-1 -> 2030 | BS47: =$BO47+BS$1-1 -> 2031 | BT47: =$BO47+BT$1-1 -> 2032 | BU47: =$BO47+BU$1-1 -> 2033
A48: 43651 | B48: 41159.651 | C48: 98885.856 | D48: 442502.92 | E48: 1242824.1 | F48: 1316032.7 | G48: 1427891.5 | H48: 1678733.8 | O48: =YEAR($A47) -> 2019 | P48: =$B47 -> 356443.81 | Q48: =C47-B47 -> 89955.74 | R48: =D47-C47 -> 135215.44 | S48: =E47-D47 -> 8919.53 | T48: =F47-E47 -> 112664.62 | U48: =G47-F47 -> 29359.61 | V48: =H47-G47 -> 24576.708 | AB48: =$O48 -> 2019 | AC48: =P48*VLOOKUP(BO48,Exposure!$B$33:$C$53,2,FALSE)/VLOOKUP(AZ48,Exposure!$B$33:$C$53,2,FALSE) -> 518172.51 | AD48: =Q48*VLOOKUP(BP48,Exposure!$B$33:$C$53,2,FALSE)/VLOOKUP(BA48,Exposure!$B$33:$C$53,2,FALSE) -> 132125.27 | AE48: =R48*VLOOKUP(BQ48,Exposure!$B$33:$C$53,2,FALSE)/VLOOKUP(BB48,Exposure!$B$33:$C$53,2,FALSE) -> 197377.38 | AF48: =S48*VLOOKUP(BR48,Exposure!$B$33:$C$53,2,FALSE)/VLOOKUP(BC48,Exposure!$B$33:$C$53,2,FALSE) -> 12108.216 | AG48: =T48*VLOOKUP(BS48,Exposure!$B$33:$C$53,2,FALSE)/VLOOKUP(BD48,Exposure!$B$33:$C$53,2,FALSE) -> 149590.43 | AH48: =U48*VLOOKUP(BT48,Exposure!$B$33:$C$53,2,FALSE)/VLOOKUP(BE48,Exposure!$B$33:$C$53,2,FALSE) -> 38481.502 | AI48: =V48*VLOOKUP(BU48,Exposure!$B$33:$C$53,2,FALSE)/VLOOKUP(BF48,Exposure!$B$33:$C$53,2,FALSE) -> 32004.704 | AZ48: =$O48 -> 2019 | BA48: =$AZ48+BA$1-1 -> 2020 | BB48: =$AZ48+BB$1-1 -> 2021 | BC48: =$AZ48+BC$1-1 -> 2022 | BD48: =$AZ48+BD$1-1 -> 2023 | BE48: =$AZ48+BE$1-1 -> 2024 | BF48: =$AZ48+BF$1-1 -> 2025 | BO48: 2027 | BP48: =$BO48+BP$1-1 -> 2028 | BQ48: =$BO48+BQ$1-1 -> 2029 | BR48: =$BO48+BR$1-1 -> 2030 | BS48: =$BO48+BS$1-1 -> 2031 | BT48: =$BO48+BT$1-1 -> 2032 | BU48: =$BO48+BU$1-1 -> 2033
A49: 43657 | B49: 207931.15 | C49: 1267562.2 | D49: 2517997.1 | E49: 2562922.3 | F49: 2619204.4 | G49: 2635756.9 | H49: 2640256.7 | O49: =YEAR($A48) -> 2019 | P49: =$B48 -> 41159.651 | Q49: =C48-B48 -> 57726.205 | R49: =D48-C48 -> 343617.06 | S49: =E48-D48 -> 800321.19 | T49: =F48-E48 -> 73208.582 | U49: =G48-F48 -> 111858.85 | V49: =H48-G48 -> 250842.21 | AB49: =$O49 -> 2019 | AC49: =P49*VLOOKUP(BO49,Exposure!$B$33:$C$53,2,FALSE)/VLOOKUP(AZ49,Exposure!$B$33:$C$53,2,FALSE) -> 59834.956 | AD49: =Q49*VLOOKUP(BP49,Exposure!$B$33:$C$53,2,FALSE)/VLOOKUP(BA49,Exposure!$B$33:$C$53,2,FALSE) -> 84787.147 | AE49: =R49*VLOOKUP(BQ49,Exposure!$B$33:$C$53,2,FALSE)/VLOOKUP(BB49,Exposure!$B$33:$C$53,2,FALSE) -> 501586.47 | AF49: =S49*VLOOKUP(BR49,Exposure!$B$33:$C$53,2,FALSE)/VLOOKUP(BC49,Exposure!$B$33:$C$53,2,FALSE) -> 1086431.9 | AG49: =T49*VLOOKUP(BS49,Exposure!$B$33:$C$53,2,FALSE)/VLOOKUP(BD49,Exposure!$B$33:$C$53,2,FALSE) -> 97202.683 | AH49: =U49*VLOOKUP(BT49,Exposure!$B$33:$C$53,2,FALSE)/VLOOKUP(BE49,Exposure!$B$33:$C$53,2,FALSE) -> 146612.87 | AI49: =V49*VLOOKUP(BU49,Exposure!$B$33:$C$53,2,FALSE)/VLOOKUP(BF49,Exposure!$B$33:$C$53,2,FALSE) -> 326656.07 | AZ49: =$O49 -> 2019 | BA49: =$AZ49+BA$1-1 -> 2020 | BB49: =$AZ49+BB$1-1 -> 2021 | BC49: =$AZ49+BC$1-1 -> 2022 | BD49: =$AZ49+BD$1-1 -> 2023 | BE49: =$AZ49+BE$1-1 -> 2024 | BF49: =$AZ49+BF$1-1 -> 2025 | BO49: 2027 | BP49: =$BO49+BP$1-1 -> 2028 | BQ49: =$BO49+BQ$1-1 -> 2029 | BR49: =$BO49+BR$1-1 -> 2030 | BS49: =$BO49+BS$1-1 -> 2031 | BT49: =$BO49+BT$1-1 -> 2032 | BU49: =$BO49+BU$1-1 -> 2033
A50: 43664 | B50: 358230.82 | C50: 528027.88 | D50: 529904.91 | E50: 836892.14 | F50: 1455605.2 | G50: 1473578.8 | H50: 1474286 | O50: =YEAR($A49) -> 2019 | P50: =$B49 -> 207931.15 | Q50: =C49-B49 -> 1059631.1 | R50: =D49-C49 -> 1250434.9 | S50: =E49-D49 -> 44925.152 | T50: =F49-E49 -> 56282.141 | U50: =G49-F49 -> 16552.486 | V50: =H49-G49 -> 4499.7789 | AB50: =$O50 -> 2019 | AC50: =P50*VLOOKUP(BO50,Exposure!$B$33:$C$53,2,FALSE)/VLOOKUP(AZ50,Exposure!$B$33:$C$53,2,FALSE) -> 302275.43 | AD50: =Q50*VLOOKUP(BP50,Exposure!$B$33:$C$53,2,FALSE)/VLOOKUP(BA50,Exposure!$B$33:$C$53,2,FALSE) -> 1556365.9 | AE50: =R50*VLOOKUP(BQ50,Exposure!$B$33:$C$53,2,FALSE)/VLOOKUP(BB50,Exposure!$B$33:$C$53,2,FALSE) -> 1825291.3 | AF50: =S50*VLOOKUP(BR50,Exposure!$B$33:$C$53,2,FALSE)/VLOOKUP(BC50,Exposure!$B$33:$C$53,2,FALSE) -> 60985.66 | AG50: =T50*VLOOKUP(BS50,Exposure!$B$33:$C$53,2,FALSE)/VLOOKUP(BD50,Exposure!$B$33:$C$53,2,FALSE) -> 74728.603 | AH50: =U50*VLOOKUP(BT50,Exposure!$B$33:$C$53,2,FALSE)/VLOOKUP(BE50,Exposure!$B$33:$C$53,2,FALSE) -> 21695.265 | AI50: =V50*VLOOKUP(BU50,Exposure!$B$33:$C$53,2,FALSE)/VLOOKUP(BF50,Exposure!$B$33:$C$53,2,FALSE) -> 5859.7797 | AZ50: =$O50 -> 2019 | BA50: =$AZ50+BA$1-1 -> 2020 | BB50: =$AZ50+BB$1-1 -> 2021 | BC50: =$AZ50+BC$1-1 -> 2022 | BD50: =$AZ50+BD$1-1 -> 2023 | BE50: =$AZ50+BE$1-1 -> 2024 | BF50: =$AZ50+BF$1-1 -> 2025 | BO50: 2027 | BP50: =$BO50+BP$1-1 -> 2028 | BQ50: =$BO50+BQ$1-1 -> 2029 | BR50: =$BO50+BR$1-1 -> 2030 | BS50: =$BO50+BS$1-1 -> 2031 | BT50: =$BO50+BT$1-1 -> 2032 | BU50: =$BO50+BU$1-1 -> 2033
A51: 43670 | B51: 39126.81 | C51: 228323.32 | D51: 242037.24 | E51: 375264.81 | F51: 649914.47 | G51: 735325 | H51: 735668.69 | O51: =YEAR($A50) -> 2019 | P51: =$B50 -> 358230.82 | Q51: =C50-B50 -> 169797.06 | R51: =D50-C50 -> 1877.0228 | S51: =E50-D50 -> 306987.23 | T51: =F50-E50 -> 618713.07 | U51: =G50-F50 -> 17973.633 | V51: =H50-G50 -> 707.17301 | AB51: =$O51 -> 2019 | AC51: =P51*VLOOKUP(BO51,Exposure!$B$33:$C$53,2,FALSE)/VLOOKUP(AZ51,Exposure!$B$33:$C$53,2,FALSE) -> 520770.34 | AD51: =Q51*VLOOKUP(BP51,Exposure!$B$33:$C$53,2,FALSE)/VLOOKUP(BA51,Exposure!$B$33:$C$53,2,FALSE) -> 249394.68 | AE51: =R51*VLOOKUP(BQ51,Exposure!$B$33:$C$53,2,FALSE)/VLOOKUP(BB51,Exposure!$B$33:$C$53,2,FALSE) -> 2739.9374 | AF51: =S51*VLOOKUP(BR51,Exposure!$B$33:$C$53,2,FALSE)/VLOOKUP(BC51,Exposure!$B$33:$C$53,2,FALSE) -> 416733.57 | AG51: =T51*VLOOKUP(BS51,Exposure!$B$33:$C$53,2,FALSE)/VLOOKUP(BD51,Exposure!$B$33:$C$53,2,FALSE) -> 821496.18 | AH51: =U51*VLOOKUP(BT51,Exposure!$B$33:$C$53,2,FALSE)/VLOOKUP(BE51,Exposure!$B$33:$C$53,2,FALSE) -> 23557.956 | AI51: =V51*VLOOKUP(BU51,Exposure!$B$33:$C$53,2,FALSE)/VLOOKUP(BF51,Exposure!$B$33:$C$53,2,FALSE) -> 920.90703 | AZ51: =$O51 -> 2019 | BA51: =$AZ51+BA$1-1 -> 2020 | BB51: =$AZ51+BB$1-1 -> 2021 | BC51: =$AZ51+BC$1-1 -> 2022 | BD51: =$AZ51+BD$1-1 -> 2023 | BE51: =$AZ51+BE$1-1 -> 2024 | BF51: =$AZ51+BF$1-1 -> 2025 | BO51: 2027 | BP51: =$BO51+BP$1-1 -> 2028 | BQ51: =$BO51+BQ$1-1 -> 2029 | BR51: =$BO51+BR$1-1 -> 2030 | BS51: =$BO51+BS$1-1 -> 2031 | BT51: =$BO51+BT$1-1 -> 2032 | BU51: =$BO51+BU$1-1 -> 2033
A52: 43697 | B52: 7952.8202 | C52: 787681.64 | D52: 1643255.9 | E52: 3144788.4 | F52: 3276086.8 | G52: 3621176.2 | H52: 3656466.1 | O52: =YEAR($A51) -> 2019 | P52: =$B51 -> 39126.81 | Q52: =C51-B51 -> 189196.51 | R52: =D51-C51 -> 13713.916 | S52: =E51-D51 -> 133227.58 | T52: =F51-E51 -> 274649.66 | U52: =G51-F51 -> 85410.526 | V52: =H51-G51 -> 343.68974 | AB52: =$O52 -> 2019 | AC52: =P52*VLOOKUP(BO52,Exposure!$B$33:$C$53,2,FALSE)/VLOOKUP(AZ52,Exposure!$B$33:$C$53,2,FALSE) -> 56879.758 | AD52: =Q52*VLOOKUP(BP52,Exposure!$B$33:$C$53,2,FALSE)/VLOOKUP(BA52,Exposure!$B$33:$C$53,2,FALSE) -> 277888.22 | AE52: =R52*VLOOKUP(BQ52,Exposure!$B$33:$C$53,2,FALSE)/VLOOKUP(BB52,Exposure!$B$33:$C$53,2,FALSE) -> 20018.549 | AF52: =S52*VLOOKUP(BR52,Exposure!$B$33:$C$53,2,FALSE)/VLOOKUP(BC52,Exposure!$B$33:$C$53,2,FALSE) -> 180855.74 | AG52: =T52*VLOOKUP(BS52,Exposure!$B$33:$C$53,2,FALSE)/VLOOKUP(BD52,Exposure!$B$33:$C$53,2,FALSE) -> 364666.04 | AH52: =U52*VLOOKUP(BT52,Exposure!$B$33:$C$53,2,FALSE)/VLOOKUP(BE52,Exposure!$B$33:$C$53,2,FALSE) -> 111947.18 | AI52: =V52*VLOOKUP(BU52,Exposure!$B$33:$C$53,2,FALSE)/VLOOKUP(BF52,Exposure!$B$33:$C$53,2,FALSE) -> 447.56558 | AZ52: =$O52 -> 2019 | BA52: =$AZ52+BA$1-1 -> 2020 | BB52: =$AZ52+BB$1-1 -> 2021 | BC52: =$AZ52+BC$1-1 -> 2022 | BD52: =$AZ52+BD$1-1 -> 2023 | BE52: =$AZ52+BE$1-1 -> 2024 | BF52: =$AZ52+BF$1-1 -> 2025 | BO52: 2027 | BP52: =$BO52+BP$1-1 -> 2028 | BQ52: =$BO52+BQ$1-1 -> 2029 | BR52: =$BO52+BR$1-1 -> 2030 | BS52: =$BO52+BS$1-1 -> 2031 | BT52: =$BO52+BT$1-1 -> 2032 | BU52: =$BO52+BU$1-1 -> 2033
... A54: 43813 | B54: 122748.72 | C54: 417902.1 | D54: 470333.57 | E54: 478417.65 | F54: 481976.7 | G54: 495376.72 | H54: 503771.91 | O54: =YEAR($A53) -> 2019 | P54: =$B53 -> 263306.17 | Q54: =C53-B53 -> 26624.931 | R54: =D53-C53 -> 2137.0932 | S54: =E53-D53 -> 1910647.2 | T54: =F53-E53 -> 516477.4 | U54: =G53-F53 -> 108604.4 | V54: =H53-G53 -> 138883.22 | AB54: =$O54 -> 2019 | AC54: =P54*VLOOKUP(BO54,Exposure!$B$33:$C$53,2,FALSE)/VLOOKUP(AZ54,Exposure!$B$33:$C$53,2,FALSE) -> 382775.67 | AD54: =Q54*VLOOKUP(BP54,Exposure!$B$33:$C$53,2,FALSE)/VLOOKUP(BA54,Exposure!$B$33:$C$53,2,FALSE) -> 39106.19 | AE54: =R54*VLOOKUP(BQ54,Exposure!$B$33:$C$53,2,FALSE)/VLOOKUP(BB54,Exposure!$B$33:$C$53,2,FALSE) -> 3119.5687 | AF54: =S54*VLOOKUP(BR54,Exposure!$B$33:$C$53,2,FALSE)/VLOOKUP(BC54,Exposure!$B$33:$C$53,2,FALSE) -> 2593693.7 | AG54: =T54*VLOOKUP(BS54,Exposure!$B$33:$C$53,2,FALSE)/VLOOKUP(BD54,Exposure!$B$33:$C$53,2,FALSE) -> 685752.78 | AH54: =U54*VLOOKUP(BT54,Exposure!$B$33:$C$53,2,FALSE)/VLOOKUP(BE54,Exposure!$B$33:$C$53,2,FALSE) -> 142347.27 | AI54: =V54*VLOOKUP(BU54,Exposure!$B$33:$C$53,2,FALSE)/VLOOKUP(BF54,Exposure!$B$33:$C$53,2,FALSE) -> 180858.91 | AZ54: =$O54 -> 2019 | BA54: =$AZ54+BA$1-1 -> 2020 | BB54: =$AZ54+BB$1-1 -> 2021 | BC54: =$AZ54+BC$1-1 -> 2022 | BD54: =$AZ54+BD$1-1 -> 2023 | BE54: =$AZ54+BE$1-1 -> 2024 | BF54: =$AZ54+BF$1-1 -> 2025 | BO54: 2027 | BP54: =$BO54+BP$1-1 -> 2028 | BQ54: =$BO54+BQ$1-1 -> 2029 | BR54: =$BO54+BR$1-1 -> 2030 | BS54: =$BO54+BS$1-1 -> 2031 | BT54: =$BO54+BT$1-1 -> 2032 | BU54: =$BO54+BU$1-1 -> 2033
A55: 43883 | B55: 95837.963 | C55: 397918.86 | D55: 409184.44 | E55: 965273.28 | F55: 1045158.7 | G55: 1055868.8 | O55: =YEAR($A54) -> 2019 | P55: =$B54 -> 122748.72 | Q55: =C54-B54 -> 295153.38 | R55: =D54-C54 -> 52431.478 | S55: =E54-D54 -> 8084.075 | T55: =F54-E54 -> 3559.048 | U55: =G54-F54 -> 13400.02 | V55: =H54-G54 -> 8395.1961 | AB55: =$O55 -> 2019 | AC55: =P55*VLOOKUP(BO55,Exposure!$B$33:$C$53,2,FALSE)/VLOOKUP(AZ55,Exposure!$B$33:$C$53,2,FALSE) -> 178443.3 | AD55: =Q55*VLOOKUP(BP55,Exposure!$B$33:$C$53,2,FALSE)/VLOOKUP(BA55,Exposure!$B$33:$C$53,2,FALSE) -> 433515.64 | AE55: =R55*VLOOKUP(BQ55,Exposure!$B$33:$C$53,2,FALSE)/VLOOKUP(BB55,Exposure!$B$33:$C$53,2,FALSE) -> 76535.548 | AF55: =S55*VLOOKUP(BR55,Exposure!$B$33:$C$53,2,FALSE)/VLOOKUP(BC55,Exposure!$B$33:$C$53,2,FALSE) -> 10974.09 | AG55: =T55*VLOOKUP(BS55,Exposure!$B$33:$C$53,2,FALSE)/VLOOKUP(BD55,Exposure!$B$33:$C$53,2,FALSE) -> 4725.5253 | AH55: =U55*VLOOKUP(BT55,Exposure!$B$33:$C$53,2,FALSE)/VLOOKUP(BE55,Exposure!$B$33:$C$53,2,FALSE) -> 17563.343 | AI55: =V55*VLOOKUP(BU55,Exposure!$B$33:$C$53,2,FALSE)/VLOOKUP(BF55,Exposure!$B$33:$C$53,2,FALSE) -> 10932.537 | AZ55: =$O55 -> 2019 | BA55: =$AZ55+BA$1-1 -> 2020 | BB55: =$AZ55+BB$1-1 -> 2021 | BC55: =$AZ55+BC$1-1 -> 2022 | BD55: =$AZ55+BD$1-1 -> 2023 | BE55: =$AZ55+BE$1-1 -> 2024 | BF55: =$AZ55+BF$1-1 -> 2025 | BO55: 2027 | BP55: =$BO55+BP$1-1 -> 2028 | BQ55: =$BO55+BQ$1-1 -> 2029 | BR55: =$BO55+BR$1-1 -> 2030 | BS55: =$BO55+BS$1-1 -> 2031 | BT55: =$BO55+BT$1-1 -> 2032 | BU55: =$BO55+BU$1-1 -> 2033
A56: 43884 | B56: 152343.28 | C56: 1463565.6 | D56: 2220205.2 | E56: 2226988.8 | F56: 2239987.2 | G56: 2593116 | O56: =YEAR($A55) -> 2020 | P56: =$B55 -> 95837.963 | Q56: =C55-B55 -> 302080.9 | R56: =D55-C55 -> 11265.583 | S56: =E55-D55 -> 556088.84 | T56: =F55-E55 -> 79885.455 | U56: =G55-F55 -> 10710.099 | AB56: =$O56 -> 2020 | AC56: =P56*VLOOKUP(BO56,Exposure!$B$33:$C$53,2,FALSE)/VLOOKUP(AZ56,Exposure!$B$33:$C$53,2,FALSE) -> 136268.12 | AD56: =Q56*VLOOKUP(BP56,Exposure!$B$33:$C$53,2,FALSE)/VLOOKUP(BA56,Exposure!$B$33:$C$53,2,FALSE) -> 426868.43 | AE56: =R56*VLOOKUP(BQ56,Exposure!$B$33:$C$53,2,FALSE)/VLOOKUP(BB56,Exposure!$B$33:$C$53,2,FALSE) -> 14804.424 | AF56: =S56*VLOOKUP(BR56,Exposure!$B$33:$C$53,2,FALSE)/VLOOKUP(BC56,Exposure!$B$33:$C$53,2,FALSE) -> 714759.79 | AG56: =T56*VLOOKUP(BS56,Exposure!$B$33:$C$53,2,FALSE)/VLOOKUP(BD56,Exposure!$B$33:$C$53,2,FALSE) -> 101360.59 | AH56: =U56*VLOOKUP(BT56,Exposure!$B$33:$C$53,2,FALSE)/VLOOKUP(BE56,Exposure!$B$33:$C$53,2,FALSE) -> 13501.54 | AZ56: =$O56 -> 2020 | BA56: =$AZ56+BA$1-1 -> 2021 | BB56: =$AZ56+BB$1-1 -> 2022 | BC56: =$AZ56+BC$1-1 -> 2023 | BD56: =$AZ56+BD$1-1 -> 2024 | BE56: =$AZ56+BE$1-1 -> 2025 | BO56: 2027 | BP56: =$BO56+BP$1-1 -> 2028 | BQ56: =$BO56+BQ$1-1 -> 2029 | BR56: =$BO56+BR$1-1 -> 2030 | BS56: =$BO56+BS$1-1 -> 2031 | BT56: =$BO56+BT$1-1 -> 2032
A57: 43910 | B57: 193200.97 | C57: 235139.18 | D57: 974463.29 | E57: 1160364.5 | F57: 1713148.1 | G57: 2254006.4 | O57: =YEAR($A56) -> 2020 | P57: =$B56 -> 152343.28 | Q57: =C56-B56 -> 1311222.3 | R57: =D56-C56 -> 756639.58 | S57: =E56-D56 -> 6783.6254 | T57: =F56-E56 -> 12998.448 | U57: =G56-F56 -> 353128.78 | AB57: =$O57 -> 2020 | AC57: =P57*VLOOKUP(BO57,Exposure!$B$33:$C$53,2,FALSE)/VLOOKUP(AZ57,Exposure!$B$33:$C$53,2,FALSE) -> 216610.75 | AD57: =Q57*VLOOKUP(BP57,Exposure!$B$33:$C$53,2,FALSE)/VLOOKUP(BA57,Exposure!$B$33:$C$53,2,FALSE) -> 1852879.2 | AE57: =R57*VLOOKUP(BQ57,Exposure!$B$33:$C$53,2,FALSE)/VLOOKUP(BB57,Exposure!$B$33:$C$53,2,FALSE) -> 994321.68 | AF57: =S57*VLOOKUP(BR57,Exposure!$B$33:$C$53,2,FALSE)/VLOOKUP(BC57,Exposure!$B$33:$C$53,2,FALSE) -> 8719.2231 | AG57: =T57*VLOOKUP(BS57,Exposure!$B$33:$C$53,2,FALSE)/VLOOKUP(BD57,Exposure!$B$33:$C$53,2,FALSE) -> 16492.744 | AH57: =U57*VLOOKUP(BT57,Exposure!$B$33:$C$53,2,FALSE)/VLOOKUP(BE57,Exposure!$B$33:$C$53,2,FALSE) -> 445166.93 | AZ57: =$O57 -> 2020 | BA57: =$AZ57+BA$1-1 -> 2021 | BB57: =$AZ57+BB$1-1 -> 2022 | BC57: =$AZ57+BC$1-1 -> 2023 | BD57: =$AZ57+BD$1-1 -> 2024 | BE57: =$AZ57+BE$1-1 -> 2025 | BO57: 2027 | BP57: =$BO57+BP$1-1 -> 2028 | BQ57: =$BO57+BQ$1-1 -> 2029 | BR57: =$BO57+BR$1-1 -> 2030 | BS57: =$BO57+BS$1-1 -> 2031 | BT57: =$BO57+BT$1-1 -> 2032
A58: 43948 | B58: 44462.794 | C58: 126965.47 | D58: 501059.93 | E58: 501059.96 | F58: 502640.25 | G58: 520322.01 | O58: =YEAR($A57) -> 2020 | P58: =$B57 -> 193200.97 | Q58: =C57-B57 -> 41938.202 | R58: =D57-C57 -> 739324.12 | S58: =E57-D57 -> 185901.19 | T58: =F57-E57 -> 552783.58 | U58: =G57-F57 -> 540858.38 | AB58: =$O58 -> 2020 | AC58: =P58*VLOOKUP(BO58,Exposure!$B$33:$C$53,2,FALSE)/VLOOKUP(AZ58,Exposure!$B$33:$C$53,2,FALSE) -> 274704.65 | AD58: =Q58*VLOOKUP(BP58,Exposure!$B$33:$C$53,2,FALSE)/VLOOKUP(BA58,Exposure!$B$33:$C$53,2,FALSE) -> 59262.584 | AE58: =R58*VLOOKUP(BQ58,Exposure!$B$33:$C$53,2,FALSE)/VLOOKUP(BB58,Exposure!$B$33:$C$53,2,FALSE) -> 971566.94 | AF58: =S58*VLOOKUP(BR58,Exposure!$B$33:$C$53,2,FALSE)/VLOOKUP(BC58,Exposure!$B$33:$C$53,2,FALSE) -> 238945.08 | AG58: =T58*VLOOKUP(BS58,Exposure!$B$33:$C$53,2,FALSE)/VLOOKUP(BD58,Exposure!$B$33:$C$53,2,FALSE) -> 701385.13 | AH58: =U58*VLOOKUP(BT58,Exposure!$B$33:$C$53,2,FALSE)/VLOOKUP(BE58,Exposure!$B$33:$C$53,2,FALSE) -> 681825.68 | AZ58: =$O58 -> 2020 | BA58: =$AZ58+BA$1-1 -> 2021 | BB58: =$AZ58+BB$1-1 -> 2022 | BC58: =$AZ58+BC$1-1 -> 2023 | BD58: =$AZ58+BD$1-1 -> 2024 | BE58: =$AZ58+BE$1-1 -> 2025 | BO58: 2027 | BP58: =$BO58+BP$1-1 -> 2028 | BQ58: =$BO58+BQ$1-1 -> 2029 | BR58: =$BO58+BR$1-1 -> 2030 | BS58: =$BO58+BS$1-1 -> 2031 | BT58: =$BO58+BT$1-1 -> 2032
A59: 44053 | B59: 2271.0372 | C59: 117094.97 | D59: 228295.26 | E59: 931955.64 | F59: 998252.94 | G59: 1022716.3 | O59: =YEAR($A58) -> 2020 | P59: =$B58 -> 44462.794 | Q59: =C58-B58 -> 82502.679 | R59: =D58-C58 -> 374094.45 | S59: =E58-D58 -> 0.034674763 | T59: =F58-E58 -> 1580.2939 | U59: =G58-F58 -> 17681.758 | AB59: =$O59 -> 2020 | AC59: =P59*VLOOKUP(BO59,Exposure!$B$33:$C$53,2,FALSE)/VLOOKUP(AZ59,Exposure!$B$33:$C$53,2,FALSE) -> 63219.848 | AD59: =Q59*VLOOKUP(BP59,Exposure!$B$33:$C$53,2,FALSE)/VLOOKUP(BA59,Exposure!$B$33:$C$53,2,FALSE) -> 116583.97 | AE59: =R59*VLOOKUP(BQ59,Exposure!$B$33:$C$53,2,FALSE)/VLOOKUP(BB59,Exposure!$B$33:$C$53,2,FALSE) -> 491608.2 | AF59: =S59*VLOOKUP(BR59,Exposure!$B$33:$C$53,2,FALSE)/VLOOKUP(BC59,Exposure!$B$33:$C$53,2,FALSE) -> 0.044568646 | AG59: =T59*VLOOKUP(BS59,Exposure!$B$33:$C$53,2,FALSE)/VLOOKUP(BD59,Exposure!$B$33:$C$53,2,FALSE) -> 2005.115 | AH59: =U59*VLOOKUP(BT59,Exposure!$B$33:$C$53,2,FALSE)/VLOOKUP(BE59,Exposure!$B$33:$C$53,2,FALSE) -> 22290.265 | AZ59: =$O59 -> 2020 | BA59: =$AZ59+BA$1-1 -> 2021 | BB59: =$AZ59+BB$1-1 -> 2022 | BC59: =$AZ59+BC$1-1 -> 2023 | BD59: =$AZ59+BD$1-1 -> 2024 | BE59: =$AZ59+BE$1-1 -> 2025 | BO59: 2027 | BP59: =$BO59+BP$1-1 -> 2028 | BQ59: =$BO59+BQ$1-1 -> 2029 | BR59: =$BO59+BR$1-1 -> 2030 | BS59: =$BO59+BS$1-1 -> 2031 | BT59: =$BO59+BT$1-1 -> 2032
A60: 44177 | B60: 1644.4273 | C60: 100206.12 | D60: 300629.48 | E60: 362837.22 | F60: 363112.12 | G60: 445566.47 | O60: =YEAR($A59) -> 2020 | P60: =$B59 -> 2271.0372 | Q60: =C59-B59 -> 114823.93 | R60: =D59-C59 -> 111200.29 | S60: =E59-D59 -> 703660.39 | T60: =F59-E59 -> 66297.296 | U60: =G59-F59 -> 24463.319 | AB60: =$O60 -> 2020 | AC60: =P60*VLOOKUP(BO60,Exposure!$B$33:$C$53,2,FALSE)/VLOOKUP(AZ60,Exposure!$B$33:$C$53,2,FALSE) -> 3229.0959 | AD60: =Q60*VLOOKUP(BP60,Exposure!$B$33:$C$53,2,FALSE)/VLOOKUP(BA60,Exposure!$B$33:$C$53,2,FALSE) -> 162256.9 | AE60: =R60*VLOOKUP(BQ60,Exposure!$B$33:$C$53,2,FALSE)/VLOOKUP(BB60,Exposure!$B$33:$C$53,2,FALSE) -> 146131.48 | AF60: =S60*VLOOKUP(BR60,Exposure!$B$33:$C$53,2,FALSE)/VLOOKUP(BC60,Exposure!$B$33:$C$53,2,FALSE) -> 904438.49 | AG60: =T60*VLOOKUP(BS60,Exposure!$B$33:$C$53,2,FALSE)/VLOOKUP(BD60,Exposure!$B$33:$C$53,2,FALSE) -> 84119.607 | AH60: =U60*VLOOKUP(BT60,Exposure!$B$33:$C$53,2,FALSE)/VLOOKUP(BE60,Exposure!$B$33:$C$53,2,FALSE) -> 30839.346 | AZ60: =$O60 -> 2020 | BA60: =$AZ60+BA$1-1 -> 2021 | BB60: =$AZ60+BB$1-1 -> 2022 | BC60: =$AZ60+BC$1-1 -> 2023 | BD60: =$AZ60+BD$1-1 -> 2024 | BE60: =$AZ60+BE$1-1 -> 2025 | BO60: 2027 | BP60: =$BO60+BP$1-1 -> 2028 | BQ60: =$BO60+BQ$1-1 -> 2029 | BR60: =$BO60+BR$1-1 -> 2030 | BS60: =$BO60+BS$1-1 -> 2031 | BT60: =$BO60+BT$1-1 -> 2032
A61: 44301 | B61: 160802.59 | C61: 738222.49 | D61: 742998.53 | E61: 2081300.1 | F61: 2081364.9 | O61: =YEAR($A60) -> 2020 | P61: =$B60 -> 1644.4273 | Q61: =C60-B60 -> 98561.688 | R61: =D60-C60 -> 200423.36 | S61: =E60-D60 -> 62207.745 | T61: =F60-E60 -> 274.89655 | U61: =G60-F60 -> 82454.352 | AB61: =$O61 -> 2020 | AC61: =P61*VLOOKUP(BO61,Exposure!$B$33:$C$53,2,FALSE)/VLOOKUP(AZ61,Exposure!$B$33:$C$53,2,FALSE) -> 2338.1447 | AD61: =Q61*VLOOKUP(BP61,Exposure!$B$33:$C$53,2,FALSE)/VLOOKUP(BA61,Exposure!$B$33:$C$53,2,FALSE) -> 139276.84 | AE61: =R61*VLOOKUP(BQ61,Exposure!$B$33:$C$53,2,FALSE)/VLOOKUP(BB61,Exposure!$B$33:$C$53,2,FALSE) -> 263382.07 | AF61: =S61*VLOOKUP(BR61,Exposure!$B$33:$C$53,2,FALSE)/VLOOKUP(BC61,Exposure!$B$33:$C$53,2,FALSE) -> 79957.719 | AG61: =T61*VLOOKUP(BS61,Exposure!$B$33:$C$53,2,FALSE)/VLOOKUP(BD61,Exposure!$B$33:$C$53,2,FALSE) -> 348.79536 | AH61: =U61*VLOOKUP(BT61,Exposure!$B$33:$C$53,2,FALSE)/VLOOKUP(BE61,Exposure!$B$33:$C$53,2,FALSE) -> 103944.94 | AZ61: =$O61 -> 2020 | BA61: =$AZ61+BA$1-1 -> 2021 | BB61: =$AZ61+BB$1-1 -> 2022 | BC61: =$AZ61+BC$1-1 -> 2023 | BD61: =$AZ61+BD$1-1 -> 2024 | BE61: =$AZ61+BE$1-1 -> 2025 | BO61: 2027 | BP61: =$BO61+BP$1-1 -> 2028 | BQ61: =$BO61+BQ$1-1 -> 2029 | BR61: =$BO61+BR$1-1 -> 2030 | BS61: =$BO61+BS$1-1 -> 2031 | BT61: =$BO61+BT$1-1 -> 2032
A62: 44329 | B62: 98733.531 | C62: 799837.57 | D62: 969577.12 | E62: 1991763.2 | F62: 2034536.7 | O62: =YEAR($A61) -> 2021 | P62: =$B61 -> 160802.59 | Q62: =C61-B61 -> 577419.91 | R62: =D61-C61 -> 4776.0351 | S62: =E61-D61 -> 1338301.6 | T62: =F61-E61 -> 64.83383 | AB62: =$O62 -> 2021 | AC62: =P62*VLOOKUP(BO62,Exposure!$B$33:$C$53,2,FALSE)/VLOOKUP(AZ62,Exposure!$B$33:$C$53,2,FALSE) -> 219970.02 | AD62: =Q62*VLOOKUP(BP62,Exposure!$B$33:$C$53,2,FALSE)/VLOOKUP(BA62,Exposure!$B$33:$C$53,2,FALSE) -> 734563.4 | AE62: =R62*VLOOKUP(BQ62,Exposure!$B$33:$C$53,2,FALSE)/VLOOKUP(BB62,Exposure!$B$33:$C$53,2,FALSE) -> 5942.6907 | AF62: =S62*VLOOKUP(BR62,Exposure!$B$33:$C$53,2,FALSE)/VLOOKUP(BC62,Exposure!$B$33:$C$53,2,FALSE) -> 1643823.1 | AG62: =T62*VLOOKUP(BS62,Exposure!$B$33:$C$53,2,FALSE)/VLOOKUP(BD62,Exposure!$B$33:$C$53,2,FALSE) -> 79.120887 | AZ62: =$O62 -> 2021 | BA62: =$AZ62+BA$1-1 -> 2022 | BB62: =$AZ62+BB$1-1 -> 2023 | BC62: =$AZ62+BC$1-1 -> 2024 | BD62: =$AZ62+BD$1-1 -> 2025 | BO62: 2027 | BP62: =$BO62+BP$1-1 -> 2028 | BQ62: =$BO62+BQ$1-1 -> 2029 | BR62: =$BO62+BR$1-1 -> 2030 | BS62: =$BO62+BS$1-1 -> 2031
A63: 44339 | B63: 56044.453 | C63: 85775.444 | D63: 748342.91 | E63: 1168900.5 | F63: 1356427.4 | O63: =YEAR($A62) -> 2021 | P63: =$B62 -> 98733.531 | Q63: =C62-B62 -> 701104.04 | R63: =D62-C62 -> 169739.55 | S63: =E62-D62 -> 1022186.1 | T63: =F62-E62 -> 42773.528 | AB63: =$O63 -> 2021 | AC63: =P63*VLOOKUP(BO63,Exposure!$B$33:$C$53,2,FALSE)/VLOOKUP(AZ63,Exposure!$B$33:$C$53,2,FALSE) -> 135062.6 | AD63: =Q63*VLOOKUP(BP63,Exposure!$B$33:$C$53,2,FALSE)/VLOOKUP(BA63,Exposure!$B$33:$C$53,2,FALSE) -> 891907.88 | AE63: =R63*VLOOKUP(BQ63,Exposure!$B$33:$C$53,2,FALSE)/VLOOKUP(BB63,Exposure!$B$33:$C$53,2,FALSE) -> 211202.3 | AF63: =S63*VLOOKUP(BR63,Exposure!$B$33:$C$53,2,FALSE)/VLOOKUP(BC63,Exposure!$B$33:$C$53,2,FALSE) -> 1255541.4 | AG63: =T63*VLOOKUP(BS63,Exposure!$B$33:$C$53,2,FALSE)/VLOOKUP(BD63,Exposure!$B$33:$C$53,2,FALSE) -> 52199.284 | AZ63: =$O63 -> 2021 | BA63: =$AZ63+BA$1-1 -> 2022 | BB63: =$AZ63+BB$1-1 -> 2023 | BC63: =$AZ63+BC$1-1 -> 2024 | BD63: =$AZ63+BD$1-1 -> 2025 | BO63: 2027 | BP63: =$BO63+BP$1-1 -> 2028 | BQ63: =$BO63+BQ$1-1 -> 2029 | BR63: =$BO63+BR$1-1 -> 2030 | BS63: =$BO63+BS$1-1 -> 2031
A64: 44367 | B64: 120770.21 | C64: 133275.52 | D64: 243116.23 | E64: 457636.69 | F64: 554468.9 | O64: =YEAR($A63) -> 2021 | P64: =$B63 -> 56044.453 | Q64: =C63-B63 -> 29730.991 | R64: =D63-C63 -> 662567.47 | S64: =E63-D63 -> 420557.56 | T64: =F63-E63 -> 187526.93 | AB64: =$O64 -> 2021 | AC64: =P64*VLOOKUP(BO64,Exposure!$B$33:$C$53,2,FALSE)/VLOOKUP(AZ64,Exposure!$B$33:$C$53,2,FALSE) -> 76666.049 | AD64: =Q64*VLOOKUP(BP64,Exposure!$B$33:$C$53,2,FALSE)/VLOOKUP(BA64,Exposure!$B$33:$C$53,2,FALSE) -> 37822.211 | AE64: =R64*VLOOKUP(BQ64,Exposure!$B$33:$C$53,2,FALSE)/VLOOKUP(BB64,Exposure!$B$33:$C$53,2,FALSE) -> 824414.69 | AF64: =S64*VLOOKUP(BR64,Exposure!$B$33:$C$53,2,FALSE)/VLOOKUP(BC64,Exposure!$B$33:$C$53,2,FALSE) -> 516566.87 | AG64: =T64*VLOOKUP(BS64,Exposure!$B$33:$C$53,2,FALSE)/VLOOKUP(BD64,Exposure!$B$33:$C$53,2,FALSE) -> 228851.15 | AZ64: =$O64 -> 2021 | BA64: =$AZ64+BA$1-1 -> 2022 | BB64: =$AZ64+BB$1-1 -> 2023 | BC64: =$AZ64+BC$1-1 -> 2024 | BD64: =$AZ64+BD$1-1 -> 2025 | BO64: 2027 | BP64: =$BO64+BP$1-1 -> 2028 | BQ64: =$BO64+BQ$1-1 -> 2029 | BR64: =$BO64+BR$1-1 -> 2030 | BS64: =$BO64+BS$1-1 -> 2031
A65: 44406 | B65: 251519.75 | C65: 253714.44 | D65: 2629133 | E65: 2671328.9 | F65: 2949297.4 | O65: =YEAR($A64) -> 2021 | P65: =$B64 -> 120770.21 | Q65: =C64-B64 -> 12505.309 | R65: =D64-C64 -> 109840.7 | S65: =E64-D64 -> 214520.46 | T65: =F64-E64 -> 96832.215 | AB65: =$O65 -> 2021 | AC65: =P65*VLOOKUP(BO65,Exposure!$B$33:$C$53,2,FALSE)/VLOOKUP(AZ65,Exposure!$B$33:$C$53,2,FALSE) -> 165207.7 | AD65: =Q65*VLOOKUP(BP65,Exposure!$B$33:$C$53,2,FALSE)/VLOOKUP(BA65,Exposure!$B$33:$C$53,2,FALSE) -> 15908.6 | AE65: =R65*VLOOKUP(BQ65,Exposure!$B$33:$C$53,2,FALSE)/VLOOKUP(BB65,Exposure!$B$33:$C$53,2,FALSE) -> 136671.8 | AF65: =S65*VLOOKUP(BR65,Exposure!$B$33:$C$53,2,FALSE)/VLOOKUP(BC65,Exposure!$B$33:$C$53,2,FALSE) -> 263493.44 | AG65: =T65*VLOOKUP(BS65,Exposure!$B$33:$C$53,2,FALSE)/VLOOKUP(BD65,Exposure!$B$33:$C$53,2,FALSE) -> 118170.57 | AZ65: =$O65 -> 2021 | BA65: =$AZ65+BA$1-1 -> 2022 | BB65: =$AZ65+BB$1-1 -> 2023 | BC65: =$AZ65+BC$1-1 -> 2024 | BD65: =$AZ65+BD$1-1 -> 2025 | BO65: 2027 | BP65: =$BO65+BP$1-1 -> 2028 | BQ65: =$BO65+BQ$1-1 -> 2029 | BR65: =$BO65+BR$1-1 -> 2030 | BS65: =$BO65+BS$1-1 -> 2031
A66: 44410 | B66: 693848.48 | C66: 801966.88 | D66: 835705.57 | E66: 896267.05 | F66: 898039.83 | O66: =YEAR($A65) -> 2021 | P66: =$B65 -> 251519.75 | Q66: =C65-B65 -> 2194.6854 | R66: =D65-C65 -> 2375418.6 | S66: =E65-D65 -> 42195.898 | T66: =F65-E65 -> 277968.5 | AB66: =$O66 -> 2021 | AC66: =P66*VLOOKUP(BO66,Exposure!$B$33:$C$53,2,FALSE)/VLOOKUP(AZ66,Exposure!$B$33:$C$53,2,FALSE) -> 344066.63 | AD66: =Q66*VLOOKUP(BP66,Exposure!$B$33:$C$53,2,FALSE)/VLOOKUP(BA66,Exposure!$B$33:$C$53,2,FALSE) -> 2791.9639 | AE66: =R66*VLOOKUP(BQ66,Exposure!$B$33:$C$53,2,FALSE)/VLOOKUP(BB66,Exposure!$B$33:$C$53,2,FALSE) -> 2955668.8 | AF66: =S66*VLOOKUP(BR66,Exposure!$B$33:$C$53,2,FALSE)/VLOOKUP(BC66,Exposure!$B$33:$C$53,2,FALSE) -> 51828.821 | AG66: =T66*VLOOKUP(BS66,Exposure!$B$33:$C$53,2,FALSE)/VLOOKUP(BD66,Exposure!$B$33:$C$53,2,FALSE) -> 339222.81 | AZ66: =$O66 -> 2021 | BA66: =$AZ66+BA$1-1 -> 2022 | BB66: =$AZ66+BB$1-1 -> 2023 | BC66: =$AZ66+BC$1-1 -> 2024 | BD66: =$AZ66+BD$1-1 -> 2025 | BO66: 2027 | BP66: =$BO66+BP$1-1 -> 2028 | BQ66: =$BO66+BQ$1-1 -> 2029 | BR66: =$BO66+BR$1-1 -> 2030 | BS66: =$BO66+BS$1-1 -> 2031
A67: 44411 | B67: 38582.211 | C67: 708216.12 | D67: 928800.73 | E67: 1366170 | F67: 1375871.6 | O67: =YEAR($A66) -> 2021 | P67: =$B66 -> 693848.48 | Q67: =C66-B66 -> 108118.4 | R67: =D66-C66 -> 33738.694 | S67: =E66-D66 -> 60561.474 | T67: =F66-E66 -> 1772.7834 | AB67: =$O67 -> 2021 | AC67: =P67*VLOOKUP(BO67,Exposure!$B$33:$C$53,2,FALSE)/VLOOKUP(AZ67,Exposure!$B$33:$C$53,2,FALSE) -> 949150.52 | AD67: =Q67*VLOOKUP(BP67,Exposure!$B$33:$C$53,2,FALSE)/VLOOKUP(BA67,Exposure!$B$33:$C$53,2,FALSE) -> 137542.57 | AE67: =R67*VLOOKUP(BQ67,Exposure!$B$33:$C$53,2,FALSE)/VLOOKUP(BB67,Exposure!$B$33:$C$53,2,FALSE) -> 41980.14 | AF67: =S67*VLOOKUP(BR67,Exposure!$B$33:$C$53,2,FALSE)/VLOOKUP(BC67,Exposure!$B$33:$C$53,2,FALSE) -> 74387.084 | AG67: =T67*VLOOKUP(BS67,Exposure!$B$33:$C$53,2,FALSE)/VLOOKUP(BD67,Exposure!$B$33:$C$53,2,FALSE) -> 2163.4415 | AZ67: =$O67 -> 2021 | BA67: =$AZ67+BA$1-1 -> 2022 | BB67: =$AZ67+BB$1-1 -> 2023 | BC67: =$AZ67+BC$1-1 -> 2024 | BD67: =$AZ67+BD$1-1 -> 2025 | BO67: 2027 | BP67: =$BO67+BP$1-1 -> 2028 | BQ67: =$BO67+BQ$1-1 -> 2029 | BR67: =$BO67+BR$1-1 -> 2030 | BS67: =$BO67+BS$1-1 -> 2031
A68: 44478 | B68: 201132.76 | C68: 845591.96 | D68: 1431783.9 | E68: 1432882.6 | F68: 2325659.7 | O68: =YEAR($A67) -> 2021 | P68: =$B67 -> 38582.211 | Q68: =C67-B67 -> 669633.91 | R68: =D67-C67 -> 220584.62 | S68: =E67-D67 -> 437369.22 | T68: =F67-E67 -> 9701.6343 | AB68: =$O68 -> 2021 | AC68: =P68*VLOOKUP(BO68,Exposure!$B$33:$C$53,2,FALSE)/VLOOKUP(AZ68,Exposure!$B$33:$C$53,2,FALSE) -> 52778.562 | AD68: =Q68*VLOOKUP(BP68,Exposure!$B$33:$C$53,2,FALSE)/VLOOKUP(BA68,Exposure!$B$33:$C$53,2,FALSE) -> 851873.22 | AE68: =R68*VLOOKUP(BQ68,Exposure!$B$33:$C$53,2,FALSE)/VLOOKUP(BB68,Exposure!$B$33:$C$53,2,FALSE) -> 274467.44 | AF68: =S68*VLOOKUP(BR68,Exposure!$B$33:$C$53,2,FALSE)/VLOOKUP(BC68,Exposure!$B$33:$C$53,2,FALSE) -> 537216.47 | AG68: =T68*VLOOKUP(BS68,Exposure!$B$33:$C$53,2,FALSE)/VLOOKUP(BD68,Exposure!$B$33:$C$53,2,FALSE) -> 11839.527 | AZ68: =$O68 -> 2021 | BA68: =$AZ68+BA$1-1 -> 2022 | BB68: =$AZ68+BB$1-1 -> 2023 | BC68: =$AZ68+BC$1-1 -> 2024 | BD68: =$AZ68+BD$1-1 -> 2025 | BO68: 2027 | BP68: =$BO68+BP$1-1 -> 2028 | BQ68: =$BO68+BQ$1-1 -> 2029 | BR68: =$BO68+BR$1-1 -> 2030 | BS68: =$BO68+BS$1-1 -> 2031
A69: 44481 | B69: 150691.5 | C69: 250520.13 | D69: 250532.62 | E69: 1116639 | F69: 1134822.6 | O69: =YEAR($A68) -> 2021 | P69: =$B68 -> 201132.76 | Q69: =C68-B68 -> 644459.2 | R69: =D68-C68 -> 586191.93 | S69: =E68-D68 -> 1098.76 | T69: =F68-E68 -> 892777.07 | AB69: =$O69 -> 2021 | AC69: =P69*VLOOKUP(BO69,Exposure!$B$33:$C$53,2,FALSE)/VLOOKUP(AZ69,Exposure!$B$33:$C$53,2,FALSE) -> 275139.7 | AD69: =Q69*VLOOKUP(BP69,Exposure!$B$33:$C$53,2,FALSE)/VLOOKUP(BA69,Exposure!$B$33:$C$53,2,FALSE) -> 819847.27 | AE69: =R69*VLOOKUP(BQ69,Exposure!$B$33:$C$53,2,FALSE)/VLOOKUP(BB69,Exposure!$B$33:$C$53,2,FALSE) -> 729382.69 | AF69: =S69*VLOOKUP(BR69,Exposure!$B$33:$C$53,2,FALSE)/VLOOKUP(BC69,Exposure!$B$33:$C$53,2,FALSE) -> 1349.5965 | AG69: =T69*VLOOKUP(BS69,Exposure!$B$33:$C$53,2,FALSE)/VLOOKUP(BD69,Exposure!$B$33:$C$53,2,FALSE) -> 1089513.2 | AZ69: =$O69 -> 2021 | BA69: =$AZ69+BA$1-1 -> 2022 | BB69: =$AZ69+BB$1-1 -> 2023 | BC69: =$AZ69+BC$1-1 -> 2024 | BD69: =$AZ69+BD$1-1 -> 2025 | BO69: 2027 | BP69: =$BO69+BP$1-1 -> 2028 | BQ69: =$BO69+BQ$1-1 -> 2029 | BR69: =$BO69+BR$1-1 -> 2030 | BS69: =$BO69+BS$1-1 -> 2031
A70: 44512 | B70: 466504.37 | C70: 554855.29 | D70: 988643.86 | E70: 1895530 | F70: 2006646.4 | O70: =YEAR($A69) -> 2021 | P70: =$B69 -> 150691.5 | Q70: =C69-B69 -> 99828.626 | R70: =D69-C69 -> 12.491241 | S70: =E69-D69 -> 866106.41 | T70: =F69-E69 -> 18183.578 | AB70: =$O70 -> 2021 | AC70: =P70*VLOOKUP(BO70,Exposure!$B$33:$C$53,2,FALSE)/VLOOKUP(AZ70,Exposure!$B$33:$C$53,2,FALSE) -> 206138.55 | AD70: =Q70*VLOOKUP(BP70,Exposure!$B$33:$C$53,2,FALSE)/VLOOKUP(BA70,Exposure!$B$33:$C$53,2,FALSE) -> 126996.75 | AE70: =R70*VLOOKUP(BQ70,Exposure!$B$33:$C$53,2,FALSE)/VLOOKUP(BB70,Exposure!$B$33:$C$53,2,FALSE) -> 15.542511 | AF70: =S70*VLOOKUP(BR70,Exposure!$B$33:$C$53,2,FALSE)/VLOOKUP(BC70,Exposure!$B$33:$C$53,2,FALSE) -> 1063830.3 | AG70: =T70*VLOOKUP(BS70,Exposure!$B$33:$C$53,2,FALSE)/VLOOKUP(BD70,Exposure!$B$33:$C$53,2,FALSE) -> 22190.588 | AZ70: =$O70 -> 2021 | BA70: =$AZ70+BA$1-1 -> 2022 | BB70: =$AZ70+BB$1-1 -> 2023 | BC70: =$AZ70+BC$1-1 -> 2024 | BD70: =$AZ70+BD$1-1 -> 2025 | BO70: 2027 | BP70: =$BO70+BP$1-1 -> 2028 | BQ70: =$BO70+BQ$1-1 -> 2029 | BR70: =$BO70+BR$1-1 -> 2030 | BS70: =$BO70+BS$1-1 -> 2031
A71: 44566 | B71: 109113.07 | C71: 5514399.3 | D71: 6628607.7 | E71: 11037700 | O71: =YEAR($A70) -> 2021 | P71: =$B70 -> 466504.37 | Q71: =C70-B70 -> 88350.914 | R71: =D70-C70 -> 433788.57 | S71: =E70-D70 -> 906886.14 | T71: =F70-E70 -> 111116.44 | AB71: =$O71 -> 2021 | AC71: =P71*VLOOKUP(BO71,Exposure!$B$33:$C$53,2,FALSE)/VLOOKUP(AZ71,Exposure!$B$33:$C$53,2,FALSE) -> 638154.99 | AD71: =Q71*VLOOKUP(BP71,Exposure!$B$33:$C$53,2,FALSE)/VLOOKUP(BA71,Exposure!$B$33:$C$53,2,FALSE) -> 112395.41 | AE71: =R71*VLOOKUP(BQ71,Exposure!$B$33:$C$53,2,FALSE)/VLOOKUP(BB71,Exposure!$B$33:$C$53,2,FALSE) -> 539751.32 | AF71: =S71*VLOOKUP(BR71,Exposure!$B$33:$C$53,2,FALSE)/VLOOKUP(BC71,Exposure!$B$33:$C$53,2,FALSE) -> 1113919.6 | AG71: =T71*VLOOKUP(BS71,Exposure!$B$33:$C$53,2,FALSE)/VLOOKUP(BD71,Exposure!$B$33:$C$53,2,FALSE) -> 135602.53 | AZ71: =$O71 -> 2021 | BA71: =$AZ71+BA$1-1 -> 2022 | BB71: =$AZ71+BB$1-1 -> 2023 | BC71: =$AZ71+BC$1-1 -> 2024 | BD71: =$AZ71+BD$1-1 -> 2025 | BO71: 2027 | BP71: =$BO71+BP$1-1 -> 2028 | BQ71: =$BO71+BQ$1-1 -> 2029 | BR71: =$BO71+BR$1-1 -> 2030 | BS71: =$BO71+BS$1-1 -> 2031
A72: 44575 | B72: 54443.388 | C72: 699973.09 | D72: 715003.23 | E72: 883851.42 | O72: =YEAR($A71) -> 2022 | P72: =$B71 -> 109113.07 | Q72: =C71-B71 -> 5405286.2 | R72: =D71-C71 -> 1114208.4 | S72: =E71-D71 -> 4409092.3 | AB72: =$O72 -> 2022 | AC72: =P72*VLOOKUP(BO72,Exposure!$B$33:$C$53,2,FALSE)/VLOOKUP(AZ72,Exposure!$B$33:$C$53,2,FALSE) -> 134373.61 | AD72: =Q72*VLOOKUP(BP72,Exposure!$B$33:$C$53,2,FALSE)/VLOOKUP(BA72,Exposure!$B$33:$C$53,2,FALSE) -> 6510794.5 | AE72: =R72*VLOOKUP(BQ72,Exposure!$B$33:$C$53,2,FALSE)/VLOOKUP(BB72,Exposure!$B$33:$C$53,2,FALSE) -> 1324851.5 | AF72: =S72*VLOOKUP(BR72,Exposure!$B$33:$C$53,2,FALSE)/VLOOKUP(BC72,Exposure!$B$33:$C$53,2,FALSE) -> 5208807.9 | AZ72: =$O72 -> 2022 | BA72: =$AZ72+BA$1-1 -> 2023 | BB72: =$AZ72+BB$1-1 -> 2024 | BC72: =$AZ72+BC$1-1 -> 2025 | BO72: 2027 | BP72: =$BO72+BP$1-1 -> 2028 | BQ72: =$BO72+BQ$1-1 -> 2029 | BR72: =$BO72+BR$1-1 -> 2030
A73: 44612 | B73: 392575.49 | C73: 1036029.1 | D73: 1245591 | E73: 1610096.7 | O73: =YEAR($A72) -> 2022 | P73: =$B72 -> 54443.388 | Q73: =C72-B72 -> 645529.7 | R73: =D72-C72 -> 15030.146 | S73: =E72-D72 -> 168848.18 | AB73: =$O73 -> 2022 | AC73: =P73*VLOOKUP(BO73,Exposure!$B$33:$C$53,2,FALSE)/VLOOKUP(AZ73,Exposure!$B$33:$C$53,2,FALSE) -> 67047.463 | AD73: =Q73*VLOOKUP(BP73,Exposure!$B$33:$C$53,2,FALSE)/VLOOKUP(BA73,Exposure!$B$33:$C$53,2,FALSE) -> 777555.72 | AE73: =R73*VLOOKUP(BQ73,Exposure!$B$33:$C$53,2,FALSE)/VLOOKUP(BB73,Exposure!$B$33:$C$53,2,FALSE) -> 17871.622 | AF73: =S73*VLOOKUP(BR73,Exposure!$B$33:$C$53,2,FALSE)/VLOOKUP(BC73,Exposure!$B$33:$C$53,2,FALSE) -> 199473.65 | AZ73: =$O73 -> 2022 | BA73: =$AZ73+BA$1-1 -> 2023 | BB73: =$AZ73+BB$1-1 -> 2024 | BC73: =$AZ73+BC$1-1 -> 2025 | BO73: 2027 | BP73: =$BO73+BP$1-1 -> 2028 | BQ73: =$BO73+BQ$1-1 -> 2029 | BR73: =$BO73+BR$1-1 -> 2030
A74: 44631 | B74: 148363.37 | C74: 592603.43 | D74: 860140.42 | E74: 4206662.1 | O74: =YEAR($A73) -> 2022 | P74: =$B73 -> 392575.49 | Q74: =C73-B73 -> 643453.56 | R74: =D73-C73 -> 209561.96 | S74: =E73-D73 -> 364505.66 | AB74: =$O74 -> 2022 | AC74: =P74*VLOOKUP(BO74,Exposure!$B$33:$C$53,2,FALSE)/VLOOKUP(AZ74,Exposure!$B$33:$C$53,2,FALSE) -> 483459.83 | AD74: =Q74*VLOOKUP(BP74,Exposure!$B$33:$C$53,2,FALSE)/VLOOKUP(BA74,Exposure!$B$33:$C$53,2,FALSE) -> 775054.96 | AE74: =R74*VLOOKUP(BQ74,Exposure!$B$33:$C$53,2,FALSE)/VLOOKUP(BB74,Exposure!$B$33:$C$53,2,FALSE) -> 249180.03 | AF74: =S74*VLOOKUP(BR74,Exposure!$B$33:$C$53,2,FALSE)/VLOOKUP(BC74,Exposure!$B$33:$C$53,2,FALSE) -> 430619.23 | AZ74: =$O74 -> 2022 | BA74: =$AZ74+BA$1-1 -> 2023 | BB74: =$AZ74+BB$1-1 -> 2024 | BC74: =$AZ74+BC$1-1 -> 2025 | BO74: 2027 | BP74: =$BO74+BP$1-1 -> 2028 | BQ74: =$BO74+BQ$1-1 -> 2029 | BR74: =$BO74+BR$1-1 -> 2030
A75: 44887 | B75: 278689.13 | C75: 414736.26 | D75: 566223.46 | E75: 834204.29 | O75: =YEAR($A74) -> 2022 | P75: =$B74 -> 148363.37 | Q75: =C74-B74 -> 444240.06 | R75: =D74-C74 -> 267536.99 | S75: =E74-D74 -> 3346521.7 | AB75: =$O75 -> 2022 | AC75: =P75*VLOOKUP(BO75,Exposure!$B$33:$C$53,2,FALSE)/VLOOKUP(AZ75,Exposure!$B$33:$C$53,2,FALSE) -> 182710.67 | AD75: =Q75*VLOOKUP(BP75,Exposure!$B$33:$C$53,2,FALSE)/VLOOKUP(BA75,Exposure!$B$33:$C$53,2,FALSE) -> 535097.61 | AE75: =R75*VLOOKUP(BQ75,Exposure!$B$33:$C$53,2,FALSE)/VLOOKUP(BB75,Exposure!$B$33:$C$53,2,FALSE) -> 318115.34 | AF75: =S75*VLOOKUP(BR75,Exposure!$B$33:$C$53,2,FALSE)/VLOOKUP(BC75,Exposure!$B$33:$C$53,2,FALSE) -> 3953509.5 | AZ75: =$O75 -> 2022 | BA75: =$AZ75+BA$1-1 -> 2023 | BB75: =$AZ75+BB$1-1 -> 2024 | BC75: =$AZ75+BC$1-1 -> 2025 | BO75: 2027 | BP75: =$BO75+BP$1-1 -> 2028 | BQ75: =$BO75+BQ$1-1 -> 2029 | BR75: =$BO75+BR$1-1 -> 2030
A76: 44890 | B76: 4641.2336 | C76: 47472.315 | D76: 306930.69 | E76: 318353.38 | O76: =YEAR($A75) -> 2022 | P76: =$B75 -> 278689.13 | Q76: =C75-B75 -> 136047.13 | R76: =D75-C75 -> 151487.19 | S76: =E75-D75 -> 267980.83 | AB76: =$O76 -> 2022 | AC76: =P76*VLOOKUP(BO76,Exposure!$B$33:$C$53,2,FALSE)/VLOOKUP(AZ76,Exposure!$B$33:$C$53,2,FALSE) -> 343207.88 | AD76: =Q76*VLOOKUP(BP76,Exposure!$B$33:$C$53,2,FALSE)/VLOOKUP(BA76,Exposure!$B$33:$C$53,2,FALSE) -> 163871.97 | AE76: =R76*VLOOKUP(BQ76,Exposure!$B$33:$C$53,2,FALSE)/VLOOKUP(BB76,Exposure!$B$33:$C$53,2,FALSE) -> 180126.12 | AF76: =S76*VLOOKUP(BR76,Exposure!$B$33:$C$53,2,FALSE)/VLOOKUP(BC76,Exposure!$B$33:$C$53,2,FALSE) -> 316586.85 | AZ76: =$O76 -> 2022 | BA76: =$AZ76+BA$1-1 -> 2023 | BB76: =$AZ76+BB$1-1 -> 2024 | BC76: =$AZ76+BC$1-1 -> 2025 | BO76: 2027 | BP76: =$BO76+BP$1-1 -> 2028 | BQ76: =$BO76+BQ$1-1 -> 2029 | BR76: =$BO76+BR$1-1 -> 2030
A77: 44930 | B77: 14084.593 | C77: 53223.167 | D77: 135955.29 | O77: =YEAR($A76) -> 2022 | P77: =$B76 -> 4641.2336 | Q77: =C76-B76 -> 42831.081 | R77: =D76-C76 -> 259458.38 | S77: =E76-D76 -> 11422.69 | AB77: =$O77 -> 2022 | AC77: =P77*VLOOKUP(BO77,Exposure!$B$33:$C$53,2,FALSE)/VLOOKUP(AZ77,Exposure!$B$33:$C$53,2,FALSE) -> 5715.716 | AD77: =Q77*VLOOKUP(BP77,Exposure!$B$33:$C$53,2,FALSE)/VLOOKUP(BA77,Exposure!$B$33:$C$53,2,FALSE) -> 51591.045 | AE77: =R77*VLOOKUP(BQ77,Exposure!$B$33:$C$53,2,FALSE)/VLOOKUP(BB77,Exposure!$B$33:$C$53,2,FALSE) -> 308509.45 | AF77: =S77*VLOOKUP(BR77,Exposure!$B$33:$C$53,2,FALSE)/VLOOKUP(BC77,Exposure!$B$33:$C$53,2,FALSE) -> 13494.523 | AZ77: =$O77 -> 2022 | BA77: =$AZ77+BA$1-1 -> 2023 | BB77: =$AZ77+BB$1-1 -> 2024 | BC77: =$AZ77+BC$1-1 -> 2025 | BO77: 2027 | BP77: =$BO77+BP$1-1 -> 2028 | BQ77: =$BO77+BQ$1-1 -> 2029 | BR77: =$BO77+BR$1-1 -> 2030
A78: 44934 | B78: 72060.005 | C78: 707480.09 | D78: 919752.38 | O78: =YEAR($A77) -> 2023 | P78: =$B77 -> 14084.593 | Q78: =C77-B77 -> 39138.574 | R78: =D77-C77 -> 82732.119 | AB78: =$O78 -> 2023 | AC78: =P78*VLOOKUP(BO78,Exposure!$B$33:$C$53,2,FALSE)/VLOOKUP(AZ78,Exposure!$B$33:$C$53,2,FALSE) -> 16423.256 | AD78: =Q78*VLOOKUP(BP78,Exposure!$B$33:$C$53,2,FALSE)/VLOOKUP(BA78,Exposure!$B$33:$C$53,2,FALSE) -> 45051.106 | AE78: =R78*VLOOKUP(BQ78,Exposure!$B$33:$C$53,2,FALSE)/VLOOKUP(BB78,Exposure!$B$33:$C$53,2,FALSE) -> 94615.649 | AZ78: =$O78 -> 2023 | BA78: =$AZ78+BA$1-1 -> 2024 | BB78: =$AZ78+BB$1-1 -> 2025 | BO78: 2027 | BP78: =$BO78+BP$1-1 -> 2028 | BQ78: =$BO78+BQ$1-1 -> 2029
A79: 44975 | B79: 555279.27 | C79: 1437170 | D79: 1500704.8 | O79: =YEAR($A78) -> 2023 | P79: =$B78 -> 72060.005 | Q79: =C78-B78 -> 635420.09 | R79: =D78-C78 -> 212272.29 | AB79: =$O79 -> 2023 | AC79: =P79*VLOOKUP(BO79,Exposure!$B$33:$C$53,2,FALSE)/VLOOKUP(AZ79,Exposure!$B$33:$C$53,2,FALSE) -> 84025.143 | AD79: =Q79*VLOOKUP(BP79,Exposure!$B$33:$C$53,2,FALSE)/VLOOKUP(BA79,Exposure!$B$33:$C$53,2,FALSE) -> 731410.84 | AE79: =R79*VLOOKUP(BQ79,Exposure!$B$33:$C$53,2,FALSE)/VLOOKUP(BB79,Exposure!$B$33:$C$53,2,FALSE) -> 242762.8 | AZ79: =$O79 -> 2023 | BA79: =$AZ79+BA$1-1 -> 2024 | BB79: =$AZ79+BB$1-1 -> 2025 | BO79: 2027 | BP79: =$BO79+BP$1-1 -> 2028 | BQ79: =$BO79+BQ$1-1 -> 2029
A80: 45000 | B80: 85672.639 | C80: 607877.11 | D80: 1238148.7 | O80: =YEAR($A79) -> 2023 | P80: =$B79 -> 555279.27 | Q80: =C79-B79 -> 881890.68 | R80: =D79-C79 -> 63534.861 | AB80: =$O80 -> 2023 | AC80: =P80*VLOOKUP(BO80,Exposure!$B$33:$C$53,2,FALSE)/VLOOKUP(AZ80,Exposure!$B$33:$C$53,2,FALSE) -> 647480.11 | AD80: =Q80*VLOOKUP(BP80,Exposure!$B$33:$C$53,2,FALSE)/VLOOKUP(BA80,Exposure!$B$33:$C$53,2,FALSE) -> 1015114.9 | AE80: =R80*VLOOKUP(BQ80,Exposure!$B$33:$C$53,2,FALSE)/VLOOKUP(BB80,Exposure!$B$33:$C$53,2,FALSE) -> 72660.922 | AZ80: =$O80 -> 2023 | BA80: =$AZ80+BA$1-1 -> 2024 | BB80: =$AZ80+BB$1-1 -> 2025 | BO80: 2027 | BP80: =$BO80+BP$1-1 -> 2028 | BQ80: =$BO80+BQ$1-1 -> 2029
A81: 45017 | B81: 150538.2 | C81: 681639.11 | D81: 689027.79 | O81: =YEAR($A80) -> 2023 | P81: =$B80 -> 85672.639 | Q81: =C80-B80 -> 522204.47 | R81: =D80-C80 -> 630271.6 | AB81: =$O81 -> 2023 | AC81: =P81*VLOOKUP(BO81,Exposure!$B$33:$C$53,2,FALSE)/VLOOKUP(AZ81,Exposure!$B$33:$C$53,2,FALSE) -> 99898.074 | AD81: =Q81*VLOOKUP(BP81,Exposure!$B$33:$C$53,2,FALSE)/VLOOKUP(BA81,Exposure!$B$33:$C$53,2,FALSE) -> 601092.13 | AE81: =R81*VLOOKUP(BQ81,Exposure!$B$33:$C$53,2,FALSE)/VLOOKUP(BB81,Exposure!$B$33:$C$53,2,FALSE) -> 720802.96 | AZ81: =$O81 -> 2023 | BA81: =$AZ81+BA$1-1 -> 2024 | BB81: =$AZ81+BB$1-1 -> 2025 | BO81: 2027 | BP81: =$BO81+BP$1-1 -> 2028 | BQ81: =$BO81+BQ$1-1 -> 2029
A82: 45019 | B82: 62820.445 | C82: 71622.999 | D82: 975665.05 | O82: =YEAR($A81) -> 2023 | P82: =$B81 -> 150538.2 | Q82: =C81-B81 -> 531100.91 | R82: =D81-C81 -> 7388.6822 | AB82: =$O82 -> 2023 | AC82: =P82*VLOOKUP(BO82,Exposure!$B$33:$C$53,2,FALSE)/VLOOKUP(AZ82,Exposure!$B$33:$C$53,2,FALSE) -> 175534.18 | AD82: =Q82*VLOOKUP(BP82,Exposure!$B$33:$C$53,2,FALSE)/VLOOKUP(BA82,Exposure!$B$33:$C$53,2,FALSE) -> 611332.52 | AE82: =R82*VLOOKUP(BQ82,Exposure!$B$33:$C$53,2,FALSE)/VLOOKUP(BB82,Exposure!$B$33:$C$53,2,FALSE) -> 8449.9825 | AZ82: =$O82 -> 2023 | BA82: =$AZ82+BA$1-1 -> 2024 | BB82: =$AZ82+BB$1-1 -> 2025 | BO82: 2027 | BP82: =$BO82+BP$1-1 -> 2028 | BQ82: =$BO82+BQ$1-1 -> 2029
A83: 45082 | B83: 41410.32 | C83: 43174.886 | D83: 43612.124 | O83: =YEAR($A82) -> 2023 | P83: =$B82 -> 62820.445 | Q83: =C82-B82 -> 8802.5543 | R83: =D82-C82 -> 904042.05 | AB83: =$O83 -> 2023 | AC83: =P83*VLOOKUP(BO83,Exposure!$B$33:$C$53,2,FALSE)/VLOOKUP(AZ83,Exposure!$B$33:$C$53,2,FALSE) -> 73251.408 | AD83: =Q83*VLOOKUP(BP83,Exposure!$B$33:$C$53,2,FALSE)/VLOOKUP(BA83,Exposure!$B$33:$C$53,2,FALSE) -> 10132.326 | AE83: =R83*VLOOKUP(BQ83,Exposure!$B$33:$C$53,2,FALSE)/VLOOKUP(BB83,Exposure!$B$33:$C$53,2,FALSE) -> 1033897.4 | AZ83: =$O83 -> 2023 | BA83: =$AZ83+BA$1-1 -> 2024 | BB83: =$AZ83+BB$1-1 -> 2025 | BO83: 2027 | BP83: =$BO83+BP$1-1 -> 2028 | BQ83: =$BO83+BQ$1-1 -> 2029
A84: 45083 | B84: 154129.41 | C84: 586155.13 | D84: 597373.17 | O84: =YEAR($A83) -> 2023 | P84: =$B83 -> 41410.32 | Q84: =C83-B83 -> 1764.5663 | R84: =D83-C83 -> 437.23847 | AB84: =$O84 -> 2023 | AC84: =P84*VLOOKUP(BO84,Exposure!$B$33:$C$53,2,FALSE)/VLOOKUP(AZ84,Exposure!$B$33:$C$53,2,FALSE) -> 48286.258 | AD84: =Q84*VLOOKUP(BP84,Exposure!$B$33:$C$53,2,FALSE)/VLOOKUP(BA84,Exposure!$B$33:$C$53,2,FALSE) -> 2031.1334 | AE84: =R84*VLOOKUP(BQ84,Exposure!$B$33:$C$53,2,FALSE)/VLOOKUP(BB84,Exposure!$B$33:$C$53,2,FALSE) -> 500.04282 | AZ84: =$O84 -> 2023 | BA84: =$AZ84+BA$1-1 -> 2024 | BB84: =$AZ84+BB$1-1 -> 2025 | BO84: 2027 | BP84: =$BO84+BP$1-1 -> 2028 | BQ84: =$BO84+BQ$1-1 -> 2029
A85: 45099 | B85: 12383.383 | C85: 12541.067 | D85: 12558.512 | O85: =YEAR($A84) -> 2023 | P85: =$B84 -> 154129.41 | Q85: =C84-B84 -> 432025.71 | R85: =D84-C84 -> 11218.041 | AB85: =$O85 -> 2023 | AC85: =P85*VLOOKUP(BO85,Exposure!$B$33:$C$53,2,FALSE)/VLOOKUP(AZ85,Exposure!$B$33:$C$53,2,FALSE) -> 179721.69 | AD85: =Q85*VLOOKUP(BP85,Exposure!$B$33:$C$53,2,FALSE)/VLOOKUP(BA85,Exposure!$B$33:$C$53,2,FALSE) -> 497290.37 | AE85: =R85*VLOOKUP(BQ85,Exposure!$B$33:$C$53,2,FALSE)/VLOOKUP(BB85,Exposure!$B$33:$C$53,2,FALSE) -> 12829.386 | AZ85: =$O85 -> 2023 | BA85: =$AZ85+BA$1-1 -> 2024 | BB85: =$AZ85+BB$1-1 -> 2025 | BO85: 2027 | BP85: =$BO85+BP$1-1 -> 2028 | BQ85: =$BO85+BQ$1-1 -> 2029
A86: 45108 | B86: 33505.758 | C86: 106764.31 | D86: 112947.95 | O86: =YEAR($A85) -> 2023 | P86: =$B85 -> 12383.383 | Q86: =C85-B85 -> 157.68384 | R86: =D85-C85 -> 17.445616 | AB86: =$O86 -> 2023 | AC86: =P86*VLOOKUP(BO86,Exposure!$B$33:$C$53,2,FALSE)/VLOOKUP(AZ86,Exposure!$B$33:$C$53,2,FALSE) -> 14439.57 | AD86: =Q86*VLOOKUP(BP86,Exposure!$B$33:$C$53,2,FALSE)/VLOOKUP(BA86,Exposure!$B$33:$C$53,2,FALSE) -> 181.5046 | AE86: =R86*VLOOKUP(BQ86,Exposure!$B$33:$C$53,2,FALSE)/VLOOKUP(BB86,Exposure!$B$33:$C$53,2,FALSE) -> 19.951481 | AZ86: =$O86 -> 2023 | BA86: =$AZ86+BA$1-1 -> 2024 | BB86: =$AZ86+BB$1-1 -> 2025 | BO86: 2027 | BP86: =$BO86+BP$1-1 -> 2028 | BQ86: =$BO86+BQ$1-1 -> 2029
A87: 45147 | B87: 515317.03 | C87: 1355985.2 | D87: 1719788.5 | O87: =YEAR($A86) -> 2023 | P87: =$B86 -> 33505.758 | Q87: =C86-B86 -> 73258.555 | R87: =D86-C86 -> 6183.6398 | AB87: =$O87 -> 2023 | AC87: =P87*VLOOKUP(BO87,Exposure!$B$33:$C$53,2,FALSE)/VLOOKUP(AZ87,Exposure!$B$33:$C$53,2,FALSE) -> 39069.191 | AD87: =Q87*VLOOKUP(BP87,Exposure!$B$33:$C$53,2,FALSE)/VLOOKUP(BA87,Exposure!$B$33:$C$53,2,FALSE) -> 84325.477 | AE87: =R87*VLOOKUP(BQ87,Exposure!$B$33:$C$53,2,FALSE)/VLOOKUP(BB87,Exposure!$B$33:$C$53,2,FALSE) -> 7071.8495 | AZ87: =$O87 -> 2023 | BA87: =$AZ87+BA$1-1 -> 2024 | BB87: =$AZ87+BB$1-1 -> 2025 | BO87: 2027 | BP87: =$BO87+BP$1-1 -> 2028 | BQ87: =$BO87+BQ$1-1 -> 2029
A88: 45178 | B88: 1098060.7 | C88: 1126145.5 | D88: 1361274.5 | O88: =YEAR($A87) -> 2023 | P88: =$B87 -> 515317.03 | Q88: =C87-B87 -> 840668.19 | R88: =D87-C87 -> 363803.26 | AB88: =$O88 -> 2023 | AC88: =P88*VLOOKUP(BO88,Exposure!$B$33:$C$53,2,FALSE)/VLOOKUP(AZ88,Exposure!$B$33:$C$53,2,FALSE) -> 600882.37 | AD88: =Q88*VLOOKUP(BP88,Exposure!$B$33:$C$53,2,FALSE)/VLOOKUP(BA88,Exposure!$B$33:$C$53,2,FALSE) -> 967665.08 | AE88: =R88*VLOOKUP(BQ88,Exposure!$B$33:$C$53,2,FALSE)/VLOOKUP(BB88,Exposure!$B$33:$C$53,2,FALSE) -> 416059.47 | AZ88: =$O88 -> 2023 | BA88: =$AZ88+BA$1-1 -> 2024 | BB88: =$AZ88+BB$1-1 -> 2025 | BO88: 2027 | BP88: =$BO88+BP$1-1 -> 2028 | BQ88: =$BO88+BQ$1-1 -> 2029
A89: 45182 | B89: 1684.7394 | C89: 89383.829 | D89: 294493.79 | O89: =YEAR($A88) -> 2023 | P89: =$B88 -> 1098060.7 | Q89: =C88-B88 -> 28084.856 | R89: =D88-C88 -> 235128.96 | AB89: =$O89 -> 2023 | AC89: =P89*VLOOKUP(BO89,Exposure!$B$33:$C$53,2,FALSE)/VLOOKUP(AZ89,Exposure!$B$33:$C$53,2,FALSE) -> 1280387.1 | AD89: =Q89*VLOOKUP(BP89,Exposure!$B$33:$C$53,2,FALSE)/VLOOKUP(BA89,Exposure!$B$33:$C$53,2,FALSE) -> 32327.54 | AE89: =R89*VLOOKUP(BQ89,Exposure!$B$33:$C$53,2,FALSE)/VLOOKUP(BB89,Exposure!$B$33:$C$53,2,FALSE) -> 268902.57 | AZ89: =$O89 -> 2023 | BA89: =$AZ89+BA$1-1 -> 2024 | BB89: =$AZ89+BB$1-1 -> 2025 | BO89: 2027 | BP89: =$BO89+BP$1-1 -> 2028 | BQ89: =$BO89+BQ$1-1 -> 2029
... A92: 45289 | B92: 21.091759 | C92: 353410.74 | D92: 359706.11 | O92: =YEAR($A91) -> 2023 | P92: =$B91 -> 339333.82 | Q92: =C91-B91 -> 2.5381214 | R92: =D91-C91 -> 42275.721 | AB92: =$O92 -> 2023 | AC92: =P92*VLOOKUP(BO92,Exposure!$B$33:$C$53,2,FALSE)/VLOOKUP(AZ92,Exposure!$B$33:$C$53,2,FALSE) -> 395678.19 | AD92: =Q92*VLOOKUP(BP92,Exposure!$B$33:$C$53,2,FALSE)/VLOOKUP(BA92,Exposure!$B$33:$C$53,2,FALSE) -> 2.9215468 | AE92: =R92*VLOOKUP(BQ92,Exposure!$B$33:$C$53,2,FALSE)/VLOOKUP(BB92,Exposure!$B$33:$C$53,2,FALSE) -> 48348.148 | AZ92: =$O92 -> 2023 | BA92: =$AZ92+BA$1-1 -> 2024 | BB92: =$AZ92+BB$1-1 -> 2025 | BO92: 2027 | BP92: =$BO92+BP$1-1 -> 2028 | BQ92: =$BO92+BQ$1-1 -> 2029
A93: 45313 | B93: 33511.903 | C93: 36789.731 | O93: =YEAR($A92) -> 2023 | P93: =$B92 -> 21.091759 | Q93: =C92-B92 -> 353389.65 | R93: =D92-C92 -> 6295.3661 | AB93: =$O93 -> 2023 | AC93: =P93*VLOOKUP(BO93,Exposure!$B$33:$C$53,2,FALSE)/VLOOKUP(AZ93,Exposure!$B$33:$C$53,2,FALSE) -> 24.593921 | AD93: =Q93*VLOOKUP(BP93,Exposure!$B$33:$C$53,2,FALSE)/VLOOKUP(BA93,Exposure!$B$33:$C$53,2,FALSE) -> 406775.03 | AE93: =R93*VLOOKUP(BQ93,Exposure!$B$33:$C$53,2,FALSE)/VLOOKUP(BB93,Exposure!$B$33:$C$53,2,FALSE) -> 7199.624 | AZ93: =$O93 -> 2023 | BA93: =$AZ93+BA$1-1 -> 2024 | BB93: =$AZ93+BB$1-1 -> 2025 | BO93: 2027 | BP93: =$BO93+BP$1-1 -> 2028 | BQ93: =$BO93+BQ$1-1 -> 2029
A94: 45315 | B94: 221890.53 | C94: 253796.99 | O94: =YEAR($A93) -> 2024 | P94: =$B93 -> 33511.903 | Q94: =C93-B93 -> 3277.8278 | AB94: =$O94 -> 2024 | AC94: =P94*VLOOKUP(BO94,Exposure!$B$33:$C$53,2,FALSE)/VLOOKUP(AZ94,Exposure!$B$33:$C$53,2,FALSE) -> 37342.142 | AD94: =Q94*VLOOKUP(BP94,Exposure!$B$33:$C$53,2,FALSE)/VLOOKUP(BA94,Exposure!$B$33:$C$53,2,FALSE) -> 3628.897 | AZ94: =$O94 -> 2024 | BA94: =$AZ94+BA$1-1 -> 2025 | BO94: 2027 | BP94: =$BO94+BP$1-1 -> 2028
A95: 45321 | B95: 57704.345 | C95: 61838.556 | O95: =YEAR($A94) -> 2024 | P95: =$B94 -> 221890.53 | Q95: =C94-B94 -> 31906.46 | AB95: =$O95 -> 2024 | AC95: =P95*VLOOKUP(BO95,Exposure!$B$33:$C$53,2,FALSE)/VLOOKUP(AZ95,Exposure!$B$33:$C$53,2,FALSE) -> 247251.48 | AD95: =Q95*VLOOKUP(BP95,Exposure!$B$33:$C$53,2,FALSE)/VLOOKUP(BA95,Exposure!$B$33:$C$53,2,FALSE) -> 35323.776 | AZ95: =$O95 -> 2024 | BA95: =$AZ95+BA$1-1 -> 2025 | BO95: 2027 | BP95: =$BO95+BP$1-1 -> 2028
A96: 45325 | B96: 71677.44 | C96: 155007.98 | O96: =YEAR($A95) -> 2024 | P96: =$B95 -> 57704.345 | Q96: =C95-B95 -> 4134.2102 | AB96: =$O96 -> 2024 | AC96: =P96*VLOOKUP(BO96,Exposure!$B$33:$C$53,2,FALSE)/VLOOKUP(AZ96,Exposure!$B$33:$C$53,2,FALSE) -> 64299.656 | AD96: =Q96*VLOOKUP(BP96,Exposure!$B$33:$C$53,2,FALSE)/VLOOKUP(BA96,Exposure!$B$33:$C$53,2,FALSE) -> 4577.0015 | AZ96: =$O96 -> 2024 | BA96: =$AZ96+BA$1-1 -> 2025 | BO96: 2027 | BP96: =$BO96+BP$1-1 -> 2028
A97: 45340 | B97: 42786.604 | C97: 64069.497 | O97: =YEAR($A96) -> 2024 | P97: =$B96 -> 71677.44 | Q97: =C96-B96 -> 83330.542 | AB97: =$O97 -> 2024 | AC97: =P97*VLOOKUP(BO97,Exposure!$B$33:$C$53,2,FALSE)/VLOOKUP(AZ97,Exposure!$B$33:$C$53,2,FALSE) -> 79869.804 | AD97: =Q97*VLOOKUP(BP97,Exposure!$B$33:$C$53,2,FALSE)/VLOOKUP(BA97,Exposure!$B$33:$C$53,2,FALSE) -> 92255.594 | AZ97: =$O97 -> 2024 | BA97: =$AZ97+BA$1-1 -> 2025 | BO97: 2027 | BP97: =$BO97+BP$1-1 -> 2028
A98: 45395 | B98: 479321.73 | C98: 479618.81 | O98: =YEAR($A97) -> 2024 | P98: =$B97 -> 42786.604 | Q98: =C97-B97 -> 21282.893 | AB98: =$O98 -> 2024 | AC98: =P98*VLOOKUP(BO98,Exposure!$B$33:$C$53,2,FALSE)/VLOOKUP(AZ98,Exposure!$B$33:$C$53,2,FALSE) -> 47676.893 | AD98: =Q98*VLOOKUP(BP98,Exposure!$B$33:$C$53,2,FALSE)/VLOOKUP(BA98,Exposure!$B$33:$C$53,2,FALSE) -> 23562.381 | AZ98: =$O98 -> 2024 | BA98: =$AZ98+BA$1-1 -> 2025 | BO98: 2027 | BP98: =$BO98+BP$1-1 -> 2028
A99: 45401 | B99: 166493.34 | C99: 172708.1 | O99: =YEAR($A98) -> 2024 | P99: =$B98 -> 479321.73 | Q99: =C98-B98 -> 297.08446 | AB99: =$O99 -> 2024 | AC99: =P99*VLOOKUP(BO99,Exposure!$B$33:$C$53,2,FALSE)/VLOOKUP(AZ99,Exposure!$B$33:$C$53,2,FALSE) -> 534105.74 | AD99: =Q99*VLOOKUP(BP99,Exposure!$B$33:$C$53,2,FALSE)/VLOOKUP(BA99,Exposure!$B$33:$C$53,2,FALSE) -> 328.90346 | AZ99: =$O99 -> 2024 | BA99: =$AZ99+BA$1-1 -> 2025 | BO99: 2027 | BP99: =$BO99+BP$1-1 -> 2028
A100: 45408 | B100: 301863.02 | C100: 337736.27 | O100: =YEAR($A99) -> 2024 | P100: =$B99 -> 166493.34 | Q100: =C99-B99 -> 6214.7561 | AB100: =$O100 -> 2024 | AC100: =P100*VLOOKUP(BO100,Exposure!$B$33:$C$53,2,FALSE)/VLOOKUP(AZ100,Exposure!$B$33:$C$53,2,FALSE) -> 185522.68 | AD100: =Q100*VLOOKUP(BP100,Exposure!$B$33:$C$53,2,FALSE)/VLOOKUP(BA100,Exposure!$B$33:$C$53,2,FALSE) -> 6880.3827 | AZ100: =$O100 -> 2024 | BA100: =$AZ100+BA$1-1 -> 2025 | BO100: 2027 | BP100: =$BO100+BP$1-1 -> 2028
A101: 45419 | B101: 116096.91 | C101: 272549.51 | O101: =YEAR($A100) -> 2024 | P101: =$B100 -> 301863.02 | Q101: =C100-B100 -> 35873.256 | AB101: =$O101 -> 2024 | AC101: =P101*VLOOKUP(BO101,Exposure!$B$33:$C$53,2,FALSE)/VLOOKUP(AZ101,Exposure!$B$33:$C$53,2,FALSE) -> 336364.41 | AD101: =Q101*VLOOKUP(BP101,Exposure!$B$33:$C$53,2,FALSE)/VLOOKUP(BA101,Exposure!$B$33:$C$53,2,FALSE) -> 39715.432 | AZ101: =$O101 -> 2024 | BA101: =$AZ101+BA$1-1 -> 2025 | BO101: 2027 | BP101: =$BO101+BP$1-1 -> 2028
A102: 45422 | B102: 575262.47 | C102: 2197455.3 | O102: =YEAR($A101) -> 2024 | P102: =$B101 -> 116096.91 | Q102: =C101-B101 -> 156452.6 | AB102: =$O102 -> 2024 | AC102: =P102*VLOOKUP(BO102,Exposure!$B$33:$C$53,2,FALSE)/VLOOKUP(AZ102,Exposure!$B$33:$C$53,2,FALSE) -> 129366.19 | AD102: =Q102*VLOOKUP(BP102,Exposure!$B$33:$C$53,2,FALSE)/VLOOKUP(BA102,Exposure!$B$33:$C$53,2,FALSE) -> 173209.33 | AZ102: =$O102 -> 2024 | BA102: =$AZ102+BA$1-1 -> 2025 | BO102: 2027 | BP102: =$BO102+BP$1-1 -> 2028
A103: 45534 | B103: 263392.47 | C103: 3090549.9 | O103: =YEAR($A102) -> 2024 | P103: =$B102 -> 575262.47 | Q103: =C102-B102 -> 1622192.8 | AB103: =$O103 -> 2024 | AC103: =P103*VLOOKUP(BO103,Exposure!$B$33:$C$53,2,FALSE)/VLOOKUP(AZ103,Exposure!$B$33:$C$53,2,FALSE) -> 641012.03 | AD103: =Q103*VLOOKUP(BP103,Exposure!$B$33:$C$53,2,FALSE)/VLOOKUP(BA103,Exposure!$B$33:$C$53,2,FALSE) -> 1795936.5 | AZ103: =$O103 -> 2024 | BA103: =$AZ103+BA$1-1 -> 2025 | BO103: 2027 | BP103: =$BO103+BP$1-1 -> 2028
...

Sheet Outstanding loss reserves
A1: 42374 | B1: 357368.73 | C1: 389834.52 | D1: 316831.39 | E1: 230961.34 | F1: 54979.883 | G1: 51116.877 | H1: 17536.534 | I1: 13543.826 | J1: 119.10271 | K1: 72.395149 | M1: Indexed loss Reserves | O1: Years | P1: 1 | Q1: 2 | R1: 3 | S1: 4 | T1: 5 | U1: 6 | V1: 7 | W1: 8 | X1: 9 | Y1: 10
A2: 42415 | B2: 1568224.6 | C2: 841886.1 | D2: 697826.38 | E2: 303365.95 | F2: 57283.481 | G2: 57225.958 | H2: 13867.485 | I2: 450.93949 | J2: 48.777901 | K2: 0.11579826 | O2: =YEAR($A1) -> 2016 | P2: =B1*VLOOKUP('Cum. payments'!BO2,Exposure!$B$33:$C$53,2,FALSE)/VLOOKUP('Cum. payments'!AZ2,Exposure!$B$33:$C$53,2,FALSE) -> 573885.73 | Q2: =C1*VLOOKUP('Cum. payments'!BP2,Exposure!$B$33:$C$53,2,FALSE)/VLOOKUP('Cum. payments'!BA2,Exposure!$B$33:$C$53,2,FALSE) -> 624040.77 | R2: =D1*VLOOKUP('Cum. payments'!BQ2,Exposure!$B$33:$C$53,2,FALSE)/VLOOKUP('Cum. payments'!BB2,Exposure!$B$33:$C$53,2,FALSE) -> 505944.17 | S2: =E1*VLOOKUP('Cum. payments'!BR2,Exposure!$B$33:$C$53,2,FALSE)/VLOOKUP('Cum. payments'!BC2,Exposure!$B$33:$C$53,2,FALSE) -> 370103.8 | T2: =F1*VLOOKUP('Cum. payments'!BS2,Exposure!$B$33:$C$53,2,FALSE)/VLOOKUP('Cum. payments'!BD2,Exposure!$B$33:$C$53,2,FALSE) -> 89014.712 | U2: =G1*VLOOKUP('Cum. payments'!BT2,Exposure!$B$33:$C$53,2,FALSE)/VLOOKUP('Cum. payments'!BE2,Exposure!$B$33:$C$53,2,FALSE) -> 82250.087 | V2: =H1*VLOOKUP('Cum. payments'!BU2,Exposure!$B$33:$C$53,2,FALSE)/VLOOKUP('Cum. payments'!BF2,Exposure!$B$33:$C$53,2,FALSE) -> 26241.152 | W2: =I1*VLOOKUP('Cum. payments'!BV2,Exposure!$B$33:$C$53,2,FALSE)/VLOOKUP('Cum. payments'!BG2,Exposure!$B$33:$C$53,2,FALSE) -> 19822.507 | ... Y2: =K1*VLOOKUP('Cum. payments'!BX2,Exposure!$B$33:$C$53,2,FALSE)/VLOOKUP('Cum. payments'!BI2,Exposure!$B$33:$C$53,2,FALSE) -> 103.92034
A3: 42427 | B3: 622872.77 | C3: 604063.01 | D3: 705529.75 | E3: 34986.659 | F3: 31324.434 | G3: 23467.864 | H3: 22584.056 | I3: 12037.607 | J3: 5161.3717 | K3: 1898.0263 | O3: =YEAR($A2) -> 2016 | P3: =B2*VLOOKUP('Cum. payments'!BO3,Exposure!$B$33:$C$53,2,FALSE)/VLOOKUP('Cum. payments'!AZ3,Exposure!$B$33:$C$53,2,FALSE) -> 2518356 | Q3: =C2*VLOOKUP('Cum. payments'!BP3,Exposure!$B$33:$C$53,2,FALSE)/VLOOKUP('Cum. payments'!BA3,Exposure!$B$33:$C$53,2,FALSE) -> 1347677.6 | R3: =D2*VLOOKUP('Cum. payments'!BQ3,Exposure!$B$33:$C$53,2,FALSE)/VLOOKUP('Cum. payments'!BB3,Exposure!$B$33:$C$53,2,FALSE) -> 1114350.4 | S3: =E2*VLOOKUP('Cum. payments'!BR3,Exposure!$B$33:$C$53,2,FALSE)/VLOOKUP('Cum. payments'!BC3,Exposure!$B$33:$C$53,2,FALSE) -> 486128.52 | T3: =F2*VLOOKUP('Cum. payments'!BS3,Exposure!$B$33:$C$53,2,FALSE)/VLOOKUP('Cum. payments'!BD3,Exposure!$B$33:$C$53,2,FALSE) -> 92744.332 | U3: =G2*VLOOKUP('Cum. payments'!BT3,Exposure!$B$33:$C$53,2,FALSE)/VLOOKUP('Cum. payments'!BE3,Exposure!$B$33:$C$53,2,FALSE) -> 92079.962 | V3: =H2*VLOOKUP('Cum. payments'!BU3,Exposure!$B$33:$C$53,2,FALSE)/VLOOKUP('Cum. payments'!BF3,Exposure!$B$33:$C$53,2,FALSE) -> 20750.896 | W3: =I2*VLOOKUP('Cum. payments'!BV3,Exposure!$B$33:$C$53,2,FALSE)/VLOOKUP('Cum. payments'!BG3,Exposure!$B$33:$C$53,2,FALSE) -> 659.98716 | ... Y3: =K2*VLOOKUP('Cum. payments'!BX3,Exposure!$B$33:$C$53,2,FALSE)/VLOOKUP('Cum. payments'!BI3,Exposure!$B$33:$C$53,2,FALSE) -> 0.16622376
A4: 42443 | B4: 4402747.7 | C4: 1638380.2 | D4: 655167.58 | E4: 267151.34 | F4: 315418.28 | G4: 173837.28 | H4: 148743.73 | I4: 151407.56 | J4: 19078.16 | K4: 12497.375 | O4: =YEAR($A3) -> 2016 | P4: =B3*VLOOKUP('Cum. payments'!BO4,Exposure!$B$33:$C$53,2,FALSE)/VLOOKUP('Cum. payments'!AZ4,Exposure!$B$33:$C$53,2,FALSE) -> 1000249.2 | Q4: =C3*VLOOKUP('Cum. payments'!BP4,Exposure!$B$33:$C$53,2,FALSE)/VLOOKUP('Cum. payments'!BA4,Exposure!$B$33:$C$53,2,FALSE) -> 966974.27 | R4: =D3*VLOOKUP('Cum. payments'!BQ4,Exposure!$B$33:$C$53,2,FALSE)/VLOOKUP('Cum. payments'!BB4,Exposure!$B$33:$C$53,2,FALSE) -> 1126651.8 | S4: =E3*VLOOKUP('Cum. payments'!BR4,Exposure!$B$33:$C$53,2,FALSE)/VLOOKUP('Cum. payments'!BC4,Exposure!$B$33:$C$53,2,FALSE) -> 56064.343 | T4: =F3*VLOOKUP('Cum. payments'!BS4,Exposure!$B$33:$C$53,2,FALSE)/VLOOKUP('Cum. payments'!BD4,Exposure!$B$33:$C$53,2,FALSE) -> 50715.558 | U4: =G3*VLOOKUP('Cum. payments'!BT4,Exposure!$B$33:$C$53,2,FALSE)/VLOOKUP('Cum. payments'!BE4,Exposure!$B$33:$C$53,2,FALSE) -> 37761.186 | V4: =H3*VLOOKUP('Cum. payments'!BU4,Exposure!$B$33:$C$53,2,FALSE)/VLOOKUP('Cum. payments'!BF4,Exposure!$B$33:$C$53,2,FALSE) -> 33794.116 | W4: =I3*VLOOKUP('Cum. payments'!BV4,Exposure!$B$33:$C$53,2,FALSE)/VLOOKUP('Cum. payments'!BG4,Exposure!$B$33:$C$53,2,FALSE) -> 17618.032 | ... Y4: =K3*VLOOKUP('Cum. payments'!BX4,Exposure!$B$33:$C$53,2,FALSE)/VLOOKUP('Cum. payments'!BI4,Exposure!$B$33:$C$53,2,FALSE) -> 2724.5407
A5: 42500 | B5: 756782.2 | C5: 993502.33 | D5: 584810.65 | E5: 551731.85 | F5: 607027.19 | G5: 9749.6377 | H5: 2920.8744 | I5: 3044.7919 | J5: 1884.7599 | K5: 0 | O5: =YEAR($A4) -> 2016 | P5: =B4*VLOOKUP('Cum. payments'!BO5,Exposure!$B$33:$C$53,2,FALSE)/VLOOKUP('Cum. payments'!AZ5,Exposure!$B$33:$C$53,2,FALSE) -> 7070216 | Q5: =C4*VLOOKUP('Cum. payments'!BP5,Exposure!$B$33:$C$53,2,FALSE)/VLOOKUP('Cum. payments'!BA5,Exposure!$B$33:$C$53,2,FALSE) -> 2622692.4 | R5: =D4*VLOOKUP('Cum. payments'!BQ5,Exposure!$B$33:$C$53,2,FALSE)/VLOOKUP('Cum. payments'!BB5,Exposure!$B$33:$C$53,2,FALSE) -> 1046229.1 | S5: =E4*VLOOKUP('Cum. payments'!BR5,Exposure!$B$33:$C$53,2,FALSE)/VLOOKUP('Cum. payments'!BC5,Exposure!$B$33:$C$53,2,FALSE) -> 428096.45 | T5: =F4*VLOOKUP('Cum. payments'!BS5,Exposure!$B$33:$C$53,2,FALSE)/VLOOKUP('Cum. payments'!BD5,Exposure!$B$33:$C$53,2,FALSE) -> 510675.29 | U5: =G4*VLOOKUP('Cum. payments'!BT5,Exposure!$B$33:$C$53,2,FALSE)/VLOOKUP('Cum. payments'!BE5,Exposure!$B$33:$C$53,2,FALSE) -> 279714.49 | V5: =H4*VLOOKUP('Cum. payments'!BU5,Exposure!$B$33:$C$53,2,FALSE)/VLOOKUP('Cum. payments'!BF5,Exposure!$B$33:$C$53,2,FALSE) -> 222575.73 | W5: =I4*VLOOKUP('Cum. payments'!BV5,Exposure!$B$33:$C$53,2,FALSE)/VLOOKUP('Cum. payments'!BG5,Exposure!$B$33:$C$53,2,FALSE) -> 221597.46 | ... Y5: =K4*VLOOKUP('Cum. payments'!BX5,Exposure!$B$33:$C$53,2,FALSE)/VLOOKUP('Cum. payments'!BI5,Exposure!$B$33:$C$53,2,FALSE) -> 17939.482
A6: 42513 | B6: 2044548.5 | C6: 1184727.6 | D6: 1364172.4 | E6: 1449966 | F6: 23025.668 | G6: 1058.1314 | H6: 35.355607 | I6: 19.161024 | J6: 2.3776374 | K6: 2.2207382 | O6: =YEAR($A5) -> 2016 | P6: =B5*VLOOKUP('Cum. payments'!BO6,Exposure!$B$33:$C$53,2,FALSE)/VLOOKUP('Cum. payments'!AZ6,Exposure!$B$33:$C$53,2,FALSE) -> 1215289.6 | Q6: =C5*VLOOKUP('Cum. payments'!BP6,Exposure!$B$33:$C$53,2,FALSE)/VLOOKUP('Cum. payments'!BA6,Exposure!$B$33:$C$53,2,FALSE) -> 1590382.4 | R6: =D5*VLOOKUP('Cum. payments'!BQ6,Exposure!$B$33:$C$53,2,FALSE)/VLOOKUP('Cum. payments'!BB6,Exposure!$B$33:$C$53,2,FALSE) -> 933876.97 | S6: =E5*VLOOKUP('Cum. payments'!BR6,Exposure!$B$33:$C$53,2,FALSE)/VLOOKUP('Cum. payments'!BC6,Exposure!$B$33:$C$53,2,FALSE) -> 884122.24 | T6: =F5*VLOOKUP('Cum. payments'!BS6,Exposure!$B$33:$C$53,2,FALSE)/VLOOKUP('Cum. payments'!BD6,Exposure!$B$33:$C$53,2,FALSE) -> 982802.2 | U6: =G5*VLOOKUP('Cum. payments'!BT6,Exposure!$B$33:$C$53,2,FALSE)/VLOOKUP('Cum. payments'!BE6,Exposure!$B$33:$C$53,2,FALSE) -> 15687.745 | V6: =H5*VLOOKUP('Cum. payments'!BU6,Exposure!$B$33:$C$53,2,FALSE)/VLOOKUP('Cum. payments'!BF6,Exposure!$B$33:$C$53,2,FALSE) -> 4370.7103 | W6: =I5*VLOOKUP('Cum. payments'!BV6,Exposure!$B$33:$C$53,2,FALSE)/VLOOKUP('Cum. payments'!BG6,Exposure!$B$33:$C$53,2,FALSE) -> 4456.3043 | ... Y6: =K5*VLOOKUP('Cum. payments'!BX6,Exposure!$B$33:$C$53,2,FALSE)/VLOOKUP('Cum. payments'!BI6,Exposure!$B$33:$C$53,2,FALSE) -> 0
A7: 42516 | B7: 4413698 | C7: 2223980.9 | D7: 3823417 | E7: 1354292.8 | F7: 1108124.5 | G7: 661473.55 | H7: 29733.699 | I7: 16705.815 | J7: 6315.1568 | K7: 1311.3642 | O7: =YEAR($A6) -> 2016 | P7: =B6*VLOOKUP('Cum. payments'!BO7,Exposure!$B$33:$C$53,2,FALSE)/VLOOKUP('Cum. payments'!AZ7,Exposure!$B$33:$C$53,2,FALSE) -> 3283267.7 | Q7: =C6*VLOOKUP('Cum. payments'!BP7,Exposure!$B$33:$C$53,2,FALSE)/VLOOKUP('Cum. payments'!BA7,Exposure!$B$33:$C$53,2,FALSE) -> 1896492.8 | R7: =D6*VLOOKUP('Cum. payments'!BQ7,Exposure!$B$33:$C$53,2,FALSE)/VLOOKUP('Cum. payments'!BB7,Exposure!$B$33:$C$53,2,FALSE) -> 2178430.3 | S7: =E6*VLOOKUP('Cum. payments'!BR7,Exposure!$B$33:$C$53,2,FALSE)/VLOOKUP('Cum. payments'!BC7,Exposure!$B$33:$C$53,2,FALSE) -> 2323496.8 | T7: =F6*VLOOKUP('Cum. payments'!BS7,Exposure!$B$33:$C$53,2,FALSE)/VLOOKUP('Cum. payments'!BD7,Exposure!$B$33:$C$53,2,FALSE) -> 37279.512 | U7: =G6*VLOOKUP('Cum. payments'!BT7,Exposure!$B$33:$C$53,2,FALSE)/VLOOKUP('Cum. payments'!BE7,Exposure!$B$33:$C$53,2,FALSE) -> 1702.5962 | V7: =H6*VLOOKUP('Cum. payments'!BU7,Exposure!$B$33:$C$53,2,FALSE)/VLOOKUP('Cum. payments'!BF7,Exposure!$B$33:$C$53,2,FALSE) -> 52.905088 | W7: =I6*VLOOKUP('Cum. payments'!BV7,Exposure!$B$33:$C$53,2,FALSE)/VLOOKUP('Cum. payments'!BG7,Exposure!$B$33:$C$53,2,FALSE) -> 28.043741 | ... Y7: =K6*VLOOKUP('Cum. payments'!BX7,Exposure!$B$33:$C$53,2,FALSE)/VLOOKUP('Cum. payments'!BI7,Exposure!$B$33:$C$53,2,FALSE) -> 3.1877807
A8: 42539 | B8: 649026.69 | C8: 138605.46 | D8: 165546.39 | E8: 161495.24 | F8: 109973.51 | G8: 64381.81 | H8: 70412.573 | I8: 72025.398 | J8: 76842.527 | K8: 9797.18 | O8: =YEAR($A7) -> 2016 | P8: =B7*VLOOKUP('Cum. payments'!BO8,Exposure!$B$33:$C$53,2,FALSE)/VLOOKUP('Cum. payments'!AZ8,Exposure!$B$33:$C$53,2,FALSE) -> 7087800.6 | Q8: =C7*VLOOKUP('Cum. payments'!BP8,Exposure!$B$33:$C$53,2,FALSE)/VLOOKUP('Cum. payments'!BA8,Exposure!$B$33:$C$53,2,FALSE) -> 3560112.6 | R8: =D7*VLOOKUP('Cum. payments'!BQ8,Exposure!$B$33:$C$53,2,FALSE)/VLOOKUP('Cum. payments'!BB8,Exposure!$B$33:$C$53,2,FALSE) -> 6105567.8 | S8: =E7*VLOOKUP('Cum. payments'!BR8,Exposure!$B$33:$C$53,2,FALSE)/VLOOKUP('Cum. payments'!BC8,Exposure!$B$33:$C$53,2,FALSE) -> 2170185.4 | T8: =F7*VLOOKUP('Cum. payments'!BS8,Exposure!$B$33:$C$53,2,FALSE)/VLOOKUP('Cum. payments'!BD8,Exposure!$B$33:$C$53,2,FALSE) -> 1794099.5 | U8: =G7*VLOOKUP('Cum. payments'!BT8,Exposure!$B$33:$C$53,2,FALSE)/VLOOKUP('Cum. payments'!BE8,Exposure!$B$33:$C$53,2,FALSE) -> 1064350.2 | V8: =H7*VLOOKUP('Cum. payments'!BU8,Exposure!$B$33:$C$53,2,FALSE)/VLOOKUP('Cum. payments'!BF8,Exposure!$B$33:$C$53,2,FALSE) -> 44492.63 | W8: =I7*VLOOKUP('Cum. payments'!BV8,Exposure!$B$33:$C$53,2,FALSE)/VLOOKUP('Cum. payments'!BG8,Exposure!$B$33:$C$53,2,FALSE) -> 24450.339 | ... Y8: =K7*VLOOKUP('Cum. payments'!BX8,Exposure!$B$33:$C$53,2,FALSE)/VLOOKUP('Cum. payments'!BI8,Exposure!$B$33:$C$53,2,FALSE) -> 1882.4108
A9: 42562 | B9: 600882.22 | C9: 304345.88 | D9: 337267.95 | E9: 193771.77 | F9: 3084.5656 | G9: 3239.2355 | H9: 541.41712 | I9: 23.718377 | J9: 1.4809416 | K9: 0.33018253 | O9: =YEAR($A8) -> 2016 | P9: =B8*VLOOKUP('Cum. payments'!BO9,Exposure!$B$33:$C$53,2,FALSE)/VLOOKUP('Cum. payments'!AZ9,Exposure!$B$33:$C$53,2,FALSE) -> 1042248.9 | Q9: =C8*VLOOKUP('Cum. payments'!BP9,Exposure!$B$33:$C$53,2,FALSE)/VLOOKUP('Cum. payments'!BA9,Exposure!$B$33:$C$53,2,FALSE) -> 221877.38 | R9: =D8*VLOOKUP('Cum. payments'!BQ9,Exposure!$B$33:$C$53,2,FALSE)/VLOOKUP('Cum. payments'!BB9,Exposure!$B$33:$C$53,2,FALSE) -> 264359.01 | S9: =E8*VLOOKUP('Cum. payments'!BR9,Exposure!$B$33:$C$53,2,FALSE)/VLOOKUP('Cum. payments'!BC9,Exposure!$B$33:$C$53,2,FALSE) -> 258787.92 | T9: =F8*VLOOKUP('Cum. payments'!BS9,Exposure!$B$33:$C$53,2,FALSE)/VLOOKUP('Cum. payments'!BD9,Exposure!$B$33:$C$53,2,FALSE) -> 178051.67 | U9: =G8*VLOOKUP('Cum. payments'!BT9,Exposure!$B$33:$C$53,2,FALSE)/VLOOKUP('Cum. payments'!BE9,Exposure!$B$33:$C$53,2,FALSE) -> 103594.15 | V9: =H8*VLOOKUP('Cum. payments'!BU9,Exposure!$B$33:$C$53,2,FALSE)/VLOOKUP('Cum. payments'!BF9,Exposure!$B$33:$C$53,2,FALSE) -> 105363.3 | W9: =I8*VLOOKUP('Cum. payments'!BV9,Exposure!$B$33:$C$53,2,FALSE)/VLOOKUP('Cum. payments'!BG9,Exposure!$B$33:$C$53,2,FALSE) -> 105415.11 | ... Y9: =K8*VLOOKUP('Cum. payments'!BX9,Exposure!$B$33:$C$53,2,FALSE)/VLOOKUP('Cum. payments'!BI9,Exposure!$B$33:$C$53,2,FALSE) -> 14063.459
A10: 42598 | B10: 847936.66 | C10: 1163013.8 | D10: 1208772.3 | E10: 1067908.9 | F10: 165297.25 | G10: 37113.145 | H10: 13546.047 | I10: 1616.2027 | J10: 119.26577 | K10: 124.3706 | O10: =YEAR($A9) -> 2016 | P10: =B9*VLOOKUP('Cum. payments'!BO10,Exposure!$B$33:$C$53,2,FALSE)/VLOOKUP('Cum. payments'!AZ10,Exposure!$B$33:$C$53,2,FALSE) -> 964935.39 | Q10: =C9*VLOOKUP('Cum. payments'!BP10,Exposure!$B$33:$C$53,2,FALSE)/VLOOKUP('Cum. payments'!BA10,Exposure!$B$33:$C$53,2,FALSE) -> 487191.95 | R10: =D9*VLOOKUP('Cum. payments'!BQ10,Exposure!$B$33:$C$53,2,FALSE)/VLOOKUP('Cum. payments'!BB10,Exposure!$B$33:$C$53,2,FALSE) -> 538579.06 | S10: =E9*VLOOKUP('Cum. payments'!BR10,Exposure!$B$33:$C$53,2,FALSE)/VLOOKUP('Cum. payments'!BC10,Exposure!$B$33:$C$53,2,FALSE) -> 310509.42 | T10: =F9*VLOOKUP('Cum. payments'!BS10,Exposure!$B$33:$C$53,2,FALSE)/VLOOKUP('Cum. payments'!BD10,Exposure!$B$33:$C$53,2,FALSE) -> 4994.0396 | U10: =G9*VLOOKUP('Cum. payments'!BT10,Exposure!$B$33:$C$53,2,FALSE)/VLOOKUP('Cum. payments'!BE10,Exposure!$B$33:$C$53,2,FALSE) -> 5212.1222 | V10: =H9*VLOOKUP('Cum. payments'!BU10,Exposure!$B$33:$C$53,2,FALSE)/VLOOKUP('Cum. payments'!BF10,Exposure!$B$33:$C$53,2,FALSE) -> 810.1606 | W10: =I9*VLOOKUP('Cum. payments'!BV10,Exposure!$B$33:$C$53,2,FALSE)/VLOOKUP('Cum. payments'!BG10,Exposure!$B$33:$C$53,2,FALSE) -> 34.713802 | ... Y10: =K9*VLOOKUP('Cum. payments'!BX10,Exposure!$B$33:$C$53,2,FALSE)/VLOOKUP('Cum. payments'!BI10,Exposure!$B$33:$C$53,2,FALSE) -> 0.47396379
A11: 42618 | B11: 2614373.1 | C11: 1983780.6 | D11: 300076.04 | E11: 216086.52 | F11: 17905.537 | G11: 10881.99 | H11: 227.22912 | I11: 226.10434 | J11: 1.4606018 | K11: 0.76393196 | O11: =YEAR($A10) -> 2016 | P11: =B10*VLOOKUP('Cum. payments'!BO11,Exposure!$B$33:$C$53,2,FALSE)/VLOOKUP('Cum. payments'!AZ11,Exposure!$B$33:$C$53,2,FALSE) -> 1361671.3 | Q11: =C10*VLOOKUP('Cum. payments'!BP11,Exposure!$B$33:$C$53,2,FALSE)/VLOOKUP('Cum. payments'!BA11,Exposure!$B$33:$C$53,2,FALSE) -> 1861733.7 | R11: =D10*VLOOKUP('Cum. payments'!BQ11,Exposure!$B$33:$C$53,2,FALSE)/VLOOKUP('Cum. payments'!BB11,Exposure!$B$33:$C$53,2,FALSE) -> 1930273.7 | S11: =E10*VLOOKUP('Cum. payments'!BR11,Exposure!$B$33:$C$53,2,FALSE)/VLOOKUP('Cum. payments'!BC11,Exposure!$B$33:$C$53,2,FALSE) -> 1711269.8 | T11: =F10*VLOOKUP('Cum. payments'!BS11,Exposure!$B$33:$C$53,2,FALSE)/VLOOKUP('Cum. payments'!BD11,Exposure!$B$33:$C$53,2,FALSE) -> 267623.11 | U11: =G10*VLOOKUP('Cum. payments'!BT11,Exposure!$B$33:$C$53,2,FALSE)/VLOOKUP('Cum. payments'!BE11,Exposure!$B$33:$C$53,2,FALSE) -> 59717.252 | V11: =H10*VLOOKUP('Cum. payments'!BU11,Exposure!$B$33:$C$53,2,FALSE)/VLOOKUP('Cum. payments'!BF11,Exposure!$B$33:$C$53,2,FALSE) -> 20269.905 | W11: =I10*VLOOKUP('Cum. payments'!BV11,Exposure!$B$33:$C$53,2,FALSE)/VLOOKUP('Cum. payments'!BG11,Exposure!$B$33:$C$53,2,FALSE) -> 2365.4461 | ... Y11: =K10*VLOOKUP('Cum. payments'!BX11,Exposure!$B$33:$C$53,2,FALSE)/VLOOKUP('Cum. payments'!BI11,Exposure!$B$33:$C$53,2,FALSE) -> 178.52902
A12: 42630 | B12: 1064486.1 | C12: 863070.22 | D12: 1117585.4 | E12: 75965.852 | F12: 8961.4226 | G12: 4.0481401 | H12: 2.7886569 | I12: 2.3927865 | J12: 0.78737409 | K12: 0.20659406 | O12: =YEAR($A11) -> 2016 | P12: =B11*VLOOKUP('Cum. payments'!BO12,Exposure!$B$33:$C$53,2,FALSE)/VLOOKUP('Cum. payments'!AZ12,Exposure!$B$33:$C$53,2,FALSE) -> 4198328.8 | Q12: =C11*VLOOKUP('Cum. payments'!BP12,Exposure!$B$33:$C$53,2,FALSE)/VLOOKUP('Cum. payments'!BA12,Exposure!$B$33:$C$53,2,FALSE) -> 3175603.7 | R12: =D11*VLOOKUP('Cum. payments'!BQ12,Exposure!$B$33:$C$53,2,FALSE)/VLOOKUP('Cum. payments'!BB12,Exposure!$B$33:$C$53,2,FALSE) -> 479187.75 | S12: =E11*VLOOKUP('Cum. payments'!BR12,Exposure!$B$33:$C$53,2,FALSE)/VLOOKUP('Cum. payments'!BC12,Exposure!$B$33:$C$53,2,FALSE) -> 346267.66 | T12: =F11*VLOOKUP('Cum. payments'!BS12,Exposure!$B$33:$C$53,2,FALSE)/VLOOKUP('Cum. payments'!BD12,Exposure!$B$33:$C$53,2,FALSE) -> 28989.808 | U12: =G11*VLOOKUP('Cum. payments'!BT12,Exposure!$B$33:$C$53,2,FALSE)/VLOOKUP('Cum. payments'!BE12,Exposure!$B$33:$C$53,2,FALSE) -> 17509.768 | V12: =H11*VLOOKUP('Cum. payments'!BU12,Exposure!$B$33:$C$53,2,FALSE)/VLOOKUP('Cum. payments'!BF12,Exposure!$B$33:$C$53,2,FALSE) -> 340.01895 | W12: =I11*VLOOKUP('Cum. payments'!BV12,Exposure!$B$33:$C$53,2,FALSE)/VLOOKUP('Cum. payments'!BG12,Exposure!$B$33:$C$53,2,FALSE) -> 330.92236 | ... Y12: =K11*VLOOKUP('Cum. payments'!BX12,Exposure!$B$33:$C$53,2,FALSE)/VLOOKUP('Cum. payments'!BI12,Exposure!$B$33:$C$53,2,FALSE) -> 1.0965937
A13: 42673 | B13: 430407.86 | C13: 655081.62 | D13: 46455.527 | E13: 2543.8967 | F13: 2642.9722 | G13: 481.59721 | H13: 69.093593 | I13: 52.846442 | J13: 33.268029 | K13: 0 | O13: =YEAR($A12) -> 2016 | P13: =B12*VLOOKUP('Cum. payments'!BO13,Exposure!$B$33:$C$53,2,FALSE)/VLOOKUP('Cum. payments'!AZ13,Exposure!$B$33:$C$53,2,FALSE) -> 1709420.3 | Q13: =C12*VLOOKUP('Cum. payments'!BP13,Exposure!$B$33:$C$53,2,FALSE)/VLOOKUP('Cum. payments'!BA13,Exposure!$B$33:$C$53,2,FALSE) -> 1381588.8 | R13: =D12*VLOOKUP('Cum. payments'!BQ13,Exposure!$B$33:$C$53,2,FALSE)/VLOOKUP('Cum. payments'!BB13,Exposure!$B$33:$C$53,2,FALSE) -> 1784658.4 | S13: =E12*VLOOKUP('Cum. payments'!BR13,Exposure!$B$33:$C$53,2,FALSE)/VLOOKUP('Cum. payments'!BC13,Exposure!$B$33:$C$53,2,FALSE) -> 121731.42 | T13: =F12*VLOOKUP('Cum. payments'!BS13,Exposure!$B$33:$C$53,2,FALSE)/VLOOKUP('Cum. payments'!BD13,Exposure!$B$33:$C$53,2,FALSE) -> 14508.915 | U13: =G12*VLOOKUP('Cum. payments'!BT13,Exposure!$B$33:$C$53,2,FALSE)/VLOOKUP('Cum. payments'!BE13,Exposure!$B$33:$C$53,2,FALSE) -> 6.5136976 | V13: =H12*VLOOKUP('Cum. payments'!BU13,Exposure!$B$33:$C$53,2,FALSE)/VLOOKUP('Cum. payments'!BF13,Exposure!$B$33:$C$53,2,FALSE) -> 4.1728639 | W13: =I12*VLOOKUP('Cum. payments'!BV13,Exposure!$B$33:$C$53,2,FALSE)/VLOOKUP('Cum. payments'!BG13,Exposure!$B$33:$C$53,2,FALSE) -> 3.5020406 | ... Y13: =K12*VLOOKUP('Cum. payments'!BX13,Exposure!$B$33:$C$53,2,FALSE)/VLOOKUP('Cum. payments'!BI13,Exposure!$B$33:$C$53,2,FALSE) -> 0.29655749
A14: 42683 | B14: 562059 | C14: 999244.57 | D14: 1392780.9 | E14: =1456537 -> 1456537 | F14: 552419.63 | G14: 125908.87 | H14: 74795.276 | I14: 14662.9 | J14: 11291.083 | K14: 13044.348 | O14: =YEAR($A13) -> 2016 | P14: =B13*VLOOKUP('Cum. payments'!BO14,Exposure!$B$33:$C$53,2,FALSE)/VLOOKUP('Cum. payments'!AZ14,Exposure!$B$33:$C$53,2,FALSE) -> 691176.68 | Q14: =C13*VLOOKUP('Cum. payments'!BP14,Exposure!$B$33:$C$53,2,FALSE)/VLOOKUP('Cum. payments'!BA14,Exposure!$B$33:$C$53,2,FALSE) -> 1048644 | R14: =D13*VLOOKUP('Cum. payments'!BQ14,Exposure!$B$33:$C$53,2,FALSE)/VLOOKUP('Cum. payments'!BB14,Exposure!$B$33:$C$53,2,FALSE) -> 74184.262 | S14: =E13*VLOOKUP('Cum. payments'!BR14,Exposure!$B$33:$C$53,2,FALSE)/VLOOKUP('Cum. payments'!BC14,Exposure!$B$33:$C$53,2,FALSE) -> 4076.4651 | T14: =F13*VLOOKUP('Cum. payments'!BS14,Exposure!$B$33:$C$53,2,FALSE)/VLOOKUP('Cum. payments'!BD14,Exposure!$B$33:$C$53,2,FALSE) -> 4279.0817 | U14: =G13*VLOOKUP('Cum. payments'!BT14,Exposure!$B$33:$C$53,2,FALSE)/VLOOKUP('Cum. payments'!BE14,Exposure!$B$33:$C$53,2,FALSE) -> 774.91848 | V14: =H13*VLOOKUP('Cum. payments'!BU14,Exposure!$B$33:$C$53,2,FALSE)/VLOOKUP('Cum. payments'!BF14,Exposure!$B$33:$C$53,2,FALSE) -> 103.38962 | W14: =I13*VLOOKUP('Cum. payments'!BV14,Exposure!$B$33:$C$53,2,FALSE)/VLOOKUP('Cum. payments'!BG14,Exposure!$B$33:$C$53,2,FALSE) -> 77.34513 | ... Y14: =K13*VLOOKUP('Cum. payments'!BX14,Exposure!$B$33:$C$53,2,FALSE)/VLOOKUP('Cum. payments'!BI14,Exposure!$B$33:$C$53,2,FALSE) -> 0
A15: 42721 | B15: 1845602.6 | C15: 1068489.8 | D15: 1321665.1 | E15: 1244706 | F15: 1686668.7 | G15: 1325635.8 | H15: 1065777.4 | I15: 902615.07 | J15: 120253.58 | K15: 100746.13 | O15: =YEAR($A14) -> 2016 | P15: =B14*VLOOKUP('Cum. payments'!BO15,Exposure!$B$33:$C$53,2,FALSE)/VLOOKUP('Cum. payments'!AZ15,Exposure!$B$33:$C$53,2,FALSE) -> 902590.55 | Q15: =C14*VLOOKUP('Cum. payments'!BP15,Exposure!$B$33:$C$53,2,FALSE)/VLOOKUP('Cum. payments'!BA15,Exposure!$B$33:$C$53,2,FALSE) -> 1599574.5 | R15: =D14*VLOOKUP('Cum. payments'!BQ15,Exposure!$B$33:$C$53,2,FALSE)/VLOOKUP('Cum. payments'!BB15,Exposure!$B$33:$C$53,2,FALSE) -> 2224114.8 | S15: =E14*VLOOKUP('Cum. payments'!BR15,Exposure!$B$33:$C$53,2,FALSE)/VLOOKUP('Cum. payments'!BC15,Exposure!$B$33:$C$53,2,FALSE) -> 2334026.5 | T15: =F14*VLOOKUP('Cum. payments'!BS15,Exposure!$B$33:$C$53,2,FALSE)/VLOOKUP('Cum. payments'!BD15,Exposure!$B$33:$C$53,2,FALSE) -> 894390.31 | U15: =G14*VLOOKUP('Cum. payments'!BT15,Exposure!$B$33:$C$53,2,FALSE)/VLOOKUP('Cum. payments'!BE15,Exposure!$B$33:$C$53,2,FALSE) -> 202594.85 | V15: =H14*VLOOKUP('Cum. payments'!BU15,Exposure!$B$33:$C$53,2,FALSE)/VLOOKUP('Cum. payments'!BF15,Exposure!$B$33:$C$53,2,FALSE) -> 111921.45 | W15: =I14*VLOOKUP('Cum. payments'!BV15,Exposure!$B$33:$C$53,2,FALSE)/VLOOKUP('Cum. payments'!BG15,Exposure!$B$33:$C$53,2,FALSE) -> 21460.365 | ... Y15: =K14*VLOOKUP('Cum. payments'!BX15,Exposure!$B$33:$C$53,2,FALSE)/VLOOKUP('Cum. payments'!BI15,Exposure!$B$33:$C$53,2,FALSE) -> 18724.639
A16: 42761 | B16: 2767461.9 | C16: 2270887.6 | D16: 1061599.7 | E16: 668752.76 | F16: 384534.64 | G16: 4455.9806 | H16: 3843.0823 | I16: 3168.4673 | J16: 3080.0801 | O16: =YEAR($A15) -> 2016 | P16: =B15*VLOOKUP('Cum. payments'!BO16,Exposure!$B$33:$C$53,2,FALSE)/VLOOKUP('Cum. payments'!AZ16,Exposure!$B$33:$C$53,2,FALSE) -> 2963787.6 | Q16: =C15*VLOOKUP('Cum. payments'!BP16,Exposure!$B$33:$C$53,2,FALSE)/VLOOKUP('Cum. payments'!BA16,Exposure!$B$33:$C$53,2,FALSE) -> 1710421.2 | R16: =D15*VLOOKUP('Cum. payments'!BQ16,Exposure!$B$33:$C$53,2,FALSE)/VLOOKUP('Cum. payments'!BB16,Exposure!$B$33:$C$53,2,FALSE) -> 2110550.7 | S16: =E15*VLOOKUP('Cum. payments'!BR16,Exposure!$B$33:$C$53,2,FALSE)/VLOOKUP('Cum. payments'!BC16,Exposure!$B$33:$C$53,2,FALSE) -> 1994578 | T16: =F15*VLOOKUP('Cum. payments'!BS16,Exposure!$B$33:$C$53,2,FALSE)/VLOOKUP('Cum. payments'!BD16,Exposure!$B$33:$C$53,2,FALSE) -> 2730786.6 | U16: =G15*VLOOKUP('Cum. payments'!BT16,Exposure!$B$33:$C$53,2,FALSE)/VLOOKUP('Cum. payments'!BE16,Exposure!$B$33:$C$53,2,FALSE) -> 2133026.7 | V16: =H15*VLOOKUP('Cum. payments'!BU16,Exposure!$B$33:$C$53,2,FALSE)/VLOOKUP('Cum. payments'!BF16,Exposure!$B$33:$C$53,2,FALSE) -> 1594797.9 | W16: =I15*VLOOKUP('Cum. payments'!BV16,Exposure!$B$33:$C$53,2,FALSE)/VLOOKUP('Cum. payments'!BG16,Exposure!$B$33:$C$53,2,FALSE) -> 1321051.7 | ... Y16: =K15*VLOOKUP('Cum. payments'!BX16,Exposure!$B$33:$C$53,2,FALSE)/VLOOKUP('Cum. payments'!BI16,Exposure!$B$33:$C$53,2,FALSE) -> 144617.03
A17: 42775 | B17: 1943175.2 | C17: 936298.96 | D17: 1232212.6 | E17: 167008.05 | F17: 167087.4 | G17: 136948.86 | H17: 147130.82 | I17: 113863.7 | J17: 94761.578 | O17: =YEAR($A16) -> 2017 | P17: =B16*VLOOKUP('Cum. payments'!BO17,Exposure!$B$33:$C$53,2,FALSE)/VLOOKUP('Cum. payments'!AZ17,Exposure!$B$33:$C$53,2,FALSE) -> 4288584.7 | Q17: =C16*VLOOKUP('Cum. payments'!BP17,Exposure!$B$33:$C$53,2,FALSE)/VLOOKUP('Cum. payments'!BA17,Exposure!$B$33:$C$53,2,FALSE) -> 3510505.8 | R17: =D16*VLOOKUP('Cum. payments'!BQ17,Exposure!$B$33:$C$53,2,FALSE)/VLOOKUP('Cum. payments'!BB17,Exposure!$B$33:$C$53,2,FALSE) -> 1646814.7 | S17: =E16*VLOOKUP('Cum. payments'!BR17,Exposure!$B$33:$C$53,2,FALSE)/VLOOKUP('Cum. payments'!BC17,Exposure!$B$33:$C$53,2,FALSE) -> 1048149.5 | T17: =F16*VLOOKUP('Cum. payments'!BS17,Exposure!$B$33:$C$53,2,FALSE)/VLOOKUP('Cum. payments'!BD17,Exposure!$B$33:$C$53,2,FALSE) -> 598972.94 | U17: =G16*VLOOKUP('Cum. payments'!BT17,Exposure!$B$33:$C$53,2,FALSE)/VLOOKUP('Cum. payments'!BE17,Exposure!$B$33:$C$53,2,FALSE) -> 6454.7899 | V17: =H16*VLOOKUP('Cum. payments'!BU17,Exposure!$B$33:$C$53,2,FALSE)/VLOOKUP('Cum. payments'!BF17,Exposure!$B$33:$C$53,2,FALSE) -> 5444.9838 | W17: =I16*VLOOKUP('Cum. payments'!BV17,Exposure!$B$33:$C$53,2,FALSE)/VLOOKUP('Cum. payments'!BG17,Exposure!$B$33:$C$53,2,FALSE) -> 4431.5087 | X17: =J16*VLOOKUP('Cum. payments'!BW17,Exposure!$B$33:$C$53,2,FALSE)/VLOOKUP('Cum. payments'!BH17,Exposure!$B$33:$C$53,2,FALSE) -> 4280.0886
A18: 42832 | B18: 1814132.2 | C18: 1271704.6 | D18: 852166.84 | E18: 646038.88 | F18: 826130.53 | G18: 358336.32 | H18: 385756.03 | I18: 231929.43 | J18: 234191.12 | O18: =YEAR($A17) -> 2017 | P18: =B17*VLOOKUP('Cum. payments'!BO18,Exposure!$B$33:$C$53,2,FALSE)/VLOOKUP('Cum. payments'!AZ18,Exposure!$B$33:$C$53,2,FALSE) -> 3011232.7 | Q18: =C17*VLOOKUP('Cum. payments'!BP18,Exposure!$B$33:$C$53,2,FALSE)/VLOOKUP('Cum. payments'!BA18,Exposure!$B$33:$C$53,2,FALSE) -> 1447400.1 | R18: =D17*VLOOKUP('Cum. payments'!BQ18,Exposure!$B$33:$C$53,2,FALSE)/VLOOKUP('Cum. payments'!BB18,Exposure!$B$33:$C$53,2,FALSE) -> 1911479.2 | S18: =E17*VLOOKUP('Cum. payments'!BR18,Exposure!$B$33:$C$53,2,FALSE)/VLOOKUP('Cum. payments'!BC18,Exposure!$B$33:$C$53,2,FALSE) -> 261755.04 | T18: =F17*VLOOKUP('Cum. payments'!BS18,Exposure!$B$33:$C$53,2,FALSE)/VLOOKUP('Cum. payments'!BD18,Exposure!$B$33:$C$53,2,FALSE) -> 260264.79 | U18: =G17*VLOOKUP('Cum. payments'!BT18,Exposure!$B$33:$C$53,2,FALSE)/VLOOKUP('Cum. payments'!BE18,Exposure!$B$33:$C$53,2,FALSE) -> 198379.71 | V18: =H17*VLOOKUP('Cum. payments'!BU18,Exposure!$B$33:$C$53,2,FALSE)/VLOOKUP('Cum. payments'!BF18,Exposure!$B$33:$C$53,2,FALSE) -> 208458.96 | W18: =I17*VLOOKUP('Cum. payments'!BV18,Exposure!$B$33:$C$53,2,FALSE)/VLOOKUP('Cum. payments'!BG18,Exposure!$B$33:$C$53,2,FALSE) -> 159253.02 | X18: =J17*VLOOKUP('Cum. payments'!BW18,Exposure!$B$33:$C$53,2,FALSE)/VLOOKUP('Cum. payments'!BH18,Exposure!$B$33:$C$53,2,FALSE) -> 131680.98
A19: 42844 | B19: 1971197.6 | C19: 1223914.9 | D19: 395433.47 | E19: 481067.89 | F19: 0.21032496 | G19: 0.084024145 | H19: 0.00046615099 | I19: 9.9112236e-05 | J19: 3.8934411e-05 | O19: =YEAR($A18) -> 2017 | P19: =B18*VLOOKUP('Cum. payments'!BO19,Exposure!$B$33:$C$53,2,FALSE)/VLOOKUP('Cum. payments'!AZ19,Exposure!$B$33:$C$53,2,FALSE) -> 2811261.8 | Q19: =C18*VLOOKUP('Cum. payments'!BP19,Exposure!$B$33:$C$53,2,FALSE)/VLOOKUP('Cum. payments'!BA19,Exposure!$B$33:$C$53,2,FALSE) -> 1965895 | R19: =D18*VLOOKUP('Cum. payments'!BQ19,Exposure!$B$33:$C$53,2,FALSE)/VLOOKUP('Cum. payments'!BB19,Exposure!$B$33:$C$53,2,FALSE) -> 1321930.3 | S19: =E18*VLOOKUP('Cum. payments'!BR19,Exposure!$B$33:$C$53,2,FALSE)/VLOOKUP('Cum. payments'!BC19,Exposure!$B$33:$C$53,2,FALSE) -> 1012549.6 | T19: =F18*VLOOKUP('Cum. payments'!BS19,Exposure!$B$33:$C$53,2,FALSE)/VLOOKUP('Cum. payments'!BD19,Exposure!$B$33:$C$53,2,FALSE) -> 1286827.7 | U19: =G18*VLOOKUP('Cum. payments'!BT19,Exposure!$B$33:$C$53,2,FALSE)/VLOOKUP('Cum. payments'!BE19,Exposure!$B$33:$C$53,2,FALSE) -> 519074.44 | V19: =H18*VLOOKUP('Cum. payments'!BU19,Exposure!$B$33:$C$53,2,FALSE)/VLOOKUP('Cum. payments'!BF19,Exposure!$B$33:$C$53,2,FALSE) -> 546549.65 | W19: =I18*VLOOKUP('Cum. payments'!BV19,Exposure!$B$33:$C$53,2,FALSE)/VLOOKUP('Cum. payments'!BG19,Exposure!$B$33:$C$53,2,FALSE) -> 324383.12 | X19: =J18*VLOOKUP('Cum. payments'!BW19,Exposure!$B$33:$C$53,2,FALSE)/VLOOKUP('Cum. payments'!BH19,Exposure!$B$33:$C$53,2,FALSE) -> 325432.69
A20: 42844 | B20: 1540538.5 | C20: 743442.46 | D20: 873562.37 | E20: 95805.46 | F20: 53188.662 | G20: 50645.393 | H20: 29429.158 | I20: 25041.088 | J20: 25563.378 | O20: =YEAR($A19) -> 2017 | P20: =B19*VLOOKUP('Cum. payments'!BO20,Exposure!$B$33:$C$53,2,FALSE)/VLOOKUP('Cum. payments'!AZ20,Exposure!$B$33:$C$53,2,FALSE) -> 3054657.4 | Q20: =C19*VLOOKUP('Cum. payments'!BP20,Exposure!$B$33:$C$53,2,FALSE)/VLOOKUP('Cum. payments'!BA20,Exposure!$B$33:$C$53,2,FALSE) -> 1892018 | R20: =D19*VLOOKUP('Cum. payments'!BQ20,Exposure!$B$33:$C$53,2,FALSE)/VLOOKUP('Cum. payments'!BB20,Exposure!$B$33:$C$53,2,FALSE) -> 613419.21 | S20: =E19*VLOOKUP('Cum. payments'!BR20,Exposure!$B$33:$C$53,2,FALSE)/VLOOKUP('Cum. payments'!BC20,Exposure!$B$33:$C$53,2,FALSE) -> 753987.3 | T20: =F19*VLOOKUP('Cum. payments'!BS20,Exposure!$B$33:$C$53,2,FALSE)/VLOOKUP('Cum. payments'!BD20,Exposure!$B$33:$C$53,2,FALSE) -> 0.32761407 | U20: =G19*VLOOKUP('Cum. payments'!BT20,Exposure!$B$33:$C$53,2,FALSE)/VLOOKUP('Cum. payments'!BE20,Exposure!$B$33:$C$53,2,FALSE) -> 0.12171467 | V20: =H19*VLOOKUP('Cum. payments'!BU20,Exposure!$B$33:$C$53,2,FALSE)/VLOOKUP('Cum. payments'!BF20,Exposure!$B$33:$C$53,2,FALSE) -> 0.00066045543 | W20: =I19*VLOOKUP('Cum. payments'!BV20,Exposure!$B$33:$C$53,2,FALSE)/VLOOKUP('Cum. payments'!BG20,Exposure!$B$33:$C$53,2,FALSE) -> 0.0001386212 | X20: =J19*VLOOKUP('Cum. payments'!BW20,Exposure!$B$33:$C$53,2,FALSE)/VLOOKUP('Cum. payments'!BH20,Exposure!$B$33:$C$53,2,FALSE) -> 5.4103376e-05
A21: 42884 | B21: 793313.4 | C21: 717714.36 | D21: 456520.28 | E21: 480361.87 | F21: 7417.5035 | G21: 6824.0166 | H21: 3261.3649 | I21: 2417.7163 | J21: 0 | O21: =YEAR($A20) -> 2017 | P21: =B20*VLOOKUP('Cum. payments'!BO21,Exposure!$B$33:$C$53,2,FALSE)/VLOOKUP('Cum. payments'!AZ21,Exposure!$B$33:$C$53,2,FALSE) -> 2387288.6 | Q21: =C20*VLOOKUP('Cum. payments'!BP21,Exposure!$B$33:$C$53,2,FALSE)/VLOOKUP('Cum. payments'!BA21,Exposure!$B$33:$C$53,2,FALSE) -> 1149268.3 | R21: =D20*VLOOKUP('Cum. payments'!BQ21,Exposure!$B$33:$C$53,2,FALSE)/VLOOKUP('Cum. payments'!BB21,Exposure!$B$33:$C$53,2,FALSE) -> 1355120.3 | S21: =E20*VLOOKUP('Cum. payments'!BR21,Exposure!$B$33:$C$53,2,FALSE)/VLOOKUP('Cum. payments'!BC21,Exposure!$B$33:$C$53,2,FALSE) -> 150157.81 | T21: =F20*VLOOKUP('Cum. payments'!BS21,Exposure!$B$33:$C$53,2,FALSE)/VLOOKUP('Cum. payments'!BD21,Exposure!$B$33:$C$53,2,FALSE) -> 82849.673 | U21: =G20*VLOOKUP('Cum. payments'!BT21,Exposure!$B$33:$C$53,2,FALSE)/VLOOKUP('Cum. payments'!BE21,Exposure!$B$33:$C$53,2,FALSE) -> 73363.283 | V21: =H20*VLOOKUP('Cum. payments'!BU21,Exposure!$B$33:$C$53,2,FALSE)/VLOOKUP('Cum. payments'!BF21,Exposure!$B$33:$C$53,2,FALSE) -> 41696.033 | W21: =I20*VLOOKUP('Cum. payments'!BV21,Exposure!$B$33:$C$53,2,FALSE)/VLOOKUP('Cum. payments'!BG21,Exposure!$B$33:$C$53,2,FALSE) -> 35023.18 | X21: =J20*VLOOKUP('Cum. payments'!BW21,Exposure!$B$33:$C$53,2,FALSE)/VLOOKUP('Cum. payments'!BH21,Exposure!$B$33:$C$53,2,FALSE) -> 35522.948
A22: 42920 | B22: 4240921.1 | C22: 2366546 | D22: 1681631.1 | E22: 1880251.6 | F22: 95934.235 | G22: 882.54348 | H22: 150.99691 | I22: 140.44724 | J22: 5.1836951 | O22: =YEAR($A21) -> 2017 | P22: =B21*VLOOKUP('Cum. payments'!BO22,Exposure!$B$33:$C$53,2,FALSE)/VLOOKUP('Cum. payments'!AZ22,Exposure!$B$33:$C$53,2,FALSE) -> 1229354.5 | Q22: =C21*VLOOKUP('Cum. payments'!BP22,Exposure!$B$33:$C$53,2,FALSE)/VLOOKUP('Cum. payments'!BA22,Exposure!$B$33:$C$53,2,FALSE) -> 1109495.9 | R22: =D21*VLOOKUP('Cum. payments'!BQ22,Exposure!$B$33:$C$53,2,FALSE)/VLOOKUP('Cum. payments'!BB22,Exposure!$B$33:$C$53,2,FALSE) -> 708180.58 | S22: =E21*VLOOKUP('Cum. payments'!BR22,Exposure!$B$33:$C$53,2,FALSE)/VLOOKUP('Cum. payments'!BC22,Exposure!$B$33:$C$53,2,FALSE) -> 752880.73 | T22: =F21*VLOOKUP('Cum. payments'!BS22,Exposure!$B$33:$C$53,2,FALSE)/VLOOKUP('Cum. payments'!BD22,Exposure!$B$33:$C$53,2,FALSE) -> 11553.924 | U22: =G21*VLOOKUP('Cum. payments'!BT22,Exposure!$B$33:$C$53,2,FALSE)/VLOOKUP('Cum. payments'!BE22,Exposure!$B$33:$C$53,2,FALSE) -> 9885.0506 | V22: =H21*VLOOKUP('Cum. payments'!BU22,Exposure!$B$33:$C$53,2,FALSE)/VLOOKUP('Cum. payments'!BF22,Exposure!$B$33:$C$53,2,FALSE) -> 4620.7906 | W22: =I21*VLOOKUP('Cum. payments'!BV22,Exposure!$B$33:$C$53,2,FALSE)/VLOOKUP('Cum. payments'!BG22,Exposure!$B$33:$C$53,2,FALSE) -> 3381.487 | X22: =J21*VLOOKUP('Cum. payments'!BW22,Exposure!$B$33:$C$53,2,FALSE)/VLOOKUP('Cum. payments'!BH22,Exposure!$B$33:$C$53,2,FALSE) -> 0
A23: 42943 | B23: 1334561.5 | C23: 2267097.6 | D23: 975297.94 | E23: 600401.84 | F23: 184665.25 | G23: 142906.08 | H23: 44355.647 | I23: 43056.051 | J23: 26.99336 | O23: =YEAR($A22) -> 2017 | P23: =B22*VLOOKUP('Cum. payments'!BO23,Exposure!$B$33:$C$53,2,FALSE)/VLOOKUP('Cum. payments'!AZ23,Exposure!$B$33:$C$53,2,FALSE) -> 6571924.2 | Q23: =C22*VLOOKUP('Cum. payments'!BP23,Exposure!$B$33:$C$53,2,FALSE)/VLOOKUP('Cum. payments'!BA23,Exposure!$B$33:$C$53,2,FALSE) -> 3658381.8 | R23: =D22*VLOOKUP('Cum. payments'!BQ23,Exposure!$B$33:$C$53,2,FALSE)/VLOOKUP('Cum. payments'!BB23,Exposure!$B$33:$C$53,2,FALSE) -> 2608643.1 | S23: =E22*VLOOKUP('Cum. payments'!BR23,Exposure!$B$33:$C$53,2,FALSE)/VLOOKUP('Cum. payments'!BC23,Exposure!$B$33:$C$53,2,FALSE) -> 2946955.9 | T23: =F22*VLOOKUP('Cum. payments'!BS23,Exposure!$B$33:$C$53,2,FALSE)/VLOOKUP('Cum. payments'!BD23,Exposure!$B$33:$C$53,2,FALSE) -> 149432.6 | U23: =G22*VLOOKUP('Cum. payments'!BT23,Exposure!$B$33:$C$53,2,FALSE)/VLOOKUP('Cum. payments'!BE23,Exposure!$B$33:$C$53,2,FALSE) -> 1278.424 | V23: =H22*VLOOKUP('Cum. payments'!BU23,Exposure!$B$33:$C$53,2,FALSE)/VLOOKUP('Cum. payments'!BF23,Exposure!$B$33:$C$53,2,FALSE) -> 213.93654 | W23: =I22*VLOOKUP('Cum. payments'!BV23,Exposure!$B$33:$C$53,2,FALSE)/VLOOKUP('Cum. payments'!BG23,Exposure!$B$33:$C$53,2,FALSE) -> 196.43352 | X23: =J22*VLOOKUP('Cum. payments'!BW23,Exposure!$B$33:$C$53,2,FALSE)/VLOOKUP('Cum. payments'!BH23,Exposure!$B$33:$C$53,2,FALSE) -> 7.2032784
A24: 43008 | B24: 1066911.9 | C24: 1263546.8 | D24: 1002662.1 | E24: 913746.96 | F24: 403982.81 | G24: 159850.21 | H24: 102757.38 | I24: 64264.3 | J24: 49965.121 | O24: =YEAR($A23) -> 2017 | P24: =B23*VLOOKUP('Cum. payments'!BO24,Exposure!$B$33:$C$53,2,FALSE)/VLOOKUP('Cum. payments'!AZ24,Exposure!$B$33:$C$53,2,FALSE) -> 2068097.3 | Q24: =C23*VLOOKUP('Cum. payments'!BP24,Exposure!$B$33:$C$53,2,FALSE)/VLOOKUP('Cum. payments'!BA24,Exposure!$B$33:$C$53,2,FALSE) -> 3504647 | R24: =D23*VLOOKUP('Cum. payments'!BQ24,Exposure!$B$33:$C$53,2,FALSE)/VLOOKUP('Cum. payments'!BB24,Exposure!$B$33:$C$53,2,FALSE) -> 1512938.4 | S24: =E23*VLOOKUP('Cum. payments'!BR24,Exposure!$B$33:$C$53,2,FALSE)/VLOOKUP('Cum. payments'!BC24,Exposure!$B$33:$C$53,2,FALSE) -> 941021.77 | T24: =F23*VLOOKUP('Cum. payments'!BS24,Exposure!$B$33:$C$53,2,FALSE)/VLOOKUP('Cum. payments'!BD24,Exposure!$B$33:$C$53,2,FALSE) -> 287645.06 | U24: =G23*VLOOKUP('Cum. payments'!BT24,Exposure!$B$33:$C$53,2,FALSE)/VLOOKUP('Cum. payments'!BE24,Exposure!$B$33:$C$53,2,FALSE) -> 207009.15 | V24: =H23*VLOOKUP('Cum. payments'!BU24,Exposure!$B$33:$C$53,2,FALSE)/VLOOKUP('Cum. payments'!BF24,Exposure!$B$33:$C$53,2,FALSE) -> 62844.289 | W24: =I23*VLOOKUP('Cum. payments'!BV24,Exposure!$B$33:$C$53,2,FALSE)/VLOOKUP('Cum. payments'!BG24,Exposure!$B$33:$C$53,2,FALSE) -> 60219.421 | X24: =J23*VLOOKUP('Cum. payments'!BW24,Exposure!$B$33:$C$53,2,FALSE)/VLOOKUP('Cum. payments'!BH24,Exposure!$B$33:$C$53,2,FALSE) -> 37.510054
A25: 43020 | B25: 641112.25 | C25: 962799.44 | D25: 206984.96 | E25: 235327.74 | F25: 213335.14 | G25: 135806.84 | H25: 5052.0004 | I25: 1279.9144 | J25: 51.537047 | O25: =YEAR($A24) -> 2017 | P25: =B24*VLOOKUP('Cum. payments'!BO25,Exposure!$B$33:$C$53,2,FALSE)/VLOOKUP('Cum. payments'!AZ25,Exposure!$B$33:$C$53,2,FALSE) -> 1653335.1 | Q25: =C24*VLOOKUP('Cum. payments'!BP25,Exposure!$B$33:$C$53,2,FALSE)/VLOOKUP('Cum. payments'!BA25,Exposure!$B$33:$C$53,2,FALSE) -> 1953284 | R25: =D24*VLOOKUP('Cum. payments'!BQ25,Exposure!$B$33:$C$53,2,FALSE)/VLOOKUP('Cum. payments'!BB25,Exposure!$B$33:$C$53,2,FALSE) -> 1555387.2 | S25: =E24*VLOOKUP('Cum. payments'!BR25,Exposure!$B$33:$C$53,2,FALSE)/VLOOKUP('Cum. payments'!BC25,Exposure!$B$33:$C$53,2,FALSE) -> 1432133.8 | T25: =F24*VLOOKUP('Cum. payments'!BS25,Exposure!$B$33:$C$53,2,FALSE)/VLOOKUP('Cum. payments'!BD25,Exposure!$B$33:$C$53,2,FALSE) -> 629266.51 | U25: =G24*VLOOKUP('Cum. payments'!BT25,Exposure!$B$33:$C$53,2,FALSE)/VLOOKUP('Cum. payments'!BE25,Exposure!$B$33:$C$53,2,FALSE) -> 231553.86 | V25: =H24*VLOOKUP('Cum. payments'!BU25,Exposure!$B$33:$C$53,2,FALSE)/VLOOKUP('Cum. payments'!BF25,Exposure!$B$33:$C$53,2,FALSE) -> 145589.45 | W25: =I24*VLOOKUP('Cum. payments'!BV25,Exposure!$B$33:$C$53,2,FALSE)/VLOOKUP('Cum. payments'!BG25,Exposure!$B$33:$C$53,2,FALSE) -> 89881.884 | X25: =J24*VLOOKUP('Cum. payments'!BW25,Exposure!$B$33:$C$53,2,FALSE)/VLOOKUP('Cum. payments'!BH25,Exposure!$B$33:$C$53,2,FALSE) -> 69431.683
A26: 43038 | B26: 934649 | C26: 2671964.8 | D26: 2258112 | E26: 161386.25 | F26: 114297.73 | G26: 6267.4572 | H26: 5941.6547 | I26: 19.490596 | J26: 0 | O26: =YEAR($A25) -> 2017 | P26: =B25*VLOOKUP('Cum. payments'!BO26,Exposure!$B$33:$C$53,2,FALSE)/VLOOKUP('Cum. payments'!AZ26,Exposure!$B$33:$C$53,2,FALSE) -> 993496.7 | Q26: =C25*VLOOKUP('Cum. payments'!BP26,Exposure!$B$33:$C$53,2,FALSE)/VLOOKUP('Cum. payments'!BA26,Exposure!$B$33:$C$53,2,FALSE) -> 1488366.5 | R26: =D25*VLOOKUP('Cum. payments'!BQ26,Exposure!$B$33:$C$53,2,FALSE)/VLOOKUP('Cum. payments'!BB26,Exposure!$B$33:$C$53,2,FALSE) -> 321087.01 | S26: =E25*VLOOKUP('Cum. payments'!BR26,Exposure!$B$33:$C$53,2,FALSE)/VLOOKUP('Cum. payments'!BC26,Exposure!$B$33:$C$53,2,FALSE) -> 368833.85 | T26: =F25*VLOOKUP('Cum. payments'!BS26,Exposure!$B$33:$C$53,2,FALSE)/VLOOKUP('Cum. payments'!BD26,Exposure!$B$33:$C$53,2,FALSE) -> 332302.9 | U26: =G25*VLOOKUP('Cum. payments'!BT26,Exposure!$B$33:$C$53,2,FALSE)/VLOOKUP('Cum. payments'!BE26,Exposure!$B$33:$C$53,2,FALSE) -> 196725.42 | V26: =H25*VLOOKUP('Cum. payments'!BU26,Exposure!$B$33:$C$53,2,FALSE)/VLOOKUP('Cum. payments'!BF26,Exposure!$B$33:$C$53,2,FALSE) -> 7157.8118 | W26: =I25*VLOOKUP('Cum. payments'!BV26,Exposure!$B$33:$C$53,2,FALSE)/VLOOKUP('Cum. payments'!BG26,Exposure!$B$33:$C$53,2,FALSE) -> 1790.1248 | X26: =J25*VLOOKUP('Cum. payments'!BW26,Exposure!$B$33:$C$53,2,FALSE)/VLOOKUP('Cum. payments'!BH26,Exposure!$B$33:$C$53,2,FALSE) -> 71.616037
A27: 43053 | B27: 6262683.1 | C27: 3434225.8 | D27: 2517863.4 | E27: 1619451.8 | F27: 1060192.9 | G27: 617432.95 | H27: 2255.1652 | I27: 1320.4281 | J27: 1086.2666 | O27: =YEAR($A26) -> 2017 | P27: =B26*VLOOKUP('Cum. payments'!BO27,Exposure!$B$33:$C$53,2,FALSE)/VLOOKUP('Cum. payments'!AZ27,Exposure!$B$33:$C$53,2,FALSE) -> 1448374.6 | Q27: =C26*VLOOKUP('Cum. payments'!BP27,Exposure!$B$33:$C$53,2,FALSE)/VLOOKUP('Cum. payments'!BA27,Exposure!$B$33:$C$53,2,FALSE) -> 4130520.6 | R27: =D26*VLOOKUP('Cum. payments'!BQ27,Exposure!$B$33:$C$53,2,FALSE)/VLOOKUP('Cum. payments'!BB27,Exposure!$B$33:$C$53,2,FALSE) -> 3502913.6 | S27: =E26*VLOOKUP('Cum. payments'!BR27,Exposure!$B$33:$C$53,2,FALSE)/VLOOKUP('Cum. payments'!BC27,Exposure!$B$33:$C$53,2,FALSE) -> 252943.88 | T27: =F26*VLOOKUP('Cum. payments'!BS27,Exposure!$B$33:$C$53,2,FALSE)/VLOOKUP('Cum. payments'!BD27,Exposure!$B$33:$C$53,2,FALSE) -> 178036.63 | U27: =G26*VLOOKUP('Cum. payments'!BT27,Exposure!$B$33:$C$53,2,FALSE)/VLOOKUP('Cum. payments'!BE27,Exposure!$B$33:$C$53,2,FALSE) -> 9078.8364 | V27: =H26*VLOOKUP('Cum. payments'!BU27,Exposure!$B$33:$C$53,2,FALSE)/VLOOKUP('Cum. payments'!BF27,Exposure!$B$33:$C$53,2,FALSE) -> 8418.2983 | W27: =I26*VLOOKUP('Cum. payments'!BV27,Exposure!$B$33:$C$53,2,FALSE)/VLOOKUP('Cum. payments'!BG27,Exposure!$B$33:$C$53,2,FALSE) -> 27.260103 | X27: =J26*VLOOKUP('Cum. payments'!BW27,Exposure!$B$33:$C$53,2,FALSE)/VLOOKUP('Cum. payments'!BH27,Exposure!$B$33:$C$53,2,FALSE) -> 0
A28: 43055 | B28: 1665077.8 | C28: 1427959.3 | D28: 1094132.2 | E28: 1199322.1 | F28: 25771.939 | G28: 20287.395 | H28: 23150.863 | I28: 22648.147 | J28: 18187.812 | O28: =YEAR($A27) -> 2017 | P28: =B27*VLOOKUP('Cum. payments'!BO28,Exposure!$B$33:$C$53,2,FALSE)/VLOOKUP('Cum. payments'!AZ28,Exposure!$B$33:$C$53,2,FALSE) -> 9704938.5 | Q28: =C27*VLOOKUP('Cum. payments'!BP28,Exposure!$B$33:$C$53,2,FALSE)/VLOOKUP('Cum. payments'!BA28,Exposure!$B$33:$C$53,2,FALSE) -> 5308880.1 | R28: =D27*VLOOKUP('Cum. payments'!BQ28,Exposure!$B$33:$C$53,2,FALSE)/VLOOKUP('Cum. payments'!BB28,Exposure!$B$33:$C$53,2,FALSE) -> 3905854.8 | S28: =E27*VLOOKUP('Cum. payments'!BR28,Exposure!$B$33:$C$53,2,FALSE)/VLOOKUP('Cum. payments'!BC28,Exposure!$B$33:$C$53,2,FALSE) -> 2538199.1 | T28: =F27*VLOOKUP('Cum. payments'!BS28,Exposure!$B$33:$C$53,2,FALSE)/VLOOKUP('Cum. payments'!BD28,Exposure!$B$33:$C$53,2,FALSE) -> 1651416.6 | U28: =G27*VLOOKUP('Cum. payments'!BT28,Exposure!$B$33:$C$53,2,FALSE)/VLOOKUP('Cum. payments'!BE28,Exposure!$B$33:$C$53,2,FALSE) -> 894393.47 | V28: =H27*VLOOKUP('Cum. payments'!BU28,Exposure!$B$33:$C$53,2,FALSE)/VLOOKUP('Cum. payments'!BF28,Exposure!$B$33:$C$53,2,FALSE) -> 3195.1795 | W28: =I27*VLOOKUP('Cum. payments'!BV28,Exposure!$B$33:$C$53,2,FALSE)/VLOOKUP('Cum. payments'!BG28,Exposure!$B$33:$C$53,2,FALSE) -> 1846.7884 | X28: =J27*VLOOKUP('Cum. payments'!BW28,Exposure!$B$33:$C$53,2,FALSE)/VLOOKUP('Cum. payments'!BH28,Exposure!$B$33:$C$53,2,FALSE) -> 1509.4794
A29: 43151 | B29: 2254908.9 | C29: 1580249.1 | D29: 1719247.2 | E29: 1378209.6 | F29: 122597.15 | G29: 84981.804 | H29: 73431.665 | I29: 67997.36 | O29: =YEAR($A28) -> 2017 | P29: =B28*VLOOKUP('Cum. payments'!BO29,Exposure!$B$33:$C$53,2,FALSE)/VLOOKUP('Cum. payments'!AZ29,Exposure!$B$33:$C$53,2,FALSE) -> 2580280.3 | Q29: =C28*VLOOKUP('Cum. payments'!BP29,Exposure!$B$33:$C$53,2,FALSE)/VLOOKUP('Cum. payments'!BA29,Exposure!$B$33:$C$53,2,FALSE) -> 2207445 | R29: =D28*VLOOKUP('Cum. payments'!BQ29,Exposure!$B$33:$C$53,2,FALSE)/VLOOKUP('Cum. payments'!BB29,Exposure!$B$33:$C$53,2,FALSE) -> 1697280.9 | S29: =E28*VLOOKUP('Cum. payments'!BR29,Exposure!$B$33:$C$53,2,FALSE)/VLOOKUP('Cum. payments'!BC29,Exposure!$B$33:$C$53,2,FALSE) -> 1879721.5 | T29: =F28*VLOOKUP('Cum. payments'!BS29,Exposure!$B$33:$C$53,2,FALSE)/VLOOKUP('Cum. payments'!BD29,Exposure!$B$33:$C$53,2,FALSE) -> 40143.833 | U29: =G28*VLOOKUP('Cum. payments'!BT29,Exposure!$B$33:$C$53,2,FALSE)/VLOOKUP('Cum. payments'!BE29,Exposure!$B$33:$C$53,2,FALSE) -> 29387.666 | V29: =H28*VLOOKUP('Cum. payments'!BU29,Exposure!$B$33:$C$53,2,FALSE)/VLOOKUP('Cum. payments'!BF29,Exposure!$B$33:$C$53,2,FALSE) -> 32800.774 | W29: =I28*VLOOKUP('Cum. payments'!BV29,Exposure!$B$33:$C$53,2,FALSE)/VLOOKUP('Cum. payments'!BG29,Exposure!$B$33:$C$53,2,FALSE) -> 31676.344 | X29: =J28*VLOOKUP('Cum. payments'!BW29,Exposure!$B$33:$C$53,2,FALSE)/VLOOKUP('Cum. payments'!BH29,Exposure!$B$33:$C$53,2,FALSE) -> 25273.838
A30: 43161 | B30: 997830.98 | C30: 1701646.2 | D30: 188664.07 | E30: 159806.72 | F30: 141107.82 | G30: 3587.795 | H30: 46.48588 | I30: 47.417407 | O30: =YEAR($A29) -> 2018 | P30: =B29*VLOOKUP('Cum. payments'!BO30,Exposure!$B$33:$C$53,2,FALSE)/VLOOKUP('Cum. payments'!AZ30,Exposure!$B$33:$C$53,2,FALSE) -> 3374448 | Q30: =C29*VLOOKUP('Cum. payments'!BP30,Exposure!$B$33:$C$53,2,FALSE)/VLOOKUP('Cum. payments'!BA30,Exposure!$B$33:$C$53,2,FALSE) -> 2373062.5 | R30: =D29*VLOOKUP('Cum. payments'!BQ30,Exposure!$B$33:$C$53,2,FALSE)/VLOOKUP('Cum. payments'!BB30,Exposure!$B$33:$C$53,2,FALSE) -> 2608529 | S30: =E29*VLOOKUP('Cum. payments'!BR30,Exposure!$B$33:$C$53,2,FALSE)/VLOOKUP('Cum. payments'!BC30,Exposure!$B$33:$C$53,2,FALSE) -> 2078196.9 | T30: =F29*VLOOKUP('Cum. payments'!BS30,Exposure!$B$33:$C$53,2,FALSE)/VLOOKUP('Cum. payments'!BD30,Exposure!$B$33:$C$53,2,FALSE) -> 171917.02 | U30: =G29*VLOOKUP('Cum. payments'!BT30,Exposure!$B$33:$C$53,2,FALSE)/VLOOKUP('Cum. payments'!BE30,Exposure!$B$33:$C$53,2,FALSE) -> 116558.12 | V30: =H29*VLOOKUP('Cum. payments'!BU30,Exposure!$B$33:$C$53,2,FALSE)/VLOOKUP('Cum. payments'!BF30,Exposure!$B$33:$C$53,2,FALSE) -> 99422.674 | W30: =I29*VLOOKUP('Cum. payments'!BV30,Exposure!$B$33:$C$53,2,FALSE)/VLOOKUP('Cum. payments'!BG30,Exposure!$B$33:$C$53,2,FALSE) -> 91470.801
A31: 43206 | B31: 1165857.2 | C31: 1735911 | D31: 161207.83 | E31: 173611.05 | F31: 41457.178 | G31: 22505.458 | H31: 17520.2 | I31: 11053.733 | O31: =YEAR($A30) -> 2018 | P31: =B30*VLOOKUP('Cum. payments'!BO31,Exposure!$B$33:$C$53,2,FALSE)/VLOOKUP('Cum. payments'!AZ31,Exposure!$B$33:$C$53,2,FALSE) -> 1493243.8 | Q31: =C30*VLOOKUP('Cum. payments'!BP31,Exposure!$B$33:$C$53,2,FALSE)/VLOOKUP('Cum. payments'!BA31,Exposure!$B$33:$C$53,2,FALSE) -> 2555364.7 | R31: =D30*VLOOKUP('Cum. payments'!BQ31,Exposure!$B$33:$C$53,2,FALSE)/VLOOKUP('Cum. payments'!BB31,Exposure!$B$33:$C$53,2,FALSE) -> 286250.68 | S31: =E30*VLOOKUP('Cum. payments'!BR31,Exposure!$B$33:$C$53,2,FALSE)/VLOOKUP('Cum. payments'!BC31,Exposure!$B$33:$C$53,2,FALSE) -> 240971.93 | T31: =F30*VLOOKUP('Cum. payments'!BS31,Exposure!$B$33:$C$53,2,FALSE)/VLOOKUP('Cum. payments'!BD31,Exposure!$B$33:$C$53,2,FALSE) -> 197874.39 | U31: =G30*VLOOKUP('Cum. payments'!BT31,Exposure!$B$33:$C$53,2,FALSE)/VLOOKUP('Cum. payments'!BE31,Exposure!$B$33:$C$53,2,FALSE) -> 4920.8961 | V31: =H30*VLOOKUP('Cum. payments'!BU31,Exposure!$B$33:$C$53,2,FALSE)/VLOOKUP('Cum. payments'!BF31,Exposure!$B$33:$C$53,2,FALSE) -> 62.939476 | W31: =I30*VLOOKUP('Cum. payments'!BV31,Exposure!$B$33:$C$53,2,FALSE)/VLOOKUP('Cum. payments'!BG31,Exposure!$B$33:$C$53,2,FALSE) -> 63.78642
A32: 43249 | B32: 714565 | C32: 1098681.2 | D32: 90109.923 | E32: 35503.229 | F32: 31459.719 | G32: 32754.352 | H32: 19460.589 | I32: 626.52982 | O32: =YEAR($A31) -> 2018 | P32: =B31*VLOOKUP('Cum. payments'!BO32,Exposure!$B$33:$C$53,2,FALSE)/VLOOKUP('Cum. payments'!AZ32,Exposure!$B$33:$C$53,2,FALSE) -> 1744693.4 | Q32: =C31*VLOOKUP('Cum. payments'!BP32,Exposure!$B$33:$C$53,2,FALSE)/VLOOKUP('Cum. payments'!BA32,Exposure!$B$33:$C$53,2,FALSE) -> 2606820.2 | R32: =D31*VLOOKUP('Cum. payments'!BQ32,Exposure!$B$33:$C$53,2,FALSE)/VLOOKUP('Cum. payments'!BB32,Exposure!$B$33:$C$53,2,FALSE) -> 244592.68 | S32: =E31*VLOOKUP('Cum. payments'!BR32,Exposure!$B$33:$C$53,2,FALSE)/VLOOKUP('Cum. payments'!BC32,Exposure!$B$33:$C$53,2,FALSE) -> 261787.42 | T32: =F31*VLOOKUP('Cum. payments'!BS32,Exposure!$B$33:$C$53,2,FALSE)/VLOOKUP('Cum. payments'!BD32,Exposure!$B$33:$C$53,2,FALSE) -> 58135.074 | U32: =G31*VLOOKUP('Cum. payments'!BT32,Exposure!$B$33:$C$53,2,FALSE)/VLOOKUP('Cum. payments'!BE32,Exposure!$B$33:$C$53,2,FALSE) -> 30867.711 | V32: =H31*VLOOKUP('Cum. payments'!BU32,Exposure!$B$33:$C$53,2,FALSE)/VLOOKUP('Cum. payments'!BF32,Exposure!$B$33:$C$53,2,FALSE) -> 23721.444 | W32: =I31*VLOOKUP('Cum. payments'!BV32,Exposure!$B$33:$C$53,2,FALSE)/VLOOKUP('Cum. payments'!BG32,Exposure!$B$33:$C$53,2,FALSE) -> 14869.604
A33: 43266 | B33: 292577.18 | C33: 581946.74 | D33: 516362.31 | E33: 24376.185 | F33: 20262.953 | G33: 23419.806 | H33: 16201.927 | I33: 388.65147 | O33: =YEAR($A32) -> 2018 | P33: =B32*VLOOKUP('Cum. payments'!BO33,Exposure!$B$33:$C$53,2,FALSE)/VLOOKUP('Cum. payments'!AZ33,Exposure!$B$33:$C$53,2,FALSE) -> 1069339.2 | Q33: =C32*VLOOKUP('Cum. payments'!BP33,Exposure!$B$33:$C$53,2,FALSE)/VLOOKUP('Cum. payments'!BA33,Exposure!$B$33:$C$53,2,FALSE) -> 1649891.2 | R33: =D32*VLOOKUP('Cum. payments'!BQ33,Exposure!$B$33:$C$53,2,FALSE)/VLOOKUP('Cum. payments'!BB33,Exposure!$B$33:$C$53,2,FALSE) -> 136719.34 | S33: =E32*VLOOKUP('Cum. payments'!BR33,Exposure!$B$33:$C$53,2,FALSE)/VLOOKUP('Cum. payments'!BC33,Exposure!$B$33:$C$53,2,FALSE) -> 53535.18 | T33: =F32*VLOOKUP('Cum. payments'!BS33,Exposure!$B$33:$C$53,2,FALSE)/VLOOKUP('Cum. payments'!BD33,Exposure!$B$33:$C$53,2,FALSE) -> 44115.717 | U33: =G32*VLOOKUP('Cum. payments'!BT33,Exposure!$B$33:$C$53,2,FALSE)/VLOOKUP('Cum. payments'!BE33,Exposure!$B$33:$C$53,2,FALSE) -> 44924.742 | V33: =H32*VLOOKUP('Cum. payments'!BU33,Exposure!$B$33:$C$53,2,FALSE)/VLOOKUP('Cum. payments'!BF33,Exposure!$B$33:$C$53,2,FALSE) -> 26348.63 | W33: =I32*VLOOKUP('Cum. payments'!BV33,Exposure!$B$33:$C$53,2,FALSE)/VLOOKUP('Cum. payments'!BG33,Exposure!$B$33:$C$53,2,FALSE) -> 842.81484
A34: 43306 | B34: 950221.75 | C34: 513537.33 | D34: 664241.38 | E34: 520157.27 | F34: 417085.2 | G34: 356762.47 | H34: 330893.61 | I34: 151895.55 | O34: =YEAR($A33) -> 2018 | P34: =B33*VLOOKUP('Cum. payments'!BO34,Exposure!$B$33:$C$53,2,FALSE)/VLOOKUP('Cum. payments'!AZ34,Exposure!$B$33:$C$53,2,FALSE) -> 437838.74 | Q34: =C33*VLOOKUP('Cum. payments'!BP34,Exposure!$B$33:$C$53,2,FALSE)/VLOOKUP('Cum. payments'!BA34,Exposure!$B$33:$C$53,2,FALSE) -> 873910.31 | R34: =D33*VLOOKUP('Cum. payments'!BQ34,Exposure!$B$33:$C$53,2,FALSE)/VLOOKUP('Cum. payments'!BB34,Exposure!$B$33:$C$53,2,FALSE) -> 783451.06 | S34: =E33*VLOOKUP('Cum. payments'!BR34,Exposure!$B$33:$C$53,2,FALSE)/VLOOKUP('Cum. payments'!BC34,Exposure!$B$33:$C$53,2,FALSE) -> 36756.754 | T34: =F33*VLOOKUP('Cum. payments'!BS34,Exposure!$B$33:$C$53,2,FALSE)/VLOOKUP('Cum. payments'!BD34,Exposure!$B$33:$C$53,2,FALSE) -> 28414.58 | U34: =G33*VLOOKUP('Cum. payments'!BT34,Exposure!$B$33:$C$53,2,FALSE)/VLOOKUP('Cum. payments'!BE34,Exposure!$B$33:$C$53,2,FALSE) -> 32121.8 | V34: =H33*VLOOKUP('Cum. payments'!BU34,Exposure!$B$33:$C$53,2,FALSE)/VLOOKUP('Cum. payments'!BF34,Exposure!$B$33:$C$53,2,FALSE) -> 21936.571 | W34: =I33*VLOOKUP('Cum. payments'!BV34,Exposure!$B$33:$C$53,2,FALSE)/VLOOKUP('Cum. payments'!BG34,Exposure!$B$33:$C$53,2,FALSE) -> 522.81826
A35: 43316 | B35: 2176556.3 | C35: 1599761.8 | D35: 443677.72 | E35: 299890.68 | F35: 11237.337 | G35: 7475.9079 | H35: 4051.6062 | I35: 14.399031 | O35: =YEAR($A34) -> 2018 | P35: =B34*VLOOKUP('Cum. payments'!BO35,Exposure!$B$33:$C$53,2,FALSE)/VLOOKUP('Cum. payments'!AZ35,Exposure!$B$33:$C$53,2,FALSE) -> 1421997.1 | Q35: =C34*VLOOKUP('Cum. payments'!BP35,Exposure!$B$33:$C$53,2,FALSE)/VLOOKUP('Cum. payments'!BA35,Exposure!$B$33:$C$53,2,FALSE) -> 771179.78 | R35: =D34*VLOOKUP('Cum. payments'!BQ35,Exposure!$B$33:$C$53,2,FALSE)/VLOOKUP('Cum. payments'!BB35,Exposure!$B$33:$C$53,2,FALSE) -> 1007820.7 | S35: =E34*VLOOKUP('Cum. payments'!BR35,Exposure!$B$33:$C$53,2,FALSE)/VLOOKUP('Cum. payments'!BC35,Exposure!$B$33:$C$53,2,FALSE) -> 784343.11 | T35: =F34*VLOOKUP('Cum. payments'!BS35,Exposure!$B$33:$C$53,2,FALSE)/VLOOKUP('Cum. payments'!BD35,Exposure!$B$33:$C$53,2,FALSE) -> 584875.29 | U35: =G34*VLOOKUP('Cum. payments'!BT35,Exposure!$B$33:$C$53,2,FALSE)/VLOOKUP('Cum. payments'!BE35,Exposure!$B$33:$C$53,2,FALSE) -> 489323.12 | V35: =H34*VLOOKUP('Cum. payments'!BU35,Exposure!$B$33:$C$53,2,FALSE)/VLOOKUP('Cum. payments'!BF35,Exposure!$B$33:$C$53,2,FALSE) -> 448012.82 | W35: =I34*VLOOKUP('Cum. payments'!BV35,Exposure!$B$33:$C$53,2,FALSE)/VLOOKUP('Cum. payments'!BG35,Exposure!$B$33:$C$53,2,FALSE) -> 204331.58
A36: 43333 | B36: 1192018.1 | C36: 2167928 | D36: 1383186.3 | E36: 1420198.1 | F36: 231917.56 | G36: 32993.552 | H36: 9197.5431 | I36: 1535.5831 | O36: =YEAR($A35) -> 2018 | P36: =B35*VLOOKUP('Cum. payments'!BO36,Exposure!$B$33:$C$53,2,FALSE)/VLOOKUP('Cum. payments'!AZ36,Exposure!$B$33:$C$53,2,FALSE) -> 3257194.2 | Q36: =C35*VLOOKUP('Cum. payments'!BP36,Exposure!$B$33:$C$53,2,FALSE)/VLOOKUP('Cum. payments'!BA36,Exposure!$B$33:$C$53,2,FALSE) -> 2402364.8 | R36: =D35*VLOOKUP('Cum. payments'!BQ36,Exposure!$B$33:$C$53,2,FALSE)/VLOOKUP('Cum. payments'!BB36,Exposure!$B$33:$C$53,2,FALSE) -> 673170.32 | S36: =E35*VLOOKUP('Cum. payments'!BR36,Exposure!$B$33:$C$53,2,FALSE)/VLOOKUP('Cum. payments'!BC36,Exposure!$B$33:$C$53,2,FALSE) -> 452203.98 | T36: =F35*VLOOKUP('Cum. payments'!BS36,Exposure!$B$33:$C$53,2,FALSE)/VLOOKUP('Cum. payments'!BD36,Exposure!$B$33:$C$53,2,FALSE) -> 15758.03 | U36: =G35*VLOOKUP('Cum. payments'!BT36,Exposure!$B$33:$C$53,2,FALSE)/VLOOKUP('Cum. payments'!BE36,Exposure!$B$33:$C$53,2,FALSE) -> 10253.698 | V36: =H35*VLOOKUP('Cum. payments'!BU36,Exposure!$B$33:$C$53,2,FALSE)/VLOOKUP('Cum. payments'!BF36,Exposure!$B$33:$C$53,2,FALSE) -> 5485.6651 | W36: =I35*VLOOKUP('Cum. payments'!BV36,Exposure!$B$33:$C$53,2,FALSE)/VLOOKUP('Cum. payments'!BG36,Exposure!$B$33:$C$53,2,FALSE) -> 19.369736
A37: 43356 | B37: 2985472.2 | C37: 1808443.2 | D37: 652270.04 | E37: 582543.77 | F37: 44950.39 | G37: 43134.116 | H37: 1674.951 | I37: 375.46325 | O37: =YEAR($A36) -> 2018 | P37: =B36*VLOOKUP('Cum. payments'!BO37,Exposure!$B$33:$C$53,2,FALSE)/VLOOKUP('Cum. payments'!AZ37,Exposure!$B$33:$C$53,2,FALSE) -> 1783842.9 | Q37: =C36*VLOOKUP('Cum. payments'!BP37,Exposure!$B$33:$C$53,2,FALSE)/VLOOKUP('Cum. payments'!BA37,Exposure!$B$33:$C$53,2,FALSE) -> 3255580.7 | R37: =D36*VLOOKUP('Cum. payments'!BQ37,Exposure!$B$33:$C$53,2,FALSE)/VLOOKUP('Cum. payments'!BB37,Exposure!$B$33:$C$53,2,FALSE) -> 2098640.3 | S37: =E36*VLOOKUP('Cum. payments'!BR37,Exposure!$B$33:$C$53,2,FALSE)/VLOOKUP('Cum. payments'!BC37,Exposure!$B$33:$C$53,2,FALSE) -> 2141511.2 | T37: =F36*VLOOKUP('Cum. payments'!BS37,Exposure!$B$33:$C$53,2,FALSE)/VLOOKUP('Cum. payments'!BD37,Exposure!$B$33:$C$53,2,FALSE) -> 325216.17 | U37: =G36*VLOOKUP('Cum. payments'!BT37,Exposure!$B$33:$C$53,2,FALSE)/VLOOKUP('Cum. payments'!BE37,Exposure!$B$33:$C$53,2,FALSE) -> 45252.82 | V37: =H36*VLOOKUP('Cum. payments'!BU37,Exposure!$B$33:$C$53,2,FALSE)/VLOOKUP('Cum. payments'!BF37,Exposure!$B$33:$C$53,2,FALSE) -> 12452.997 | W37: =I36*VLOOKUP('Cum. payments'!BV37,Exposure!$B$33:$C$53,2,FALSE)/VLOOKUP('Cum. payments'!BG37,Exposure!$B$33:$C$53,2,FALSE) -> 2065.6834
A38: 43365 | B38: 1606249.9 | C38: 1599158.1 | D38: 1222174.2 | E38: 628320.34 | F38: 104381.35 | G38: 4734.8999 | H38: 4271.0544 | I38: 3469.8253 | O38: =YEAR($A37) -> 2018 | P38: =B37*VLOOKUP('Cum. payments'!BO38,Exposure!$B$33:$C$53,2,FALSE)/VLOOKUP('Cum. payments'!AZ38,Exposure!$B$33:$C$53,2,FALSE) -> 4467728.6 | Q38: =C37*VLOOKUP('Cum. payments'!BP38,Exposure!$B$33:$C$53,2,FALSE)/VLOOKUP('Cum. payments'!BA38,Exposure!$B$33:$C$53,2,FALSE) -> 2715741.9 | R38: =D37*VLOOKUP('Cum. payments'!BQ38,Exposure!$B$33:$C$53,2,FALSE)/VLOOKUP('Cum. payments'!BB38,Exposure!$B$33:$C$53,2,FALSE) -> 989657.15 | S38: =E37*VLOOKUP('Cum. payments'!BR38,Exposure!$B$33:$C$53,2,FALSE)/VLOOKUP('Cum. payments'!BC38,Exposure!$B$33:$C$53,2,FALSE) -> 878415.48 | T38: =F37*VLOOKUP('Cum. payments'!BS38,Exposure!$B$33:$C$53,2,FALSE)/VLOOKUP('Cum. payments'!BD38,Exposure!$B$33:$C$53,2,FALSE) -> 63033.577 | U38: =G37*VLOOKUP('Cum. payments'!BT38,Exposure!$B$33:$C$53,2,FALSE)/VLOOKUP('Cum. payments'!BE38,Exposure!$B$33:$C$53,2,FALSE) -> 59161.269 | V38: =H37*VLOOKUP('Cum. payments'!BU38,Exposure!$B$33:$C$53,2,FALSE)/VLOOKUP('Cum. payments'!BF38,Exposure!$B$33:$C$53,2,FALSE) -> 2267.7969 | W38: =I37*VLOOKUP('Cum. payments'!BV38,Exposure!$B$33:$C$53,2,FALSE)/VLOOKUP('Cum. payments'!BG38,Exposure!$B$33:$C$53,2,FALSE) -> 505.07732
A39: 43388 | B39: 1093750.2 | C39: 1664181.1 | D39: 1062252.1 | E39: 218379.3 | F39: 26048.08 | G39: 3335.2077 | H39: 2928.033 | I39: 2474.0638 | O39: =YEAR($A38) -> 2018 | P39: =B38*VLOOKUP('Cum. payments'!BO39,Exposure!$B$33:$C$53,2,FALSE)/VLOOKUP('Cum. payments'!AZ39,Exposure!$B$33:$C$53,2,FALSE) -> 2403736.6 | Q39: =C38*VLOOKUP('Cum. payments'!BP39,Exposure!$B$33:$C$53,2,FALSE)/VLOOKUP('Cum. payments'!BA39,Exposure!$B$33:$C$53,2,FALSE) -> 2401458.2 | R39: =D38*VLOOKUP('Cum. payments'!BQ39,Exposure!$B$33:$C$53,2,FALSE)/VLOOKUP('Cum. payments'!BB39,Exposure!$B$33:$C$53,2,FALSE) -> 1854344.6 | S39: =E38*VLOOKUP('Cum. payments'!BR39,Exposure!$B$33:$C$53,2,FALSE)/VLOOKUP('Cum. payments'!BC39,Exposure!$B$33:$C$53,2,FALSE) -> 947441.78 | T39: =F38*VLOOKUP('Cum. payments'!BS39,Exposure!$B$33:$C$53,2,FALSE)/VLOOKUP('Cum. payments'!BD39,Exposure!$B$33:$C$53,2,FALSE) -> 146373.15 | U39: =G38*VLOOKUP('Cum. payments'!BT39,Exposure!$B$33:$C$53,2,FALSE)/VLOOKUP('Cum. payments'!BE39,Exposure!$B$33:$C$53,2,FALSE) -> 6494.2257 | V39: =H38*VLOOKUP('Cum. payments'!BU39,Exposure!$B$33:$C$53,2,FALSE)/VLOOKUP('Cum. payments'!BF39,Exposure!$B$33:$C$53,2,FALSE) -> 5782.7866 | W39: =I38*VLOOKUP('Cum. payments'!BV39,Exposure!$B$33:$C$53,2,FALSE)/VLOOKUP('Cum. payments'!BG39,Exposure!$B$33:$C$53,2,FALSE) -> 4667.6474
A40: 43466 | B40: 291807.23 | C40: 949225.38 | D40: 816915.37 | E40: 159574.16 | F40: 82142.194 | G40: 38607.439 | H40: 16609.464 | O40: =YEAR($A39) -> 2018 | P40: =B39*VLOOKUP('Cum. payments'!BO40,Exposure!$B$33:$C$53,2,FALSE)/VLOOKUP('Cum. payments'!AZ40,Exposure!$B$33:$C$53,2,FALSE) -> 1636785.9 | Q40: =C39*VLOOKUP('Cum. payments'!BP40,Exposure!$B$33:$C$53,2,FALSE)/VLOOKUP('Cum. payments'!BA40,Exposure!$B$33:$C$53,2,FALSE) -> 2499103.2 | R40: =D39*VLOOKUP('Cum. payments'!BQ40,Exposure!$B$33:$C$53,2,FALSE)/VLOOKUP('Cum. payments'!BB40,Exposure!$B$33:$C$53,2,FALSE) -> 1611702.7 | S40: =E39*VLOOKUP('Cum. payments'!BR40,Exposure!$B$33:$C$53,2,FALSE)/VLOOKUP('Cum. payments'!BC40,Exposure!$B$33:$C$53,2,FALSE) -> 329293.29 | T40: =F39*VLOOKUP('Cum. payments'!BS40,Exposure!$B$33:$C$53,2,FALSE)/VLOOKUP('Cum. payments'!BD40,Exposure!$B$33:$C$53,2,FALSE) -> 36527.018 | U40: =G39*VLOOKUP('Cum. payments'!BT40,Exposure!$B$33:$C$53,2,FALSE)/VLOOKUP('Cum. payments'!BE40,Exposure!$B$33:$C$53,2,FALSE) -> 4574.4561 | V40: =H39*VLOOKUP('Cum. payments'!BU40,Exposure!$B$33:$C$53,2,FALSE)/VLOOKUP('Cum. payments'!BF40,Exposure!$B$33:$C$53,2,FALSE) -> 3964.4052 | W40: =I39*VLOOKUP('Cum. payments'!BV40,Exposure!$B$33:$C$53,2,FALSE)/VLOOKUP('Cum. payments'!BG40,Exposure!$B$33:$C$53,2,FALSE) -> 3328.138
A41: 43485 | B41: 1609432.1 | C41: 1192672.2 | D41: 488353 | E41: 567564.14 | F41: 164722.15 | G41: 131407.57 | H41: 60295.94 | O41: =YEAR($A40) -> 2019 | P41: =B40*VLOOKUP('Cum. payments'!BO41,Exposure!$B$33:$C$53,2,FALSE)/VLOOKUP('Cum. payments'!AZ41,Exposure!$B$33:$C$53,2,FALSE) -> 424208.48 | Q41: =C40*VLOOKUP('Cum. payments'!BP41,Exposure!$B$33:$C$53,2,FALSE)/VLOOKUP('Cum. payments'!BA41,Exposure!$B$33:$C$53,2,FALSE) -> 1394204.1 | R41: =D40*VLOOKUP('Cum. payments'!BQ41,Exposure!$B$33:$C$53,2,FALSE)/VLOOKUP('Cum. payments'!BB41,Exposure!$B$33:$C$53,2,FALSE) -> 1192471.9 | S41: =E40*VLOOKUP('Cum. payments'!BR41,Exposure!$B$33:$C$53,2,FALSE)/VLOOKUP('Cum. payments'!BC41,Exposure!$B$33:$C$53,2,FALSE) -> 216621.09 | T41: =F40*VLOOKUP('Cum. payments'!BS41,Exposure!$B$33:$C$53,2,FALSE)/VLOOKUP('Cum. payments'!BD41,Exposure!$B$33:$C$53,2,FALSE) -> 109064.29 | U41: =G40*VLOOKUP('Cum. payments'!BT41,Exposure!$B$33:$C$53,2,FALSE)/VLOOKUP('Cum. payments'!BE41,Exposure!$B$33:$C$53,2,FALSE) -> 50602.589 | V41: =H40*VLOOKUP('Cum. payments'!BU41,Exposure!$B$33:$C$53,2,FALSE)/VLOOKUP('Cum. payments'!BF41,Exposure!$B$33:$C$53,2,FALSE) -> 21629.463
